Workbook
Name IQ_CH: 110000
Name IQ_CQ: 5000
Name IQ_CY: 10000
Name IQ_DAILY: 500000
Name IQ_FH: 100000
Name IQ_FQ: 500
Name IQ_FY: 1000
Name IQ_LTM: 2000
Name IQ_MONTH: 15000
Name IQ_NTM: 6000
Name IQ_WEEK: 50000
Name IQ_YTD: 3000

Sheet _CIQHiddenCacheSheet
A1: 88 | B1: BAABTAVMT0NBTAFI/////wFQzQEAABxDSVEuTUVUQS5JUV9QUklNQVJZX0lORFVTVFJZAQAAABfbPAEDAAAAHkludGVyYWN0aXZlIE1lZGlhIGFuZCBTZXJ2aWNlcwBX57SZ8QrfCMlh3JnxCt8IG0NJUS5NRVRBLklRX0lORFVTVFJZX1NFQ1RPUgEAAAAX2zwBAwAAABZDb21tdW5pY2F0aW9uIFNlcnZpY2VzAFfntJnxCt8IyWHcmfEK3wgYQ0lRLk1FVEEuSVFfQ09NUEFOWV9OQU1FAQAAABfbPAEDAAAAFE1ldGEgUGxhdGZvcm1zLCBJbmMuAFfntJnxCt8IyWHcmfEK3wgbQ0lRLk1FVEEuSVFfQ09NUEFOWV9BRERSRVNTAQAAABfbPAEDAAAAODEgTWV0YSBXYXksIE1lbmxvIFBhcmssIENhbGlmb3JuaWEsIDk0MDI1LCBVbml0ZWQgU3RhdGVzAFfntJnxCt8IyWHcmfEK3wgUQ0lRLk1FVEEuSVFfRVhDSEFOR0UBAAAAF9s8AQMAAAAITmFzZGFxR1MAV+e0mfEK3wjJYdyZ8QrfCBxDSVEuTUVUQS5JUV9QUklDRV9TQUxFUy4yMDAwAQAAABfbPAECAAAADzYuODMzODc0NDE1MzMzNQEHAAAABQAAAAExAQAAAAstMTg3OTk1Njk5MQMAAAABMAIAAAAFMzg5NTgEAAAAATAHAAAACDkvNC8yMDI2CAAAAAg5LzQvMjAyNlfntJnxCt8IyWHcmfEK3wgYQ0lRLk1FVEEuSVFfUEVfRVhDTC4yMDAwAQAAABfbPAECAAAAEDIzLjI0MTM2MDU3MDUwODIBBwAAAAUAAAABMQEAAAALLTE4Nzk5NTY5OTEDAAAAATACAAAABjEw | C1: MDA2NgQAAAABMAcAAAAIOS80LzIwMjYIAAAACDkvNC8yMDI2V+e0mfEK3wjJYdyZ8QrfCBNDSVEubWV0YS5JUV9ORVdTLjEwAQAAABfbPAEDAAAAQUludmVuZXJneSBzZWN1cmVzICQyMTVNIHRheCBlcXVpdHkgaW52ZXN0bWVudCBmb3IgT2hpbyBzb2xhciBmYXJtAQMAAAAFAAAAAjE3AQAAAAkzMjI3Mzk5ODMCAAAABDc3NzHhNbWZ8QrfCLgT3JnxCt8IE0NJUS5tZXRhLklRX05FV1MuMTEBAAAAF9s8AQMAAABGQXBwbGUgcGF5cyAkMTdCIGluIElyaXNoIHRheGVzOyBVYmVyIGZhY2VzIOKCrDgyNU0gZmluZSBpbiBOZXRoZXJsYW5kcwEDAAAABQAAAAIxNwEAAAAJMzIyNzM5OTI0AgAAAAQ3Nzcx4TW1mfEK3wi4E9yZ8QrfCBNDSVEubWV0YS5JUV9ORVdTLjEyAQAAABfbPAEDAAAAKlNvcm9zIHVwcyBleHBvc3VyZSB0byB1dGlsaXRpZXMgaW4gUTIgMjAyNgEDAAAABQAAAAIxNwEAAAAJMzIyNzM5ODc2AgAAAAQ3Nzcx4TW1mfEK3wi4E9yZ8QrfCBNDSVEubWV0YS5JUV9ORVdTLjE1AQAAABfbPAEDAAAAOFdpZGVyIFMmUCA1MDAgYnJlYWR0aCBmbGFzaGVzIHdhcm5pbmcgc2lnbiBmb3IgaW52ZXN0b3JzAQMAAAAFAAAAAjE3AQAAAAkzMjI3Mzk3OTgCAAAABDc3NzHhNbWZ8QrfCLgT3JnxCt8IE0NJUS5tZXRhLklRX05FV1MuMTcBAAAAF9s8AQMAAABLU2FnZSBHZW9zeXN0ZW1zIGhhcm5lc3NlcyBl | D1: YXJ0aCdzIHByZXNzdXJlIHRvIGdlbmVyYXRlIHBvd2VyIGZvciBUZXhhcyBncmlkAQMAAAAFAAAAAjE3AQAAAAkzMjI3Mzk3NDACAAAABDc3NzHhNbWZ8QrfCLgT3JnxCt8IE0NJUS5tZXRhLklRX05FV1MuMjIBAAAAF9s8AQMAAABJQnJvYWRjYXN0ZXJzIHB1cnN1ZSBNJkEgYXMgRkNDIGxpZnRzIG93bmVyc2hpcCBjYXA7IGRlYnQgY29uY2VybnMgcGVyc2lzdAEDAAAABQAAAAIxNwEAAAAJMzIyNzM5NDUwAgAAAAQ3Nzcx4TW1mfEK3wi4E9yZ8QrfCBNDSVEubWV0YS5JUV9ORVdTLjIzAQAAABfbPAEDAAAAT1RlbmNlbnQgdG8gYmVjb21lIGxhcmdlc3QgTWFudXMgc2hhcmVob2xkZXI7IExha2VycyBzYWxlIGZ1ZWxzIHNwb3J0cyBNJkEgc3VyZ2UBAwAAAAUAAAACMTcBAAAACTMyMjczOTQwMgIAAAAENzc3MeE1tZnxCt8IuBPcmfEK3wgZQ0lRQVZHLk1FVEEuSVFfVk9MVU1FLi0zTQEAAAAX2zwBAgAAABAxOC4wOTI2NzA5MjMwNzY5AFfntJnxCt8IyWHcmfEK3wggQ0lRLk1FVEEuSVFfUEVfRVhDTF9GV0RfQ0lRLjYwMDABAAAAF9s8AQIAAAAQMTkuMDU2NTIwNDA5MjAzNwENAAAABQAAAAE5AQAAAAkxMjY5MTAzMzcCAAAACTY1MjQyMjU0MwMAAAAGMTAwMzA5BAAAAAEyBgAAAAEwBwAAAAMxNjAIAAAAATAJAAAAATEKAAAAATALAAAACzE0OTM2OTkxOTY5DAAAAAIxMg0AAAAIOS81LzIwMjZgDrWZ | E1: 8QrfCMlh3JnxCt8IGENJUS5NRVRBLklRX1BFR19GV0QuNjAwMAEAAAAX2zwBAgAAABEwLjk4MDI5OTkwNTYxNDk0OQENAAAABQAAAAE5AQAAAAkxMjY5MTAzMzcCAAAACTY1MjQyMjU0MwMAAAAGMTAwMzExBAAAAAEyBgAAAAEwBwAAAAMxNjAIAAAAATAJAAAAATEKAAAAATALAAAACzE0OTM2OTkxOTY5DAAAAAIxMg0AAAAIOS81LzIwMjZgDrWZ8QrfCLU63JnxCt8IIUNJUS5NRVRBLklRX1BFX0VYQ0xfRldEX0NJUS4xMDAwMAEAAAAX2zwBAwAAAAAAYA61mfEK3wjJYdyZ8QrfCBxDSVEuTUVUQS5JUV9DQVNIX09QRVJfQ1MuOTk4AQAAABfbPAECAAAABTcxMTEzAQkAAAAFAAAAAjE5AQAAAAgyNzM5MjM3NQIAAAAFMzI4MjQJAAAAAi0xAwAAAAMxNjAGAAAACDIvMi8yMDI0BwAAAAg5LzQvMjAyNggAAAABMAQAAAABMOE1tZnxCt8ItTrcmfEK3wgdQ0lRLk1FVEEuSVFfQ0FTSF9PUEVSX0NTLjIwMDABAAAAF9s8AQIAAAAGMTMwMzAxAQkAAAAFAAAAAjE5AQAAAAgyOTk2NjY3NgIAAAAFMzI4MjQJAAAAAi0xAwAAAAMxNjAGAAAACTcvMzAvMjAyNgcAAAAIOS80LzIwMjYIAAAAATAEAAAAATDhNbWZ8QrfCLU63JnxCt8IHUNJUS5NRVRBLklRX0NBU0hfT1BFUl9DUy4xMDAwAQAAABfbPAECAAAABjExNTgwMAEJAAAABQAAAAIxOQEAAAAIMjk0NDQzMTUCAAAABTMyODI0CQAAAAItMQMAAAADMTYwBgAAAAkx | F1: LzI5LzIwMjYHAAAACDkvNC8yMDI2CAAAAAEwBAAAAAEw4TW1mfEK3wi1OtyZ8QrfCBxDSVEuTUVUQS5JUV9DQVNIX09QRVJfQ1MuOTk3AQAAABfbPAECAAAABTUwNDc1AQkAAAAFAAAAAjE5AQAAAAgyNjMyMzE1NwIAAAAFMzI4MjQJAAAAAi0xAwAAAAMxNjAGAAAACDIvMi8yMDIzBwAAAAg5LzQvMjAyNggAAAABMAQAAAABMOE1tZnxCt8ItTrcmfEK3wgeQ0lRLk1FVEEuSVFfRklMSU5HX0NVUlJFTkNZX0NTAQAAABfbPAEDAAAAA1VTRADhNbWZ8QrfCMlh3JnxCt8IHENJUS5NRVRBLklRX0NBU0hfT1BFUl9DUy45OTYBAAAAF9s8AQIAAAAFNTc2ODMBCQAAAAUAAAACMTkBAAAACDI1MjQxMzkyAgAAAAUzMjgyNAkAAAACLTEDAAAAAzE2MAYAAAAIMi8zLzIwMjIHAAAACDkvNC8yMDI2CAAAAAEwBAAAAAEw4TW1mfEK3wi1OtyZ8QrfCBxDSVEuTUVUQS5JUV9DQVNIX09QRVJfQ1MuOTk5AQAAABfbPAECAAAABTkxMzI4AQkAAAAFAAAAAjE5AQAAAAgyODQ0ODI2MQIAAAAFMzI4MjQJAAAAAi0xAwAAAAMxNjAGAAAACTEvMzAvMjAyNQcAAAAIOS80LzIwMjYIAAAAATAEAAAAATDhNbWZ8QrfCLU63JnxCt8IGkNJUS5NRVRBLklRX1RPVEFMX0RFQlQuOTk2AQAAABfbPAECAAAABTEzODczAQgAAAAFAAAAATEBAAAACy0yMDExODQzODA0AwAAAAMxNjACAAAABDQxNzMEAAAAATAHAAAACDkvNC8yMDI2CAAAAAox | G1: Mi8zMS8yMDIxCQAAAAEw4TW1mfEK3wi4E9yZ8QrfCBVDSVEuTUVUQS5JUV9DQVBFWC45OTYBAAAAF9s8AQIAAAAGLTE4NjkwAQgAAAAFAAAAATEBAAAACy0yMDExODQzODA0AwAAAAMxNjACAAAABDIwMjEEAAAAATAHAAAACDkvNC8yMDI2CAAAAAoxMi8zMS8yMDIxCQAAAAEwYA61mfEK3wi1OtyZ8QrfCB1DSVEuTUVUQS5JUV9UT1RBTF9BU1NFVFMuMjAwMAEAAAAX2zwBAgAAAAY0NDk5NTYBCAAAAAUAAAABMQEAAAALLTE4Nzk5NTY5OTEDAAAAAzE2MAIAAAAEMTAwNwQAAAABMAcAAAAIOS80LzIwMjYIAAAACTYvMzAvMjAyNgkAAAABMOE1tZnxCt8IuBPcmfEK3wgcQ0lRLk1FVEEuSVFfVE9UQUxfRVFVSVRZLjk5OAEAAAAX2zwBAgAAAAYxNTMxNjgBCAAAAAUAAAABMQEAAAALLTE5MDg1MTMzNTIDAAAAAzE2MAIAAAAEMTI3NQQAAAABMAcAAAAIOS80LzIwMjYIAAAACjEyLzMxLzIwMjMJAAAAATDhNbWZ8QrfCLgT3JnxCt8IH0NJUS5NRVRBLklRX0NBU0hfU1RfSU5WRVNULjEwMDABAAAAF9s8AQIAAAAFODE1OTIBCAAAAAUAAAABMQEAAAALLTE5MDg1MTMzNTMDAAAAAzE2MAIAAAAEMTAwMgQAAAABMAcAAAAIOS80LzIwMjYIAAAACjEyLzMxLzIwMjUJAAAAATDhNbWZ8QrfCLgT3JnxCt8IIUNJUS5NRVRBLklRX1RPVEFMX0RJVl9QQUlEX0NGLjk5NgEAAAAX2zwBAwAAAAAAYA61mfEK3wi4E9yZ8Qrf | H1: CBJDSVEuTUVUQS5JUV9OSS45OTkBAAAAF9s8AQIAAAAFNjIzNjABCAAAAAUAAAABMQEAAAALLTE5MDg1MTMzNDUDAAAAAzE2MAIAAAACMTUEAAAAATAHAAAACDkvNC8yMDI2CAAAAAoxMi8zMS8yMDI0CQAAAAEwYA61mfEK3wi1OtyZ8QrfCBNDSVEuTUVUQS5JUV9HUC4xMDAwAQAAABfbPAECAAAABjE2NDc5MQEIAAAABQAAAAExAQAAAAstMTkwODUxMzM1MwMAAAADMTYwAgAAAAIxMAQAAAABMAcAAAAIOS80LzIwMjYIAAAACjEyLzMxLzIwMjUJAAAAATBgDrWZ8QrfCLU63JnxCt8IHUNJUS5NRVRBLklRX1FVSUNLX1JBVElPLjEwMDAwAQAAABfbPAECAAAACDIuNDIyODE3AQgAAAAFAAAAATEBAAAACy0xOTA4NTExNTAwAwAAAAMxNjACAAAABDQxMjEEAAAAATAHAAAACDkvNC8yMDI2CAAAAAoxMi8zMS8yMDI1CQAAAAEwYA61mfEK3wi1OtyZ8QrfCB5DSVEuTUVUQS5JUV9DQVNIX1NUX0lOVkVTVC45OTkBAAAAF9s8AQIAAAAFNzc4MTUBCAAAAAUAAAABMQEAAAALLTE5MDg1MTMzNDUDAAAAAzE2MAIAAAAEMTAwMgQAAAABMAcAAAAIOS80LzIwMjYIAAAACjEyLzMxLzIwMjQJAAAAATDhNbWZ8QrfCLgT3JnxCt8IEkNJUS5NRVRBLklRX05JLjk5OAEAAAAX2zwBAgAAAAUzOTA5OAEIAAAABQAAAAExAQAAAAstMTkwODUxMzM1MgMAAAADMTYwAgAAAAIxNQQAAAABMAcAAAAIOS80LzIwMjYIAAAACjEyLzMx | I1: LzIwMjMJAAAAATBgDrWZ8QrfCLU63JnxCt8IEkNJUS5NRVRBLklRX0dQLjk5OQEAAAAX2zwBAgAAAAYxMzQzNDABCAAAAAUAAAABMQEAAAALLTE5MDg1MTMzNDUDAAAAAzE2MAIAAAACMTAEAAAAATAHAAAACDkvNC8yMDI2CAAAAAoxMi8zMS8yMDI0CQAAAAEwYA61mfEK3wi1OtyZ8QrfCBxDSVEuTUVUQS5JUV9UT1RBTF9FUVVJVFkuOTk2AQAAABfbPAECAAAABjEyNDg3OQEIAAAABQAAAAExAQAAAAstMjAxMTg0MzgwNAMAAAADMTYwAgAAAAQxMjc1BAAAAAEwBwAAAAg5LzQvMjAyNggAAAAKMTIvMzEvMjAyMQkAAAABMOE1tZnxCt8IuBPcmfEK3wgZQ0lRLk1FVEEuSVFfT1BFUl9JTkMuMjAwMAEAAAAX2zwBAgAAAAU4NjkyNgEIAAAABQAAAAExAQAAAAstMTg3OTk1Njk5MQMAAAADMTYwAgAAAAIyMQQAAAABMAcAAAAIOS80LzIwMjYIAAAACTYvMzAvMjAyNgkAAAABMGAOtZnxCt8ItTrcmfEK3wgeQ0lRLk1FVEEuSVFfQ0FTSF9TVF9JTlZFU1QuOTk3AQAAABfbPAECAAAABTQwNzM4AQgAAAAFAAAAATEBAAAACy0xOTYxNDkxNzMyAwAAAAMxNjACAAAABDEwMDIEAAAAATAHAAAACDkvNC8yMDI2CAAAAAoxMi8zMS8yMDIyCQAAAAEw4TW1mfEK3wi4E9yZ8QrfCBJDSVEuTUVUQS5JUV9HUC45OTYBAAAAF9s8AQIAAAAFOTUyODABCAAAAAUAAAABMQEAAAALLTIwMTE4NDM4MDQDAAAAAzE2MAIAAAACMTAE | J1: AAAAATAHAAAACDkvNC8yMDI2CAAAAAoxMi8zMS8yMDIxCQAAAAEwYA61mfEK3wi1OtyZ8QrfCBpDSVEuTUVUQS5JUV9DT01NT05fUkVQLjk5OQEAAAAX2zwBAgAAAAYtNDM4OTUBCAAAAAUAAAABMQEAAAALLTE5MDg1MTMzNDUDAAAAAzE2MAIAAAAEMjE2NAQAAAABMAcAAAAIOS80LzIwMjYIAAAACjEyLzMxLzIwMjQJAAAAATBgDrWZ8QrfCLgT3JnxCt8IHENJUS5NRVRBLklRX1RPVEFMX0VRVUlUWS45OTcBAAAAF9s8AQIAAAAGMTI1NzEzAQgAAAAFAAAAATEBAAAACy0xOTYxNDkxNzMyAwAAAAMxNjACAAAABDEyNzUEAAAAATAHAAAACDkvNC8yMDI2CAAAAAoxMi8zMS8yMDIyCQAAAAEw4TW1mfEK3wi4E9yZ8QrfCB9DSVEuTUVUQS5JUV9DVVJSRU5UX1JBVElPLjEwMDAwAQAAABfbPAECAAAACDIuNTk4NzY2AQgAAAAFAAAAATEBAAAACy0xOTA4NTExNTAwAwAAAAMxNjACAAAABDQwMzAEAAAAATAHAAAACDkvNC8yMDI2CAAAAAoxMi8zMS8yMDI1CQAAAAEwYA61mfEK3wi1OtyZ8QrfCB5DSVEuTUVUQS5JUV9DQVNIX1NUX0lOVkVTVC45OTgBAAAAF9s8AQIAAAAFNjU0MDMBCAAAAAUAAAABMQEAAAALLTE5MDg1MTMzNTIDAAAAAzE2MAIAAAAEMTAwMgQAAAABMAcAAAAIOS80LzIwMjYIAAAACjEyLzMxLzIwMjMJAAAAATDhNbWZ8QrfCLgT3JnxCt8IEkNJUS5NRVRBLklRX05JLjk5NwEAAAAX2zwBAgAA | K1: AAUyMzIwMAEIAAAABQAAAAExAQAAAAstMTk2MTQ5MTczMgMAAAADMTYwAgAAAAIxNQQAAAABMAcAAAAIOS80LzIwMjYIAAAACjEyLzMxLzIwMjIJAAAAATBgDrWZ8QrfCLU63JnxCt8IEkNJUS5NRVRBLklRX0dQLjk5OAEAAAAX2zwBAgAAAAYxMDg5NDMBCAAAAAUAAAABMQEAAAALLTE5MDg1MTMzNTIDAAAAAzE2MAIAAAACMTAEAAAAATAHAAAACDkvNC8yMDI2CAAAAAoxMi8zMS8yMDIzCQAAAAEwYA61mfEK3wi1OtyZ8QrfCCJDSVEuTUVUQS5JUV9UT1RBTF9ERUJUX0VRVUlUWS41MDAwAQAAABfbPAECAAAABzQyLjk5NzMBCAAAAAUAAAABMQEAAAALLTE4Nzk5NTkwOTIDAAAAAzE2MAIAAAAENDAzNAQAAAABMAcAAAAIOS80LzIwMjYIAAAACTYvMzAvMjAyNgkAAAABMGAOtZnxCt8ItTrcmfEK3wgSQ0lRLk1FVEEuSVFfR1AuOTk3AQAAABfbPAECAAAABTkyODU1AQgAAAAFAAAAATEBAAAACy0xOTYxNDkxNzMyAwAAAAMxNjACAAAAAjEwBAAAAAEwBwAAAAg5LzQvMjAyNggAAAAKMTIvMzEvMjAyMgkAAAABMGAOtZnxCt8ItTrcmfEK3wgYQ0lRLk1FVEEuSVFfT1BFUl9JTkMuOTk4AQAAABfbPAECAAAABTQ2NzUxAQgAAAAFAAAAATEBAAAACy0xOTA4NTEzMzUyAwAAAAMxNjACAAAAAjIxBAAAAAEwBwAAAAg5LzQvMjAyNggAAAAKMTIvMzEvMjAyMwkAAAABMGAOtZnxCt8ItTrcmfEK3wgbQ0lRLk1FVEEu | L1: SVFfQ09NTU9OX1JFUC4xMDAwAQAAABfbPAECAAAABi00NDY0OAEIAAAABQAAAAExAQAAAAstMTkwODUxMzM1MwMAAAADMTYwAgAAAAQyMTY0BAAAAAEwBwAAAAg5LzQvMjAyNggAAAAKMTIvMzEvMjAyNQkAAAABMGAOtZnxCt8IuBPcmfEK3wgfQ0lRLk1FVEEuSVFfU1RPQ0tfQkFTRURfQ0YuMjAwMAEAAAAX2zwBAgAAAAUyNTEzNgEIAAAABQAAAAExAQAAAAstMTg3OTk1Njk5MQMAAAADMTYwAgAAAAQyMTI3BAAAAAEwBwAAAAg5LzQvMjAyNggAAAAJNi8zMC8yMDI2CQAAAAEwYA61mfEK3wi4E9yZ8QrfCB1DSVEuTUVUQS5JUV9ESUxVVF9XRUlHSFQuMTAwMAEAAAAX2zwBAgAAAAQyNTc0AOE1tZnxCt8IuBPcmfEK3wgdQ0lRLk1FVEEuSVFfVE9UQUxfQVNTRVRTLjEwMDABAAAAF9s8AQIAAAAGMzY2MDIxAQgAAAAFAAAAATEBAAAACy0xOTA4NTEzMzUzAwAAAAMxNjACAAAABDEwMDcEAAAAATAHAAAACDkvNC8yMDI2CAAAAAoxMi8zMS8yMDI1CQAAAAEw4TW1mfEK3wi4E9yZ8QrfCBpDSVEuTUVUQS5JUV9DT01NT05fUkVQLjk5OAEAAAAX2zwBAgAAAAYtMjY3ODYBCAAAAAUAAAABMQEAAAALLTE5MDg1MTMzNTIDAAAAAzE2MAIAAAAEMjE2NAQAAAABMAcAAAAIOS80LzIwMjYIAAAACjEyLzMxLzIwMjMJAAAAATBgDrWZ8QrfCLgT3JnxCt8IH0NJUS5NRVRBLklRX1NUT0NLX0JBU0VEX0NGLjEwMDABAAAA | M1: F9s8AQIAAAAFMjA0MjcBCAAAAAUAAAABMQEAAAALLTE5MDg1MTMzNTMDAAAAAzE2MAIAAAAEMjEyNwQAAAABMAcAAAAIOS80LzIwMjYIAAAACjEyLzMxLzIwMjUJAAAAATBgDrWZ8QrfCLgT3JnxCt8IFkNJUS5NRVRBLklRX0VCSVREQS45OTgBAAAAF9s8AQIAAAAFNTc5MjkBCAAAAAUAAAABMQEAAAALLTE5MDg1MTMzNTIDAAAAAzE2MAIAAAAENDA1MQQAAAABMAcAAAAIOS80LzIwMjYIAAAACjEyLzMxLzIwMjMJAAAAATBgDrWZ8QrfCLU63JnxCt8IGUNJUS5NRVRBLklRX1RPVEFMX1JFVi45OTkBAAAAF9s8AQIAAAAGMTY0NTAxAQgAAAAFAAAAATEBAAAACy0xOTA4NTEzMzQ1AwAAAAMxNjACAAAAAjI4BAAAAAEwBwAAAAg5LzQvMjAyNggAAAAKMTIvMzEvMjAyNAkAAAABMGAOtZnxCt8ItTrcmfEK3wgdQ0lRLk1FVEEuSVFfRElMVVRfV0VJR0hULjIwMDABAAAAF9s8AQIAAAAGMjU2Ni41AOE1tZnxCt8IuBPcmfEK3wgaQ0lRLk1FVEEuSVFfVE9UQUxfUkVWLjEwMDABAAAAF9s8AQIAAAAGMjAwOTY2AQgAAAAFAAAAATEBAAAACy0xOTA4NTEzMzUzAwAAAAMxNjACAAAAAjI4BAAAAAEwBwAAAAg5LzQvMjAyNggAAAAKMTIvMzEvMjAyNQkAAAABMGAOtZnxCt8ItTrcmfEK3wgcQ0lRLk1FVEEuSVFfRElMVVRfV0VJR0hULjk5OQEAAAAX2zwBAgAAAAQyNjE0AOE1tZnxCt8IuBPcmfEK3wgcQ0lRLk1FVEEu | N1: SVFfVE9UQUxfQVNTRVRTLjk5OQEAAAAX2zwBAgAAAAYyNzYwNTQBCAAAAAUAAAABMQEAAAALLTE5MDg1MTMzNDUDAAAAAzE2MAIAAAAEMTAwNwQAAAABMAcAAAAIOS80LzIwMjYIAAAACjEyLzMxLzIwMjQJAAAAATDhNbWZ8QrfCLgT3JnxCt8IG0NJUS5NRVRBLklRX1RPVEFMX0RFQlQuMjAwMAEAAAAX2zwBAgAAAAYxMTIzMTgBCAAAAAUAAAABMQEAAAALLTE4Nzk5NTY5OTEDAAAAAzE2MAIAAAAENDE3MwQAAAABMAcAAAAIOS80LzIwMjYIAAAACTYvMzAvMjAyNgkAAAABMOE1tZnxCt8IuBPcmfEK3wgaQ0lRLk1FVEEuSVFfQ09NTU9OX1JFUC45OTcBAAAAF9s8AQIAAAAGLTMxNTUxAQgAAAAFAAAAATEBAAAACy0xOTYxNDkxNzMyAwAAAAMxNjACAAAABDIxNjQEAAAAATAHAAAACDkvNC8yMDI2CAAAAAoxMi8zMS8yMDIyCQAAAAEwYA61mfEK3wi4E9yZ8QrfCB5DSVEuTUVUQS5JUV9TVE9DS19CQVNFRF9DRi45OTkBAAAAF9s8AQIAAAAFMTY2OTABCAAAAAUAAAABMQEAAAALLTE5MDg1MTMzNDUDAAAAAzE2MAIAAAAEMjEyNwQAAAABMAcAAAAIOS80LzIwMjYIAAAACjEyLzMxLzIwMjQJAAAAATBgDrWZ8QrfCLgT3JnxCt8IFkNJUS5NRVRBLklRX0VCSVREQS45OTcBAAAAF9s8AQIAAAAFNDIyNDEBCAAAAAUAAAABMQEAAAALLTE5NjE0OTE3MzIDAAAAAzE2MAIAAAAENDA1MQQAAAABMAcAAAAIOS80LzIw | O1: MjYIAAAACjEyLzMxLzIwMjIJAAAAATBgDrWZ8QrfCLU63JnxCt8IGUNJUS5NRVRBLklRX1RPVEFMX1JFVi45OTgBAAAAF9s8AQIAAAAGMTM0OTAyAQgAAAAFAAAAATEBAAAACy0xOTA4NTEzMzUyAwAAAAMxNjACAAAAAjI4BAAAAAEwBwAAAAg5LzQvMjAyNggAAAAKMTIvMzEvMjAyMwkAAAABMGAOtZnxCt8ItTrcmfEK3wgVQ0lRLk1FVEEuSVFfQ0FQRVguOTk4AQAAABfbPAECAAAABi0yNzA0NQEIAAAABQAAAAExAQAAAAstMTkwODUxMzM1MgMAAAADMTYwAgAAAAQyMDIxBAAAAAEwBwAAAAg5LzQvMjAyNggAAAAKMTIvMzEvMjAyMwkAAAABMGAOtZnxCt8ItTrcmfEK3wgVQ0lRLk1FVEEuSVFfQ0FQRVguOTk3AQAAABfbPAECAAAABi0zMTE4NgEIAAAABQAAAAExAQAAAAstMTk2MTQ5MTczMgMAAAADMTYwAgAAAAQyMDIxBAAAAAEwBwAAAAg5LzQvMjAyNggAAAAKMTIvMzEvMjAyMgkAAAABMGAOtZnxCt8ItTrcmfEK3wghQ0lRLk1FVEEuSVFfVE9UQUxfRElWX1BBSURfQ0YuOTk3AQAAABfbPAEDAAAAAABgDrWZ8QrfCLgT3JnxCt8IGUNJUS5NRVRBLklRX0VCSVRfSU5ULjIwMDABAAAAF9s8AQIAAAAJNDIuODQxNzkzAQgAAAAFAAAAATEBAAAACy0xODc5OTU2OTkxAwAAAAMxNjACAAAABDQxODkEAAAAATAHAAAACDkvNC8yMDI2CAAAAAk2LzMwLzIwMjYJAAAAATBgDrWZ8QrfCLU63JnxCt8IEkNJUS5N | P1: RVRBLklRX05JLjk5NgEAAAAX2zwBAgAAAAUzOTM3MAEIAAAABQAAAAExAQAAAAstMjAxMTg0MzgwNAMAAAADMTYwAgAAAAIxNQQAAAABMAcAAAAIOS80LzIwMjYIAAAACjEyLzMxLzIwMjEJAAAAATBgDrWZ8QrfCLU63JnxCt8IGENJUS5NRVRBLklRX09QRVJfSU5DLjk5OQEAAAAX2zwBAgAAAAU2OTM4MAEIAAAABQAAAAExAQAAAAstMTkwODUxMzM0NQMAAAADMTYwAgAAAAIyMQQAAAABMAcAAAAIOS80LzIwMjYIAAAACjEyLzMxLzIwMjQJAAAAATBgDrWZ8QrfCLU63JnxCt8IGENJUS5NRVRBLklRX09QRVJfSU5DLjk5NwEAAAAX2zwBAgAAAAUzMzU1NQEIAAAABQAAAAExAQAAAAstMTk2MTQ5MTczMgMAAAADMTYwAgAAAAIyMQQAAAABMAcAAAAIOS80LzIwMjYIAAAACjEyLzMxLzIwMjIJAAAAATBgDrWZ8QrfCLU63JnxCt8IFkNJUS5NRVRBLklRX0VCSVREQS45OTkBAAAAF9s8AQIAAAAFODQ4MjABCAAAAAUAAAABMQEAAAALLTE5MDg1MTMzNDUDAAAAAzE2MAIAAAAENDA1MQQAAAABMAcAAAAIOS80LzIwMjYIAAAACjEyLzMxLzIwMjQJAAAAATBgDrWZ8QrfCLU63JnxCt8IHENJUS5NRVRBLklRX0RJTFVUX1dFSUdIVC45OTgBAAAAF9s8AQIAAAAEMjYyOQDhNbWZ8QrfCLgT3JnxCt8IHENJUS5NRVRBLklRX1RPVEFMX0FTU0VUUy45OTgBAAAAF9s8AQIAAAAGMjI5NjIzAQgAAAAFAAAAATEBAAAACy0x | Q1: OTA4NTEzMzUyAwAAAAMxNjACAAAABDEwMDcEAAAAATAHAAAACDkvNC8yMDI2CAAAAAoxMi8zMS8yMDIzCQAAAAEw4TW1mfEK3wi4E9yZ8QrfCBtDSVEuTUVUQS5JUV9UT1RBTF9ERUJULjEwMDABAAAAF9s8AQIAAAAFODUwODEBCAAAAAUAAAABMQEAAAALLTE5MDg1MTMzNTMDAAAAAzE2MAIAAAAENDE3MwQAAAABMAcAAAAIOS80LzIwMjYIAAAACjEyLzMxLzIwMjUJAAAAATDhNbWZ8QrfCLgT3JnxCt8IGkNJUS5NRVRBLklRX0NPTU1PTl9SRVAuOTk2AQAAABfbPAECAAAABi01MDA1MgEIAAAABQAAAAExAQAAAAstMjAxMTg0MzgwNAMAAAADMTYwAgAAAAQyMTY0BAAAAAEwBwAAAAg5LzQvMjAyNggAAAAKMTIvMzEvMjAyMQkAAAABMGAOtZnxCt8IuBPcmfEK3wgeQ0lRLk1FVEEuSVFfU1RPQ0tfQkFTRURfQ0YuOTk4AQAAABfbPAECAAAABTE0MDI3AQgAAAAFAAAAATEBAAAACy0xOTA4NTEzMzUyAwAAAAMxNjACAAAABDIxMjcEAAAAATAHAAAACDkvNC8yMDI2CAAAAAoxMi8zMS8yMDIzCQAAAAEwYA61mfEK3wi1OtyZ8QrfCBZDSVEuTUVUQS5JUV9DQVBFWC4yMDAwAQAAABfbPAECAAAABi04OTMyNQEIAAAABQAAAAExAQAAAAstMTg3OTk1Njk5MQMAAAADMTYwAgAAAAQyMDIxBAAAAAEwBwAAAAg5LzQvMjAyNggAAAAJNi8zMC8yMDI2CQAAAAEwYA61mfEK3wi4E9yZ8QrfCBZDSVEuTUVUQS5JUV9FQklU | R1: REEuOTk2AQAAABfbPAECAAAABTU0NzIwAQgAAAAFAAAAATEBAAAACy0yMDExODQzODA0AwAAAAMxNjACAAAABDQwNTEEAAAAATAHAAAACDkvNC8yMDI2CAAAAAoxMi8zMS8yMDIxCQAAAAEwYA61mfEK3wi1OtyZ8QrfCBlDSVEuTUVUQS5JUV9UT1RBTF9SRVYuOTk3AQAAABfbPAECAAAABjExNjYwOQEIAAAABQAAAAExAQAAAAstMTk2MTQ5MTczMgMAAAADMTYwAgAAAAIyOAQAAAABMAcAAAAIOS80LzIwMjYIAAAACjEyLzMxLzIwMjIJAAAAATBgDrWZ8QrfCLU63JnxCt8IHENJUS5NRVRBLklRX0RJTFVUX1dFSUdIVC45OTYBAAAAF9s8AQIAAAAEMjg1OQDhNbWZ8QrfCLgT3JnxCt8IHENJUS5NRVRBLklRX1RPVEFMX0FTU0VUUy45OTYBAAAAF9s8AQIAAAAGMTY1OTg3AQgAAAAFAAAAATEBAAAACy0yMDExODQzODA0AwAAAAMxNjACAAAABDEwMDcEAAAAATAHAAAACDkvNC8yMDI2CAAAAAoxMi8zMS8yMDIxCQAAAAEw4TW1mfEK3wi4E9yZ8QrfCBpDSVEuTUVUQS5JUV9UT1RBTF9ERUJULjk5OAEAAAAX2zwBAgAAAAUzNzIzNAEIAAAABQAAAAExAQAAAAstMTkwODUxMzM1MgMAAAADMTYwAgAAAAQ0MTczBAAAAAEwBwAAAAg5LzQvMjAyNggAAAAKMTIvMzEvMjAyMwkAAAABMOE1tZnxCt8IuBPcmfEK3wgiQ0lRLk1FVEEuSVFfVE9UQUxfRElWX1BBSURfQ0YuMTAwMAEAAAAX2zwBAgAAAAUtNTMyNAEIAAAA | S1: BQAAAAExAQAAAAstMTkwODUxMzM1MwMAAAADMTYwAgAAAAQyMDIyBAAAAAEwBwAAAAg5LzQvMjAyNggAAAAKMTIvMzEvMjAyNQkAAAABMGAOtZnxCt8IuBPcmfEK3wgeQ0lRLk1FVEEuSVFfU1RPQ0tfQkFTRURfQ0YuOTk2AQAAABfbPAECAAAABDkxNjQBCAAAAAUAAAABMQEAAAALLTIwMTE4NDM4MDQDAAAAAzE2MAIAAAAEMjEyNwQAAAABMAcAAAAIOS80LzIwMjYIAAAACjEyLzMxLzIwMjEJAAAAATBgDrWZ8QrfCLgT3JnxCt8IJUNJUS5NRVRBLklRX1NIT1JUX0lOVEVSRVNUX09WRVJfRkxPQVQBAAAAF9s8AQIAAAAGMS4yNzM5AGAOtZnxCt8ItTrcmfEK3wgdQ0lRLk1FVEEuSVFfVE9UQUxfRVFVSVRZLjIwMDABAAAAF9s8AQIAAAAGMjYxMjIxAQgAAAAFAAAAATEBAAAACy0xODc5OTU2OTkxAwAAAAMxNjACAAAABDEyNzUEAAAAATAHAAAACDkvNC8yMDI2CAAAAAk2LzMwLzIwMjYJAAAAATDhNbWZ8QrfCLgT3JnxCt8IIUNJUS5NRVRBLklRX1RPVEFMX0RJVl9QQUlEX0NGLjk5OQEAAAAX2zwBAgAAAAUtNTA3MgEIAAAABQAAAAExAQAAAAstMTkwODUxMzM0NQMAAAADMTYwAgAAAAQyMDIyBAAAAAEwBwAAAAg5LzQvMjAyNggAAAAKMTIvMzEvMjAyNAkAAAABMGAOtZnxCt8IuBPcmfEK3wghQ0lRLk1FVEEuSVFfVE9UQUxfRElWX1BBSURfQ0YuOTk4AQAAABfbPAEDAAAAAABgDrWZ8QrfCLgT3JnxCt8I | T1: GUNJUS5NRVRBLklRX0dXX0lOVEFOLjUwMDABAAAAF9s8AQIAAAAFMjM0MDYBCAAAAAUAAAABMQEAAAALLTE4Nzk5NTkwOTIDAAAAAzE2MAIAAAAFMzUzODEEAAAAATAHAAAACDkvNC8yMDI2CAAAAAk2LzMwLzIwMjYJAAAAATBgDrWZ8QrfCLU63JnxCt8IH0NJUS5NRVRBLklRX0NBU0hfU1RfSU5WRVNULjIwMDABAAAAF9s8AQIAAAAFOTAyNjABCAAAAAUAAAABMQEAAAALLTE4Nzk5NTY5OTEDAAAAAzE2MAIAAAAEMTAwMgQAAAABMAcAAAAIOS80LzIwMjYIAAAACTYvMzAvMjAyNgkAAAABMOE1tZnxCt8IuBPcmfEK3wgeQ0lRLk1FVEEuSVFfQ0FTSF9TVF9JTlZFU1QuOTk2AQAAABfbPAECAAAABTQ3OTk4AQgAAAAFAAAAATEBAAAACy0yMDExODQzODA0AwAAAAMxNjACAAAABDEwMDIEAAAAATAHAAAACDkvNC8yMDI2CAAAAAoxMi8zMS8yMDIxCQAAAAEwYA61mfEK3wi4E9yZ8QrfCBpDSVEuTUVUQS5JUV9UT1RBTF9SRVYuMjAwMAEAAAAX2zwBAgAAAAYyMjgyNDcBCAAAAAUAAAABMQEAAAALLTE4Nzk5NTY5OTEDAAAAAzE2MAIAAAACMjgEAAAAATAHAAAACDkvNC8yMDI2CAAAAAk2LzMwLzIwMjYJAAAAATBgDrWZ8QrfCLU63JnxCt8IHENJUS5NRVRBLklRX0RJTFVUX1dFSUdIVC45OTcBAAAAF9s8AQIAAAAEMjcwMgDhNbWZ8QrfCLgT3JnxCt8IHENJUS5NRVRBLklRX1RPVEFMX0FTU0VUUy45OTcBAAAA | U1: F9s8AQIAAAAGMTg1NzI3AQgAAAAFAAAAATEBAAAACy0xOTYxNDkxNzMyAwAAAAMxNjACAAAABDEwMDcEAAAAATAHAAAACDkvNC8yMDI2CAAAAAoxMi8zMS8yMDIyCQAAAAEw4TW1mfEK3wi4E9yZ8QrfCBpDSVEuTUVUQS5JUV9UT1RBTF9ERUJULjk5OQEAAAAX2zwBAgAAAAU0OTA2MAEIAAAABQAAAAExAQAAAAstMTkwODUxMzM0NQMAAAADMTYwAgAAAAQ0MTczBAAAAAEwBwAAAAg5LzQvMjAyNggAAAAKMTIvMzEvMjAyNAkAAAABMOE1tZnxCt8IuBPcmfEK3wgiQ0lRLk1FVEEuSVFfVE9UQUxfRElWX1BBSURfQ0YuMjAwMAEAAAAX2zwBAgAAAAUtNTM2NwEIAAAABQAAAAExAQAAAAstMTg3OTk1Njk5MQMAAAADMTYwAgAAAAQyMDIyBAAAAAEwBwAAAAg5LzQvMjAyNggAAAAJNi8zMC8yMDI2CQAAAAEwYA61mfEK3wi4E9yZ8QrfCB5DSVEuTUVUQS5JUV9TVE9DS19CQVNFRF9DRi45OTcBAAAAF9s8AQIAAAAFMTE5OTIBCAAAAAUAAAABMQEAAAALLTE5NjE0OTE3MzIDAAAAAzE2MAIAAAAEMjEyNwQAAAABMAcAAAAIOS80LzIwMjYIAAAACjEyLzMxLzIwMjIJAAAAATBgDrWZ8QrfCLU63JnxCt8IFkNJUS5NRVRBLklRX0NBUEVYLjEwMDABAAAAF9s8AQIAAAAGLTY5NjkxAQgAAAAFAAAAATEBAAAACy0xOTA4NTEzMzUzAwAAAAMxNjACAAAABDIwMjEEAAAAATAHAAAACDkvNC8yMDI2CAAAAAoxMi8zMS8yMDI1 | V1: CQAAAAEwYA61mfEK3wi4E9yZ8QrfCBlDSVEuTUVUQS5JUV9UT1RBTF9SRVYuOTk2AQAAABfbPAECAAAABjExNzkyOQEIAAAABQAAAAExAQAAAAstMjAxMTg0MzgwNAMAAAADMTYwAgAAAAIyOAQAAAABMAcAAAAIOS80LzIwMjYIAAAACjEyLzMxLzIwMjEJAAAAATBgDrWZ8QrfCLU63JnxCt8IFUNJUS5NRVRBLklRX0NBUEVYLjk5OQEAAAAX2zwBAgAAAAYtMzcyNTYBCAAAAAUAAAABMQEAAAALLTE5MDg1MTMzNDUDAAAAAzE2MAIAAAAEMjAyMQQAAAABMAcAAAAIOS80LzIwMjYIAAAACjEyLzMxLzIwMjQJAAAAATBgDrWZ8QrfCLU63JnxCt8IGkNJUS5NRVRBLklRX1RPVEFMX0RFQlQuOTk3AQAAABfbPAECAAAABTI2NTkxAQgAAAAFAAAAATEBAAAACy0xOTYxNDkxNzMyAwAAAAMxNjACAAAABDQxNzMEAAAAATAHAAAACDkvNC8yMDI2CAAAAAoxMi8zMS8yMDIyCQAAAAEw4TW1mfEK3wi4E9yZ8QrfCBpDSVEuTUVUQS5JUV9UQlZfU0hBUkUuNTAwMAEAAAAX2zwBAgAAAAk5My4zMzM5ODcBCAAAAAUAAAABMQEAAAALLTE4Nzk5NTkwOTIDAAAAAzE2MAIAAAAENDE1NgQAAAABMAcAAAAIOS80LzIwMjYIAAAACTYvMzAvMjAyNgkAAAABMGAOtZnxCt8ItTrcmfEK3wgdQ0lRLk1FVEEuSVFfVE9UQUxfRVFVSVRZLjEwMDABAAAAF9s8AQIAAAAGMjE3MjQzAQgAAAAFAAAAATEBAAAACy0xOTA4NTEzMzUzAwAAAAMx | W1: NjACAAAABDEyNzUEAAAAATAHAAAACDkvNC8yMDI2CAAAAAoxMi8zMS8yMDI1CQAAAAEw4TW1mfEK3wi4E9yZ8QrfCBNDSVEuTUVUQS5JUV9OSS4yMDAwAQAAABfbPAECAAAABTY4MDk4AQgAAAAFAAAAATEBAAAACy0xODc5OTU2OTkxAwAAAAMxNjACAAAAAjE1BAAAAAEwBwAAAAg5LzQvMjAyNggAAAAJNi8zMC8yMDI2CQAAAAEwYA61mfEK3wi1OtyZ8QrfCBxDSVEuTUVUQS5JUV9UT1RBTF9FUVVJVFkuOTk5AQAAABfbPAECAAAABjE4MjYzNwEIAAAABQAAAAExAQAAAAstMTkwODUxMzM0NQMAAAADMTYwAgAAAAQxMjc1BAAAAAEwBwAAAAg5LzQvMjAyNggAAAAKMTIvMzEvMjAyNAkAAAABMOE1tZnxCt8IuBPcmfEK3wgTQ0lRLk1FVEEuSVFfTkkuMTAwMAEAAAAX2zwBAgAAAAU2MDQ1OAEIAAAABQAAAAExAQAAAAstMTkwODUxMzM1MwMAAAADMTYwAgAAAAIxNQQAAAABMAcAAAAIOS80LzIwMjYIAAAACjEyLzMxLzIwMjUJAAAAATBgDrWZ8QrfCLU63JnxCt8IE0NJUS5NRVRBLklRX0dQLjIwMDABAAAAF9s8AQIAAAAGMTg2NTg2AQgAAAAFAAAAATEBAAAACy0xODc5OTU2OTkxAwAAAAMxNjACAAAAAjEwBAAAAAEwBwAAAAg5LzQvMjAyNggAAAAJNi8zMC8yMDI2CQAAAAEwYA61mfEK3wi1OtyZ8QrfCBlDSVEuTUVUQS5JUV9PUEVSX0lOQy4xMDAwAQAAABfbPAECAAAABTgzMjc2AQgAAAAFAAAAATEBAAAA | X1: Cy0xOTA4NTEzMzUzAwAAAAMxNjACAAAAAjIxBAAAAAEwBwAAAAg5LzQvMjAyNggAAAAKMTIvMzEvMjAyNQkAAAABMGAOtZnxCt8ItTrcmfEK3wgbQ0lRLk1FVEEuSVFfQ09NTU9OX1JFUC4yMDAwAQAAABfbPAECAAAABi0yMTQzOAEIAAAABQAAAAExAQAAAAstMTg3OTk1Njk5MQMAAAADMTYwAgAAAAQyMTY0BAAAAAEwBwAAAAg5LzQvMjAyNggAAAAJNi8zMC8yMDI2CQAAAAEwYA61mfEK3wiE5Rf58QrfCBdDSVEuTUVUQS5JUV9FQklUREEuMjAwMAEAAAAX2zwBAgAAAAYxMDk2NTUBCAAAAAUAAAABMQEAAAALLTE4Nzk5NTY5OTEDAAAAAzE2MAIAAAAENDA1MQQAAAABMAcAAAAIOS80LzIwMjYIAAAACTYvMzAvMjAyNgkAAAABMGAOtZnxCt8ItgsY+fEK3wgXQ0lRLk1FVEEuSVFfRUJJVERBLjEwMDABAAAAF9s8AQIAAAAGMTAxODkyAQgAAAAFAAAAATEBAAAACy0xOTA4NTEzMzUzAwAAAAMxNjACAAAABDQwNTEEAAAAATAHAAAACDkvNC8yMDI2CAAAAAoxMi8zMS8yMDI1CQAAAAEwYA61mfEK3wi1OtyZ8QrfCBhDSVEuTUVUQS5JUV9PUEVSX0lOQy45OTYBAAAAF9s8AQIAAAAFNDY3NTMBCAAAAAUAAAABMQEAAAALLTIwMTE4NDM4MDQDAAAAAzE2MAIAAAACMjEEAAAAATAHAAAACDkvNC8yMDI2CAAAAAoxMi8zMS8yMDIxCQAAAAEwYA61mfEK3wi1OtyZ8QrfCBFDSVEuTUVUQS5JUV9QQlYuLgEAAAAX2zwB | Y1: AgAAABA1Ljk1NjY5MDUwNTc1MTQ5AQcAAAAFAAAAATEBAAAACy0xODc5OTU2OTkxAwAAAAEwAgAAAAYxMDAwNjcEAAAAATAHAAAACDkvMy8yMDI2CAAAAAg5LzMvMjAyNs34xwDJCt8IyWHcmfEK3wgYQ0lRLk1FVEEuSVFfVEVWX0VCSVREQS4uAQAAABfbPAECAAAAEDEzLjg0MzYwMTQ1NTQ4NDMBBwAAAAUAAAABMQEAAAALLTE4Nzk5NTY5OTEDAAAAATACAAAABjEwMDA2MwQAAAABMAcAAAAIOS8zLzIwMjYIAAAACDkvMy8yMDI2zfjHAMkK3wjJYdyZ8QrfCBtDSVEuTUVUQS5JUV9URVZfVE9UQUxfUkVWLi4BAAAAF9s8AQIAAAAQNi45MTI1NTEzMjE1MjAxMQEHAAAABQAAAAExAQAAAAstMTg3OTk1Njk5MQMAAAABMAIAAAAGMTAwMDYxBAAAAAEwBwAAAAg5LzMvMjAyNggAAAAIOS8zLzIwMjbN+McAyQrfCLU63JnxCt8IKkNJUS5NRVRBLklRX1RPVEFMX09VVFNUQU5ESU5HX0JTX0RBVEVfQ1MuLgEAAAAX2zwBAgAAAAQyNTQ4AQkAAAAFAAAAAjE5AQAAAAgyOTk2NjY3NgIAAAAFMzI2NjIJAAAAAi0xAwAAAAEwBgAAAAg4LzEvMjAyNgcAAAAIOS80LzIwMjYIAAAAATAEAAAAATDN+McAyQrfCMlh3JnxCt8IFUNJUS5NRVRBLklRX0JFVEFfNVlSLgEAAAAX2zwBAgAAABAxLjI0MjQ3MTc4NDgwODQ1AM34xwDJCt8IyWHcmfEK3wgXQ0lRLk1FVEEuSVFfQ0xPU0VQUklDRS4BAAAAF9s8AQIAAAAGNjEwLjY4 | Z1: AM34xwDJCt8IyWHcmfEK3wgjQ0lRLk1FVEEuSVFfU0hBUkVTT1VUU1RBTkRJTkdfT1VULi4BAAAAF9s8AQIAAAALMjU0Ny41MDYyMjUAzfjHAMkK3wjJYdyZ8QrfCBFDSVEuTUVUQS5JUV9URVYuLgEAAAAX2zwBAgAAAA4xNTc3NzY5LjEwMTQ4MwEGAAAABQAAAAExAQAAAAstMTg3OTk1OTA5MgMAAAADMTYwAgAAAAYxMDAwNjAEAAAAATAHAAAACDkvMy8yMDI2zfjHAMkK3wi1OtyZ8QrfCBBDSVEuTUVUQS5JUV9URVYuAQAAABfbPAECAAAADjE1Nzc3NjkuMTAxNDgzAQYAAAAFAAAAATEBAAAACy0xODc5OTU5MDkyAwAAAAMxNjACAAAABjEwMDA2MAQAAAABMAcAAAAIOS8zLzIwMjbN+McAyQrfCMlh3JnxCt8IFENJUS5NRVRBLklRX1lFQVJMT1cuAQAAABfbPAECAAAABjUyMC4yNgDN+McAyQrfCMlh3JnxCt8IFkNJUS5NRVRBLklRX01BUktFVENBUC4BAAAAF9s8AQIAAAAOMTU1NTcxMS4xMDE0ODMBBgAAAAUAAAABMQEAAAALLTE4Nzk5NTkwOTIDAAAAAzE2MAIAAAAGMTAwMDU0BAAAAAEwBwAAAAg5LzMvMjAyNs34xwDJCt8IyWHcmfEK3wgXQ0lRLk1FVEEuSVFfTUFSS0VUQ0FQLi4BAAAAF9s8AQIAAAAOMTU1NTcxMS4xMDE0ODMBBgAAAAUAAAABMQEAAAALLTE4Nzk5NTkwOTIDAAAAAzE2MAIAAAAGMTAwMDU0BAAAAAEwBwAAAAg5LzMvMjAyNs34xwDJCt8ItTrcmfEK3wgbQ0lRLk1FVEEuSVFfRElW | AA1: SURFTkRfWUlFTEQuAQAAABfbPAECAAAABjAuMzQzOADN+McAyQrfCLU63JnxCt8IFUNJUS5NRVRBLklRX1lFQVJISUdILgEAAAAX2zwBAgAAAAU3OTAuOADN+McAyQrfCMlh3JnxCt8IGENJUS5NRVRBLklRX1RPVEFMX0RFQlQuLgEAAAAX2zwBAgAAAAYxMTIzMTgBCAAAAAUAAAABMQEAAAALLTE4Nzk5NTY5OTEDAAAAAzE2MAIAAAAENDE3MwQAAAABMAcAAAAIOS80LzIwMjYIAAAACTYvMzAvMjAyNgkAAAABMM34xwDJCt8ItTrcmfEK3wgcQ0lRLk1FVEEuSVFfQ0FTSF9TVF9JTlZFU1QuLgEAAAAX2zwBAgAAAAU5MDI2MAEIAAAABQAAAAExAQAAAAstMTg3OTk1Njk5MQMAAAADMTYwAgAAAAQxMDAyBAAAAAEwBwAAAAg5LzQvMjAyNggAAAAJNi8zMC8yMDI2CQAAAAEwzfjHAMkK3wi1OtyZ8QrfCBpDSVEuTUVUQS5JUV9JTlNUX09XTkVSU0hJUAUAAAAAAAAACAAAABYoSW52YWxpZCBGb3JtdWxhIE5hbWUpV+e0mfEK3wjiFIX18QrfCBdDSVEuTUVUQS5JUV9JTlNUX1NIQVJFUwUAAAAAAAAACAAAABYoSW52YWxpZCBGb3JtdWxhIE5hbWUpV+e0mfEK3wjiFIX18QrfCB1DSVEuTUVUQS5JUV9JTlNJREVSX09XTkVSU0hJUAUAAAAAAAAACAAAABYoSW52YWxpZCBGb3JtdWxhIE5hbWUpV+e0mfEK3whMPO6Z8QrfCB5DSVEuTUVUQS5JUV9CRVRBXzVZUi4wNS1TRVAtMjYBAAAAF9s8AQIAAAAQMS4yNDI0NzE3 | AB1: ODQ4MDg0NQBgDrWZ8QrfCITlF/nxCt8IGkNJUS5NRVRBLklRX1BCVi4uMDUtU0VQLTI2AQAAABfbPAECAAAAEDYuMDE2MDkzNTQwMzY4NjgBBwAAAAUAAAABMQEAAAALLTE4Nzk5NTY5OTEDAAAAATACAAAABjEwMDA2NwQAAAABMAcAAAAIOS80LzIwMjYIAAAACDkvNC8yMDI2V+e0mfEK3wiE5Rf58QrfCCRDSVEuTUVUQS5JUV9URVZfVE9UQUxfUkVWLi4wNS1TRVAtMjYBAAAAF9s8AQIAAAAQNi45ODA1MjI5MTc2ODY3NgEHAAAABQAAAAExAQAAAAstMTg3OTk1Njk5MQMAAAABMAIAAAAGMTAwMDYxBAAAAAEwBwAAAAg5LzQvMjAyNggAAAAIOS80LzIwMjZX57SZ8QrfCITlF/nxCt8IIUNJUS5NRVRBLklRX1RFVl9FQklUREEuLjA1LVNFUC0yNgEAAAAX2zwBAgAAABAxMy45Nzk3MjY1NDc5MjIzAQcAAAAFAAAAATEBAAAACy0xODc5OTU2OTkxAwAAAAEwAgAAAAYxMDAwNjMEAAAAATAHAAAACDkvNC8yMDI2CAAAAAg5LzQvMjAyNlfntJnxCt8IhOUX+fEK3wgeQ0lRLk1FVEEuSVFfWUVBUkhJR0guMDUtU0VQLTI2AQAAABfbPAECAAAABTc5MC44AFfntJnxCt8IhOUX+fEK3wgkQ0lRLk1FVEEuSVFfRElWSURFTkRfWUlFTEQuMDUtU0VQLTI2AQAAABfbPAECAAAABjAuMzQzOABX57SZ8QrfCITlF/nxCt8ILENJUS5NRVRBLklRX1NIQVJFU09VVFNUQU5ESU5HX09VVC4uMDUtU0VQLTI2AQAAABfbPAECAAAA | AC1: CzI1NDcuNTA2MjI1AFfntJnxCt8IhOUX+fEK3wgfQ0lRLk1FVEEuSVFfTUFSS0VUQ0FQLjA1LVNFUC0yNgEAAAAX2zwBAgAAAA4xNTcxMjI1LjQxNDM5MwEGAAAABQAAAAExAQAAAAstMTg3OTk1OTA5MgMAAAADMTYwAgAAAAYxMDAwNTQEAAAAATAHAAAACDkvNC8yMDI2V+e0mfEK3wiE5Rf58QrfCCBDSVEuTUVUQS5JUV9NQVJLRVRDQVAuLjA1LVNFUC0yNgEAAAAX2zwBAgAAAA4xNTcxMjI1LjQxNDM5MwEGAAAABQAAAAExAQAAAAstMTg3OTk1OTA5MgMAAAADMTYwAgAAAAYxMDAwNTQEAAAAATAHAAAACDkvNC8yMDI2V+e0mfEK3wiE5Rf58QrfCBlDSVEuTUVUQS5JUV9URVYuMDUtU0VQLTI2AQAAABfbPAECAAAADjE1OTMyODMuNDE0MzkzAQYAAAAFAAAAATEBAAAACy0xODc5OTU5MDkyAwAAAAMxNjACAAAABjEwMDA2MAQAAAABMAcAAAAIOS80LzIwMjZX57SZ8QrfCITlF/nxCt8IGkNJUS5NRVRBLklRX1RFVi4uMDUtU0VQLTI2AQAAABfbPAECAAAADjE1OTMyODMuNDE0MzkzAQYAAAAFAAAAATEBAAAACy0xODc5OTU5MDkyAwAAAAMxNjACAAAABjEwMDA2MAQAAAABMAcAAAAIOS80LzIwMjZX57SZ8QrfCITlF/nxCt8IIENJUS5NRVRBLklRX0NMT1NFUFJJQ0UuMDUtU0VQLTI2AQAAABfbPAECAAAABjYxNi43NwBX57SZ8QrfCITlF/nxCt8IHUNJUS5NRVRBLklRX1lFQVJMT1cuMDUtU0VQLTI2AQAA | AD1: ABfbPAECAAAABjUyMC4yNgBX57SZ8QrfCITlF/nxCt8IM0NJUS5NRVRBLklRX1RPVEFMX09VVFNUQU5ESU5HX0JTX0RBVEVfQ1MuLjA1LVNFUC0yNgEAAAAX2zwBAgAAAAQyNTQ4AQkAAAAFAAAAAjE5AQAAAAgyOTk2NjY3NgIAAAAFMzI2NjIJAAAAAi0xAwAAAAEwBgAAAAg4LzEvMjAyNgcAAAAIOS81LzIwMjYIAAAAATAEAAAAATDhNbWZ8QrfCITlF/nxCt8IIENJUS5NRVRBLklRX0NBU0hfT1BFUi4uMDUtU0VQLTI2AQAAABfbPAECAAAABjEzMDMwMQEIAAAABQAAAAExAQAAAAstMTg3OTk1Njk5MQMAAAADMTYwAgAAAAQyMDA2BAAAAAEwBwAAAAg5LzUvMjAyNggAAAAJNi8zMC8yMDI2CQAAAAEwYA61mfEK3wiE5Rf58QrfCBxDSVEuTUVUQS5JUV9DQVBFWC4uMDUtU0VQLTI2AQAAABfbPAECAAAABi04OTMyNQEIAAAABQAAAAExAQAAAAstMTg3OTk1Njk5MQMAAAADMTYwAgAAAAQyMDIxBAAAAAEwBwAAAAg5LzUvMjAyNggAAAAJNi8zMC8yMDI2CQAAAAEwYA61mfEK3wiE5Rf58QrfCCFDSVEuTUVUQS5JUV9UT1RBTF9ERUJULi4wNS1TRVAtMjYBAAAAF9s8AQIAAAAGMTEyMzE4AQgAAAAFAAAAATEBAAAACy0xODc5OTU2OTkxAwAAAAMxNjACAAAABDQxNzMEAAAAATAHAAAACDkvNS8yMDI2CAAAAAk2LzMwLzIwMjYJAAAAATBgDrWZ8QrfCITlF/nxCt8IJUNJUS5NRVRBLklRX0NBU0hfU1RfSU5WRVNU | AE1: Li4wNS1TRVAtMjYBAAAAF9s8AQIAAAAFOTAyNjABCAAAAAUAAAABMQEAAAALLTE4Nzk5NTY5OTEDAAAAAzE2MAIAAAAEMTAwMgQAAAABMAcAAAAIOS81LzIwMjYIAAAACTYvMzAvMjAyNgkAAAABMGAOtZnxCt8IhOUX+fEK3wgaQ0lRLk1FVEEuSVFfSU5TSURFUl9TSEFSRVMBAAAAF9s8AQEAAAAJMzQxMjMyMjg4AQUAAAAFAAAAAjIxAQAAAAgyMDc2NTkxMAIAAAAIMjA3NjU0NjMGAAAAATEHAAAAATFgDrWZ8QrfCEw87pnxCt8IHUNJUS5QTFRSLklRX0lOU0lERVJfT1dORVJTSElQBQAAAAAAAAAIAAAAFihJbnZhbGlkIEZvcm11bGEgTmFtZSmxGVH88QrfCAOFcvzxCt8IGkNJUS5QTFRSLklRX0lOU1RfT1dORVJTSElQBQAAAAAAAAAIAAAAFihJbnZhbGlkIEZvcm11bGEgTmFtZSmxGVH88QrfCAOFcvzxCt8IF0NJUS5QTFRSLklRX0lOU1RfU0hBUkVTBQAAAAAAAAAIAAAAFihJbnZhbGlkIEZvcm11bGEgTmFtZSmxGVH88QrfCAOFcvzxCt8IG0NJUS5QTFRSLklRX0lORFVTVFJZX1NFQ1RPUgEAAABl+pgCAwAAABZJbmZvcm1hdGlvbiBUZWNobm9sb2d5ALEZUfzxCt8ISuhx/PEK3wgcQ0lRLlBMVFIuSVFfUFJJTUFSWV9JTkRVU1RSWQEAAABl+pgCAwAAABRBcHBsaWNhdGlvbiBTb2Z0d2FyZQCxGVH88QrfCErocfzxCt8IGENJUS5QTFRSLklRX0NPTVBBTllfTkFNRQEAAABl+pgCAwAAABpQYWxhbnRp | AF1: ciBUZWNobm9sb2dpZXMgSW5jLgCxGVH88QrfCErocfzxCt8IFENJUS5QTFRSLklRX0VYQ0hBTkdFAQAAAGX6mAIDAAAACE5hc2RhcUdTALEZUfzxCt8ISuhx/PEK3wgbQ0lRLlBMVFIuSVFfQ09NUEFOWV9BRERSRVNTAQAAAGX6mAIDAAAASDE5NTA1IEJpc2NheW5lIEJsdmQsIFN1aXRlIDIzNTAsIEF2ZW50dXJhLCBGbG9yaWRhLCAzMzE4MCwgVW5pdGVkIFN0YXRlcwCxGVH88QrfCErocfzxCt8IGENJUS5QTFRSLklRX1BFX0VYQ0wuMjAwMAEAAABl+pgCAgAAABAxNDkuMDk3NjE0MzM1NTM5AQcAAAAFAAAAATEBAAAACy0xODc5MjI4Njk5AwAAAAEwAgAAAAYxMDAwNjYEAAAAATAHAAAACDkvNC8yMDI2CAAAAAg5LzQvMjAyNrEZUfzxCt8ISuhx/PEK3wgcQ0lRLlBMVFIuSVFfUFJJQ0VfU0FMRVMuMjAwMAEAAABl+pgCAgAAABA2Ny42Njk2NzIwMDgwMTQ5AQcAAAAFAAAAATEBAAAACy0xODc5MjI4Njk5AwAAAAEwAgAAAAUzODk1OAQAAAABMAcAAAAIOS80LzIwMjYIAAAACDkvNC8yMDI2sRlR/PEK3whK6HH88QrfCCFDSVEuUExUUi5JUV9URVZfRUJJVERBLi4wNS1TRVAtMjYBAAAAZfqYAgIAAAAQMTUwLjk2MjYwMTEyNDg5NAEHAAAABQAAAAExAQAAAAstMTg3OTIyODY5OQMAAAABMAIAAAAGMTAwMDYzBAAAAAEwBwAAAAg5LzQvMjAyNggAAAAIOS80LzIwMjaxGVH88QrfCFE+cgTyCt8IGkNJUS5Q | AG1: TFRSLklRX1BCVi4uMDUtU0VQLTI2AQAAAGX6mAICAAAAEDQyLjg1NzQ0ODQwMjI5MjEBBwAAAAUAAAABMQEAAAALLTE4NzkyMjg2OTkDAAAAATACAAAABjEwMDA2NwQAAAABMAcAAAAIOS80LzIwMjYIAAAACDkvNC8yMDI2sRlR/PEK3whRPnIE8grfCCRDSVEuUExUUi5JUV9URVZfVE9UQUxfUkVWLi4wNS1TRVAtMjYBAAAAZfqYAgIAAAAPNjYuNTc2MDQwMjU0MTg3AQcAAAAFAAAAATEBAAAACy0xODc5MjI4Njk5AwAAAAEwAgAAAAYxMDAwNjEEAAAAATAHAAAACDkvNC8yMDI2CAAAAAg5LzQvMjAyNrEZUfzxCt8IUT5yBPIK3wgZQ0lRLlBMVFIuSVFfVEVWLjA1LVNFUC0yNgEAAABl+pgCAgAAAA00MDk4MzguMTc1ODE4AQYAAAAFAAAAATEBAAAACy0xODc5MjM0ODc0AwAAAAMxNjACAAAABjEwMDA2MAQAAAABMAcAAAAIOS80LzIwMjaxGVH88QrfCFE+cgTyCt8IH0NJUS5QTFRSLklRX01BUktFVENBUC4wNS1TRVAtMjYBAAAAZfqYAgIAAAANNDE4OTI1LjE4NDgxOAEGAAAABQAAAAExAQAAAAstMTg3OTIzNDg3NAMAAAADMTYwAgAAAAYxMDAwNTQEAAAAATAHAAAACDkvNC8yMDI2sRlR/PEK3whRPnIE8grfCCBDSVEuUExUUi5JUV9DTE9TRVBSSUNFLjA1LVNFUC0yNgEAAABl+pgCAgAAAAYxNzQuMzMAsRlR/PEK3whRPnIE8grfCB1DSVEuUExUUi5JUV9ZRUFSTE9XLjA1LVNFUC0yNgEAAABl+pgCAgAA | AH1: AAYxMDYuMzcAsRlR/PEK3whRPnIE8grfCB5DSVEuUExUUi5JUV9ZRUFSSElHSC4wNS1TRVAtMjYBAAAAZfqYAgIAAAAGMjA3LjUyALEZUfzxCt8IUT5yBPIK3wgsQ0lRLlBMVFIuSVFfU0hBUkVTT1VUU1RBTkRJTkdfT1VULi4wNS1TRVAtMjYBAAAAZfqYAgIAAAALMjU0Ny40NDgyMzYAsRlR/PEK3whRPnIE8grfCBpDSVEuUExUUi5JUV9URVYuLjA1LVNFUC0yNgEAAABl+pgCAgAAAA00MDk4MzguMTc1ODE4AQYAAAAFAAAAATEBAAAACy0xODc5MjM0ODc0AwAAAAMxNjACAAAABjEwMDA2MAQAAAABMAcAAAAIOS80LzIwMjaxGVH88QrfCFE+cgTyCt8IJENJUS5QTFRSLklRX0RJVklERU5EX1lJRUxELjA1LVNFUC0yNgEAAABl+pgCAwAAAAAAsRlR/PEK3whRPnIE8grfCCBDSVEuUExUUi5JUV9NQVJLRVRDQVAuLjA1LVNFUC0yNgEAAABl+pgCAgAAAA00MTg5MjUuMTg0ODE4AQYAAAAFAAAAATEBAAAACy0xODc5MjM0ODc0AwAAAAMxNjACAAAABjEwMDA1NAQAAAABMAcAAAAIOS80LzIwMjaxGVH88QrfCFE+cgTyCt8IGUNJUUFWRy5QTFRSLklRX1ZPTFVNRS4tM00BAAAAZfqYAgIAAAAQNDAuNzg0MjQzMDMwNzY5MgCxGVH88QrfCErocfzxCt8IHkNJUS5QTFRSLklRX0JFVEFfNVlSLjA1LVNFUC0yNgEAAABl+pgCAgAAABAxLjYyMTM1NDY4MDMwODk5ALEZUfzxCt8IUT5yBPIK3wgYQ0lRLlBMVFIuSVFf | AI1: UEVHX0ZXRC42MDAwAQAAAGX6mAICAAAADzEuNzA1OTc4MjY5Njg2OQENAAAABQAAAAE5AQAAAAk2ODc5OTk2OTkCAAAABzQ4NzYxNDgDAAAABjEwMDMxMQQAAAABMgYAAAABMAcAAAADMTYwCAAAAAEwCQAAAAExCgAAAAEwCwAAAAsxNDkzOTc3NzA1OAwAAAACMTINAAAACDkvNS8yMDI2sRlR/PEK3whK6HH88QrfCCBDSVEuUExUUi5JUV9QRV9FWENMX0ZXRF9DSVEuNjAwMAEAAABl+pgCAgAAABA5MS41ODg3MzU5NDYyMDE1AQ0AAAAFAAAAATkBAAAACTY4Nzk5OTY5OQIAAAAHNDg3NjE0OAMAAAAGMTAwMzA5BAAAAAEyBgAAAAEwBwAAAAMxNjAIAAAAATAJAAAAATEKAAAAATALAAAACzE0OTM5Nzc3MDU4DAAAAAIxMg0AAAAIOS81LzIwMjaxGVH88QrfCErocfzxCt8IIUNJUS5QTFRSLklRX1BFX0VYQ0xfRldEX0NJUS4xMDAwMAEAAABl+pgCAwAAAAAAsRlR/PEK3whK6HH88QrfCChDSVFSQU5HRS5QTFRSLklRX05FV1MuMS4yNS4uLi4uTkVXUyBEQVRFAwAAAGX6mAIEAAAAAAAAAAMAAAAAAAAABiJQTFRSIgRQTFRSAQAAAAkiSVFfTkVXUyIHSVFfTkVXUwIAAAABMQExAAAAAAMAAAAAAAAABiJQTFRSIgRQTFRSAQAAAAkiSVFfTkVXUyIHSVFfTkVXUwIAAAABMgEyAAAAAAMAAAAAAAAABiJQTFRSIgRQTFRSAQAAAAkiSVFfTkVXUyIHSVFfTkVXUwIAAAABMwEzAAAAAAMAAAAAAAAABiJQTFRSIgRQTFRS | AJ1: AQAAAAkiSVFfTkVXUyIHSVFfTkVXUwIAAAABNAE0sRlR/PEK3wixGVH88QrfCBJDSVEuUExUUi5JUV9ORVdTLjEBAAAAZfqYAgMAAAAzUyZQIDUwMCByZWJvdW5kcyAyLjYlIGluIEF1Z3VzdCBhZnRlciAyLW1vbnRoIHNsaWRlAQMAAAAFAAAAAjE3AQAAAAkzMjI3NDA0OTYCAAAABDc3NzGxGVH88QrfCDNdcvzxCt8IEkNJUS5QTFRSLklRX05FV1MuMgEAAABl+pgCAwAAAENJbnRlbCwgSUJNIGxlYWQgcGVlcnMgYXMgSVQgQ0VPLXRvLWVtcGxveWVlIHBheSByYXRpbyBqdW1wcyBpbiAyMDI1AQMAAAAFAAAAAjE3AQAAAAkzMjI3Mzk3MjUCAAAABDc3NzGxGVH88QrfCDNdcvzxCt8IEkNJUS5QTFRSLklRX05FV1MuMwEAAABl+pgCAwAAAE9QSk0gcHJvcG9zZXMgZGF0YSBjZW50ZXIgZnJhbWV3b3JrOyBFUkNPVCBvdXRsaW5lcyBsYXJnZSBsb2FkIHZlcmlmaWNhdGlvbiBwbGFuAQMAAAAFAAAAAjE3AQAAAAkzMjI3Mzk1MTQCAAAABDc3NzGxGVH88QrfCDNdcvzxCt8IEkNJUS5QTFRSLklRX05FV1MuNAEAAABl+pgCAwAAAENXaWRlc3QgUyZQIDUwMCBDRU8gcGF5IHJhdGlvcyByZXBvcnRlZCBmb3IgVGVzbGEsIFdlbGx0b3dlciBpbiAyMDI1AQMAAAAFAAAAAjE3AQAAAAkzMjI3Mzk0NTICAAAABDc3NzGxGVH88QrfCDNdcvzxCt8ILENJUVJBTkdFLlBMVFIuSVFfTkVXUy4xLjI1Li4uLi5ORVdTIEhF | AK1: QURMSU5FAwAAAGX6mAIEAAAAAAAAAAMAAAAAAAAABiJQTFRSIgRQTFRSAQAAAAkiSVFfTkVXUyIHSVFfTkVXUwIAAAABMQExAAAAAAMAAAAAAAAABiJQTFRSIgRQTFRSAQAAAAkiSVFfTkVXUyIHSVFfTkVXUwIAAAABMgEyAAAAAAMAAAAAAAAABiJQTFRSIgRQTFRSAQAAAAkiSVFfTkVXUyIHSVFfTkVXUwIAAAABMwEzAAAAAAMAAAAAAAAABiJQTFRSIgRQTFRSAQAAAAkiSVFfTkVXUyIHSVFfTkVXUwIAAAABNAE0sRlR/PEK3wixGVH88QrfCCpDSVFSQU5HRS5QTFRSLklRX05FV1MuMS4yNS4uLi4uTkVXUyBTT1VSQ0UDAAAAZfqYAgQAAAAAAAAAAwAAAAAAAAAGIlBMVFIiBFBMVFIBAAAACSJJUV9ORVdTIgdJUV9ORVdTAgAAAAExATEAAAAAAwAAAAAAAAAGIlBMVFIiBFBMVFIBAAAACSJJUV9ORVdTIgdJUV9ORVdTAgAAAAEyATIAAAAAAwAAAAAAAAAGIlBMVFIiBFBMVFIBAAAACSJJUV9ORVdTIgdJUV9ORVdTAgAAAAEzATMAAAAAAwAAAAAAAAAGIlBMVFIiBFBMVFIBAAAACSJJUV9ORVdTIgdJUV9ORVdTAgAAAAE0ATSxGVH88QrfCLEZUfzxCt8IJ0NJUVJBTkdFLlBMVFIuSVFfTkVXUy4xLjI1Li4uLi5ORVdTIFVSTAMAAABl+pgCBAAAAAAAAAADAAAAAAAAAAYiUExUUiIEUExUUgEAAAAJIklRX05FV1MiB0lRX05FV1MCAAAAATEBMQAAAAADAAAAAAAAAAYiUExUUiIEUExUUgEAAAAJIklRX05FV1Mi | AL1: B0lRX05FV1MCAAAAATIBMgAAAAADAAAAAAAAAAYiUExUUiIEUExUUgEAAAAJIklRX05FV1MiB0lRX05FV1MCAAAAATMBMwAAAAADAAAAAAAAAAYiUExUUiIEUExUUgEAAAAJIklRX05FV1MiB0lRX05FV1MCAAAAATQBNLEZUfzxCt8IsRlR/PEK3wgcQ0lRLlBMVFIuSVFfRElMVVRfV0VJR0hULjk5NwEAAABl+pgCAgAAAAgyMDYzLjc5MwCxGVH88QrfCCw2cvzxCt8IHENJUS5QTFRSLklRX0RJTFVUX1dFSUdIVC45OTgBAAAAZfqYAgIAAAAIMjI5Ny45MjcAsRlR/PEK3wgsNnL88QrfCBxDSVEuUExUUi5JUV9ESUxVVF9XRUlHSFQuOTk5AQAAAGX6mAICAAAACDI0NTAuODE4ALEZUfzxCt8ILDZy/PEK3wgdQ0lRLlBMVFIuSVFfRElMVVRfV0VJR0hULjEwMDABAAAAZfqYAgIAAAAIMjU2NS4xOTcAsRlR/PEK3wgsNnL88QrfCB1DSVEuUExUUi5JUV9ESUxVVF9XRUlHSFQuMjAwMAEAAABl+pgCAgAAAAkyNTcxLjE1NDUAsRlR/PEK3wgsNnL88QrfCBxDSVEuUExUUi5JUV9UT1RBTF9BU1NFVFMuOTk4AQAAAGX6mAICAAAACDQ1MjIuNDI1AQgAAAAFAAAAATEBAAAACy0xOTA2MTI1NDAzAwAAAAMxNjACAAAABDEwMDcEAAAAATAHAAAACDkvNC8yMDI2CAAAAAoxMi8zMS8yMDIzCQAAAAEwsRlR/PEK3wgsNnL88QrfCBxDSVEuUExUUi5JUV9UT1RBTF9BU1NFVFMuOTk5AQAAAGX6mAICAAAACDYzNDAuODg0AQgA | AM1: AAAFAAAAATEBAAAACy0xOTA2MTI1Mzg4AwAAAAMxNjACAAAABDEwMDcEAAAAATAHAAAACDkvNC8yMDI2CAAAAAoxMi8zMS8yMDI0CQAAAAEwsRlR/PEK3wgsNnL88QrfCB1DSVEuUExUUi5JUV9UT1RBTF9BU1NFVFMuMTAwMAEAAABl+pgCAgAAAAg4OTAwLjM5MgEIAAAABQAAAAExAQAAAAstMTkwNjEyNTM5MgMAAAADMTYwAgAAAAQxMDA3BAAAAAEwBwAAAAg5LzQvMjAyNggAAAAKMTIvMzEvMjAyNQkAAAABMLEZUfzxCt8ILDZy/PEK3wgdQ0lRLlBMVFIuSVFfVE9UQUxfQVNTRVRTLjIwMDABAAAAZfqYAgIAAAAJMTE2NzguNTY0AQgAAAAFAAAAATEBAAAACy0xODc5MjI4Njk5AwAAAAMxNjACAAAABDEwMDcEAAAAATAHAAAACDkvNC8yMDI2CAAAAAk2LzMwLzIwMjYJAAAAATCxGVH88QrfCCw2cvzxCt8IHENJUS5QTFRSLklRX0RJTFVUX1dFSUdIVC45OTYBAAAAZfqYAgIAAAAIMTkyMy42MTcAsRlR/PEK3wgsNnL88QrfCBxDSVEuUExUUi5JUV9UT1RBTF9FUVVJVFkuOTk5AQAAAGX6mAICAAAACDUwOTQuNDA3AQgAAAAFAAAAATEBAAAACy0xOTA2MTI1Mzg4AwAAAAMxNjACAAAABDEyNzUEAAAAATAHAAAACDkvNC8yMDI2CAAAAAoxMi8zMS8yMDI0CQAAAAEwukBR/PEK3wgsNnL88QrfCB1DSVEuUExUUi5JUV9UT1RBTF9FUVVJVFkuMTAwMAEAAABl+pgCAgAAAAg3NDg4LjAxMQEIAAAABQAAAAExAQAA | AN1: AAstMTkwNjEyNTM5MgMAAAADMTYwAgAAAAQxMjc1BAAAAAEwBwAAAAg5LzQvMjAyNggAAAAKMTIvMzEvMjAyNQkAAAABMLpAUfzxCt8ILDZy/PEK3wgdQ0lRLlBMVFIuSVFfVE9UQUxfRVFVSVRZLjIwMDABAAAAZfqYAgIAAAAIOTg4NC44ODQBCAAAAAUAAAABMQEAAAALLTE4NzkyMjg2OTkDAAAAAzE2MAIAAAAEMTI3NQQAAAABMAcAAAAIOS80LzIwMjYIAAAACTYvMzAvMjAyNgkAAAABMLpAUfzxCt8ILDZy/PEK3wgcQ0lRLlBMVFIuSVFfVE9UQUxfQVNTRVRTLjk5NgEAAABl+pgCAgAAAAczMjQ3LjQ1AQgAAAAFAAAAATEBAAAACy0yMDA5NTg2MzEzAwAAAAMxNjACAAAABDEwMDcEAAAAATAHAAAACDkvNC8yMDI2CAAAAAoxMi8zMS8yMDIxCQAAAAEwukBR/PEK3wgsNnL88QrfCBxDSVEuUExUUi5JUV9UT1RBTF9BU1NFVFMuOTk3AQAAAGX6mAICAAAACDM0NjEuMjM5AQgAAAAFAAAAATEBAAAACy0xOTU5MjYyMDcyAwAAAAMxNjACAAAABDEwMDcEAAAAATAHAAAACDkvNC8yMDI2CAAAAAoxMi8zMS8yMDIyCQAAAAEwukBR/PEK3wgsNnL88QrfCBtDSVEuUExUUi5JUV9UT1RBTF9ERUJULjEwMDABAAAAZfqYAgIAAAAHMjI5LjMzOAEIAAAABQAAAAExAQAAAAstMTkwNjEyNTM5MgMAAAADMTYwAgAAAAQ0MTczBAAAAAEwBwAAAAg5LzQvMjAyNggAAAAKMTIvMzEvMjAyNQkAAAABMLpAUfzxCt8ILDZy/PEK | AO1: 3wgbQ0lRLlBMVFIuSVFfVE9UQUxfREVCVC4yMDAwAQAAAGX6mAICAAAABTIxMS40AQgAAAAFAAAAATEBAAAACy0xODc5MjI4Njk5AwAAAAMxNjACAAAABDQxNzMEAAAAATAHAAAACDkvNC8yMDI2CAAAAAk2LzMwLzIwMjYJAAAAATC6QFH88QrfCCw2cvzxCt8IHENJUS5QTFRSLklRX1RPVEFMX0VRVUlUWS45OTYBAAAAZfqYAgIAAAAHMjI5MS4wMwEIAAAABQAAAAExAQAAAAstMjAwOTU4NjMxMwMAAAADMTYwAgAAAAQxMjc1BAAAAAEwBwAAAAg5LzQvMjAyNggAAAAKMTIvMzEvMjAyMQkAAAABMLpAUfzxCt8ILDZy/PEK3wgcQ0lRLlBMVFIuSVFfVE9UQUxfRVFVSVRZLjk5NwEAAABl+pgCAgAAAAgyNjQyLjQzNwEIAAAABQAAAAExAQAAAAstMTk1OTI2MjA3MgMAAAADMTYwAgAAAAQxMjc1BAAAAAEwBwAAAAg5LzQvMjAyNggAAAAKMTIvMzEvMjAyMgkAAAABMLpAUfzxCt8ILDZy/PEK3wgcQ0lRLlBMVFIuSVFfVE9UQUxfRVFVSVRZLjk5OAEAAABl+pgCAgAAAAgzNTYwLjk2NQEIAAAABQAAAAExAQAAAAstMTkwNjEyNTQwMwMAAAADMTYwAgAAAAQxMjc1BAAAAAEwBwAAAAg5LzQvMjAyNggAAAAKMTIvMzEvMjAyMwkAAAABMLpAUfzxCt8ILDZy/PEK3wgfQ0lRLlBMVFIuSVFfQ0FTSF9TVF9JTlZFU1QuMjAwMAEAAABl+pgCAgAAAAg5NDA5LjA5OQEIAAAABQAAAAExAQAAAAstMTg3OTIyODY5OQMAAAAD | AP1: MTYwAgAAAAQxMDAyBAAAAAEwBwAAAAg5LzQvMjAyNggAAAAJNi8zMC8yMDI2CQAAAAEwukBR/PEK3wgsNnL88QrfCBpDSVEuUExUUi5JUV9UT1RBTF9ERUJULjk5NgEAAABl+pgCAgAAAAcyNjAuMDczAQgAAAAFAAAAATEBAAAACy0yMDA5NTg2MzEzAwAAAAMxNjACAAAABDQxNzMEAAAAATAHAAAACDkvNC8yMDI2CAAAAAoxMi8zMS8yMDIxCQAAAAEwukBR/PEK3wgsNnL88QrfCBpDSVEuUExUUi5JUV9UT1RBTF9ERUJULjk5NwEAAABl+pgCAgAAAAcyNDkuNDA0AQgAAAAFAAAAATEBAAAACy0xOTU5MjYyMDcyAwAAAAMxNjACAAAABDQxNzMEAAAAATAHAAAACDkvNC8yMDI2CAAAAAoxMi8zMS8yMDIyCQAAAAEwukBR/PEK3wgsNnL88QrfCBpDSVEuUExUUi5JUV9UT1RBTF9ERUJULjk5OAEAAABl+pgCAgAAAAcyMjkuMzkyAQgAAAAFAAAAATEBAAAACy0xOTA2MTI1NDAzAwAAAAMxNjACAAAABDQxNzMEAAAAATAHAAAACDkvNC8yMDI2CAAAAAoxMi8zMS8yMDIzCQAAAAEwukBR/PEK3wgsNnL88QrfCBpDSVEuUExUUi5JUV9UT1RBTF9ERUJULjk5OQEAAABl+pgCAgAAAAcyMzkuMjE5AQgAAAAFAAAAATEBAAAACy0xOTA2MTI1Mzg4AwAAAAMxNjACAAAABDQxNzMEAAAAATAHAAAACDkvNC8yMDI2CAAAAAoxMi8zMS8yMDI0CQAAAAEwukBR/PEK3wgsNnL88QrfCB5DSVEuUExUUi5JUV9DQVNIX1NUX0lOVkVT | AQ1: VC45OTYBAAAAZfqYAgIAAAAIMjUyNC44MjcBCAAAAAUAAAABMQEAAAALLTIwMDk1ODYzMTMDAAAAAzE2MAIAAAAEMTAwMgQAAAABMAcAAAAIOS80LzIwMjYIAAAACjEyLzMxLzIwMjEJAAAAATC6QFH88QrfCNEPcvzxCt8IHkNJUS5QTFRSLklRX0NBU0hfU1RfSU5WRVNULjk5NwEAAABl+pgCAgAAAAgyNjMzLjY3NQEIAAAABQAAAAExAQAAAAstMTk1OTI2MjA3MgMAAAADMTYwAgAAAAQxMDAyBAAAAAEwBwAAAAg5LzQvMjAyNggAAAAKMTIvMzEvMjAyMgkAAAABMLpAUfzxCt8ILDZy/PEK3wgeQ0lRLlBMVFIuSVFfQ0FTSF9TVF9JTlZFU1QuOTk4AQAAAGX6mAICAAAACDM2NzQuMTc5AQgAAAAFAAAAATEBAAAACy0xOTA2MTI1NDAzAwAAAAMxNjACAAAABDEwMDIEAAAAATAHAAAACDkvNC8yMDI2CAAAAAoxMi8zMS8yMDIzCQAAAAEwukBR/PEK3wgsNnL88QrfCB5DSVEuUExUUi5JUV9DQVNIX1NUX0lOVkVTVC45OTkBAAAAZfqYAgIAAAAINTIyOS45ODcBCAAAAAUAAAABMQEAAAALLTE5MDYxMjUzODgDAAAAAzE2MAIAAAAEMTAwMgQAAAABMAcAAAAIOS80LzIwMjYIAAAACjEyLzMxLzIwMjQJAAAAATC6QFH88QrfCCw2cvzxCt8IH0NJUS5QTFRSLklRX0NBU0hfU1RfSU5WRVNULjEwMDABAAAAZfqYAgIAAAAINzE3Ny4wNDMBCAAAAAUAAAABMQEAAAALLTE5MDYxMjUzOTIDAAAAAzE2MAIAAAAEMTAwMgQA | AR1: AAABMAcAAAAIOS80LzIwMjYIAAAACjEyLzMxLzIwMjUJAAAAATC6QFH88QrfCCw2cvzxCt8IGkNJUS5QTFRSLklRX0NPTU1PTl9SRVAuOTk3AQAAAGX6mAIDAAAAAAC6QFH88QrfCNEPcvzxCt8IGkNJUS5QTFRSLklRX0NPTU1PTl9SRVAuOTk4AQAAAGX6mAIDAAAAAAC6QFH88QrfCNEPcvzxCt8IGkNJUS5QTFRSLklRX0NPTU1PTl9SRVAuOTk5AQAAAGX6mAICAAAACC0yODIuNDc2AQgAAAAFAAAAATEBAAAACy0xOTA2MTI1Mzg4AwAAAAMxNjACAAAABDIxNjQEAAAAATAHAAAACDkvNC8yMDI2CAAAAAoxMi8zMS8yMDI0CQAAAAEwukBR/PEK3wjRD3L88QrfCBtDSVEuUExUUi5JUV9DT01NT05fUkVQLjEwMDABAAAAZfqYAgIAAAAILTE1Ni4xMDIBCAAAAAUAAAABMQEAAAALLTE5MDYxMjUzOTIDAAAAAzE2MAIAAAAEMjE2NAQAAAABMAcAAAAIOS80LzIwMjYIAAAACjEyLzMxLzIwMjUJAAAAATC6QFH88QrfCNEPcvzxCt8IG0NJUS5QTFRSLklRX0NPTU1PTl9SRVAuMjAwMAEAAABl+pgCAgAAAAgtMTU2LjEwMgEIAAAABQAAAAExAQAAAAstMTg3OTIyODY5OQMAAAADMTYwAgAAAAQyMTY0BAAAAAEwBwAAAAg5LzQvMjAyNggAAAAJNi8zMC8yMDI2CQAAAAEwukBR/PEK3whRPnIE8grfCCFDSVEuUExUUi5JUV9UT1RBTF9ESVZfUEFJRF9DRi45OTgBAAAAZfqYAgMAAAAAALpAUfzxCt8I0Q9y/PEK3wghQ0lR | AS1: LlBMVFIuSVFfVE9UQUxfRElWX1BBSURfQ0YuOTk5AQAAAGX6mAIDAAAAAAC6QFH88QrfCNEPcvzxCt8IIkNJUS5QTFRSLklRX1RPVEFMX0RJVl9QQUlEX0NGLjEwMDABAAAAZfqYAgMAAAAAALpAUfzxCt8I0Q9y/PEK3wgiQ0lRLlBMVFIuSVFfVE9UQUxfRElWX1BBSURfQ0YuMjAwMAEAAABl+pgCAwAAAAAAukBR/PEK3wjRD3L88QrfCBpDSVEuUExUUi5JUV9DT01NT05fUkVQLjk5NgEAAABl+pgCAwAAAAAAukBR/PEK3wjRD3L88QrfCB5DSVEuUExUUi5JUV9TVE9DS19CQVNFRF9DRi45OTkBAAAAZfqYAgIAAAAHNjkxLjYzOAEIAAAABQAAAAExAQAAAAstMTkwNjEyNTM4OAMAAAADMTYwAgAAAAQyMTI3BAAAAAEwBwAAAAg5LzQvMjAyNggAAAAKMTIvMzEvMjAyNAkAAAABMLpAUfzxCt8I0Q9y/PEK3wgfQ0lRLlBMVFIuSVFfU1RPQ0tfQkFTRURfQ0YuMTAwMAEAAABl+pgCAgAAAAc2ODQuMDMzAQgAAAAFAAAAATEBAAAACy0xOTA2MTI1MzkyAwAAAAMxNjACAAAABDIxMjcEAAAAATAHAAAACDkvNC8yMDI2CAAAAAoxMi8zMS8yMDI1CQAAAAEwukBR/PEK3wjRD3L88QrfCB9DSVEuUExUUi5JUV9TVE9DS19CQVNFRF9DRi4yMDAwAQAAAGX6mAICAAAABzgzNS41MjQBCAAAAAUAAAABMQEAAAALLTE4NzkyMjg2OTkDAAAAAzE2MAIAAAAEMjEyNwQAAAABMAcAAAAIOS80LzIwMjYIAAAACTYvMzAvMjAyNgkA | AT1: AAABMLpAUfzxCt8I0Q9y/PEK3wghQ0lRLlBMVFIuSVFfVE9UQUxfRElWX1BBSURfQ0YuOTk2AQAAAGX6mAIDAAAAAAC6QFH88QrfCNEPcvzxCt8IIUNJUS5QTFRSLklRX1RPVEFMX0RJVl9QQUlEX0NGLjk5NwEAAABl+pgCAwAAAAAAukBR/PEK3wjRD3L88QrfCBZDSVEuUExUUi5JUV9DQVBFWC4xMDAwAQAAAGX6mAICAAAABy0zMy44ODIBCAAAAAUAAAABMQEAAAALLTE5MDYxMjUzOTIDAAAAAzE2MAIAAAAEMjAyMQQAAAABMAcAAAAIOS80LzIwMjYIAAAACjEyLzMxLzIwMjUJAAAAATC6QFH88QrfCNEPcvzxCt8IFkNJUS5QTFRSLklRX0NBUEVYLjIwMDABAAAAZfqYAgIAAAAHLTQyLjAxOQEIAAAABQAAAAExAQAAAAstMTg3OTIyODY5OQMAAAADMTYwAgAAAAQyMDIxBAAAAAEwBwAAAAg5LzQvMjAyNggAAAAJNi8zMC8yMDI2CQAAAAEwukBR/PEK3wjRD3L88QrfCB5DSVEuUExUUi5JUV9TVE9DS19CQVNFRF9DRi45OTYBAAAAZfqYAgIAAAAHNzc4LjIxNQEIAAAABQAAAAExAQAAAAstMjAwOTU4NjMxMwMAAAADMTYwAgAAAAQyMTI3BAAAAAEwBwAAAAg5LzQvMjAyNggAAAAKMTIvMzEvMjAyMQkAAAABMLpAUfzxCt8I0Q9y/PEK3wgeQ0lRLlBMVFIuSVFfU1RPQ0tfQkFTRURfQ0YuOTk3AQAAAGX6mAICAAAABzU2NC43OTgBCAAAAAUAAAABMQEAAAALLTE5NTkyNjIwNzIDAAAAAzE2MAIAAAAEMjEyNwQA | AU1: AAABMAcAAAAIOS80LzIwMjYIAAAACjEyLzMxLzIwMjIJAAAAATC6QFH88QrfCNEPcvzxCt8IHkNJUS5QTFRSLklRX1NUT0NLX0JBU0VEX0NGLjk5OAEAAABl+pgCAgAAAAc0NzUuOTAzAQgAAAAFAAAAATEBAAAACy0xOTA2MTI1NDAzAwAAAAMxNjACAAAABDIxMjcEAAAAATAHAAAACDkvNC8yMDI2CAAAAAoxMi8zMS8yMDIzCQAAAAEwukBR/PEK3wjRD3L88QrfCBVDSVEuUExUUi5JUV9DQVBFWC45OTYBAAAAZfqYAgIAAAAHLTEyLjYyNwEIAAAABQAAAAExAQAAAAstMjAwOTU4NjMxMwMAAAADMTYwAgAAAAQyMDIxBAAAAAEwBwAAAAg5LzQvMjAyNggAAAAKMTIvMzEvMjAyMQkAAAABMLpAUfzxCt8I0Q9y/PEK3wgVQ0lRLlBMVFIuSVFfQ0FQRVguOTk3AQAAAGX6mAICAAAABy00MC4wMjcBCAAAAAUAAAABMQEAAAALLTE5NTkyNjIwNzIDAAAAAzE2MAIAAAAEMjAyMQQAAAABMAcAAAAIOS80LzIwMjYIAAAACjEyLzMxLzIwMjIJAAAAATC6QFH88QrfCNEPcvzxCt8IFUNJUS5QTFRSLklRX0NBUEVYLjk5OAEAAABl+pgCAgAAAActMTUuMTE0AQgAAAAFAAAAATEBAAAACy0xOTA2MTI1NDAzAwAAAAMxNjACAAAABDIwMjEEAAAAATAHAAAACDkvNC8yMDI2CAAAAAoxMi8zMS8yMDIzCQAAAAEwukBR/PEK3wjRD3L88QrfCBVDSVEuUExUUi5JUV9DQVBFWC45OTkBAAAAZfqYAgIAAAAHLTEyLjYzNAEIAAAABQAA | AV1: AAExAQAAAAstMTkwNjEyNTM4OAMAAAADMTYwAgAAAAQyMDIxBAAAAAEwBwAAAAg5LzQvMjAyNggAAAAKMTIvMzEvMjAyNAkAAAABMLpAUfzxCt8I0Q9y/PEK3wgSQ0lRLlBMVFIuSVFfTkkuOTk3AQAAAGX6mAICAAAACC0zNzMuNzA1AQgAAAAFAAAAATEBAAAACy0xOTU5MjYyMDcyAwAAAAMxNjACAAAAAjE1BAAAAAEwBwAAAAg5LzQvMjAyNggAAAAKMTIvMzEvMjAyMgkAAAABMLpAUfzxCt8I0Q9y/PEK3wgSQ0lRLlBMVFIuSVFfTkkuOTk4AQAAAGX6mAICAAAABzIwOS44MjUBCAAAAAUAAAABMQEAAAALLTE5MDYxMjU0MDMDAAAAAzE2MAIAAAACMTUEAAAAATAHAAAACDkvNC8yMDI2CAAAAAoxMi8zMS8yMDIzCQAAAAEwukBR/PEK3wjRD3L88QrfCBJDSVEuUExUUi5JUV9OSS45OTkBAAAAZfqYAgIAAAAGNDYyLjE5AQgAAAAFAAAAATEBAAAACy0xOTA2MTI1Mzg4AwAAAAMxNjACAAAAAjE1BAAAAAEwBwAAAAg5LzQvMjAyNggAAAAKMTIvMzEvMjAyNAkAAAABMLpAUfzxCt8I0Q9y/PEK3wgTQ0lRLlBMVFIuSVFfTkkuMTAwMAEAAABl+pgCAgAAAAgxNjI1LjAzMwEIAAAABQAAAAExAQAAAAstMTkwNjEyNTM5MgMAAAADMTYwAgAAAAIxNQQAAAABMAcAAAAIOS80LzIwMjYIAAAACjEyLzMxLzIwMjUJAAAAATC6QFH88QrfCNEPcvzxCt8IE0NJUS5QTFRSLklRX05JLjIwMDABAAAAZfqYAgIAAAAIMzAxNi42 | AW1: OTIBCAAAAAUAAAABMQEAAAALLTE4NzkyMjg2OTkDAAAAAzE2MAIAAAACMTUEAAAAATAHAAAACDkvNC8yMDI2CAAAAAk2LzMwLzIwMjYJAAAAATC6QFH88QrfCNEPcvzxCt8IFkNJUS5QTFRSLklRX0VCSVREQS45OTgBAAAAZfqYAgIAAAAGMTUzLjMyAQgAAAAFAAAAATEBAAAACy0xOTA2MTI1NDAzAwAAAAMxNjACAAAABDQwNTEEAAAAATAHAAAACDkvNC8yMDI2CAAAAAoxMi8zMS8yMDIzCQAAAAEwukBR/PEK3wjRD3L88QrfCBZDSVEuUExUUi5JUV9FQklUREEuOTk5AQAAAGX6mAICAAAABjM0MS45OQEIAAAABQAAAAExAQAAAAstMTkwNjEyNTM4OAMAAAADMTYwAgAAAAQ0MDUxBAAAAAEwBwAAAAg5LzQvMjAyNggAAAAKMTIvMzEvMjAyNAkAAAABMLpAUfzxCt8I0Q9y/PEK3wgXQ0lRLlBMVFIuSVFfRUJJVERBLjEwMDABAAAAZfqYAgIAAAAHMTQ0MC4xNgEIAAAABQAAAAExAQAAAAstMTkwNjEyNTM5MgMAAAADMTYwAgAAAAQ0MDUxBAAAAAEwBwAAAAg5LzQvMjAyNggAAAAKMTIvMzEvMjAyNQkAAAABMLpAUfzxCt8I0Q9y/PEK3wgXQ0lRLlBMVFIuSVFfRUJJVERBLjIwMDABAAAAZfqYAgIAAAAHMjY2Mi42MwEIAAAABQAAAAExAQAAAAstMTg3OTIyODY5OQMAAAADMTYwAgAAAAQ0MDUxBAAAAAEwBwAAAAg5LzQvMjAyNggAAAAJNi8zMC8yMDI2CQAAAAEwukBR/PEK3whRPnIE8grfCBJDSVEuUExUUi5J | AX1: UV9OSS45OTYBAAAAZfqYAgIAAAAILTUyMC4zNzkBCAAAAAUAAAABMQEAAAALLTIwMDk1ODYzMTMDAAAAAzE2MAIAAAACMTUEAAAAATAHAAAACDkvNC8yMDI2CAAAAAoxMi8zMS8yMDIxCQAAAAEwukBR/PEK3wjRD3L88QrfCBhDSVEuUExUUi5JUV9PUEVSX0lOQy45OTkBAAAAZfqYAgIAAAAHMzEwLjQwMwEIAAAABQAAAAExAQAAAAstMTkwNjEyNTM4OAMAAAADMTYwAgAAAAIyMQQAAAABMAcAAAAIOS80LzIwMjYIAAAACjEyLzMxLzIwMjQJAAAAATC6QFH88QrfCNEPcvzxCt8IGUNJUS5QTFRSLklRX09QRVJfSU5DLjEwMDABAAAAZfqYAgIAAAAIMTQxNC4wMTUBCAAAAAUAAAABMQEAAAALLTE5MDYxMjUzOTIDAAAAAzE2MAIAAAACMjEEAAAAATAHAAAACDkvNC8yMDI2CAAAAAoxMi8zMS8yMDI1CQAAAAEwukBR/PEK3wjRD3L88QrfCBlDSVEuUExUUi5JUV9PUEVSX0lOQy4yMDAwAQAAAGX6mAICAAAACDI2MzQuNjUyAQgAAAAFAAAAATEBAAAACy0xODc5MjI4Njk5AwAAAAMxNjACAAAAAjIxBAAAAAEwBwAAAAg5LzQvMjAyNggAAAAJNi8zMC8yMDI2CQAAAAEwukBR/PEK3wjRD3L88QrfCBZDSVEuUExUUi5JUV9FQklUREEuOTk2AQAAAGX6mAICAAAACC0zOTYuMTQ5AQgAAAAFAAAAATEBAAAACy0yMDA5NTg2MzEzAwAAAAMxNjACAAAABDQwNTEEAAAAATAHAAAACDkvNC8yMDI2CAAAAAoxMi8zMS8yMDIx | AY1: CQAAAAEwukBR/PEK3wjRD3L88QrfCBZDSVEuUExUUi5JUV9FQklUREEuOTk3AQAAAGX6mAICAAAACC0xMzguNjc5AQgAAAAFAAAAATEBAAAACy0xOTU5MjYyMDcyAwAAAAMxNjACAAAABDQwNTEEAAAAATAHAAAACDkvNC8yMDI2CAAAAAoxMi8zMS8yMDIyCQAAAAEwukBR/PEK3wjRD3L88QrfCBNDSVEuUExUUi5JUV9HUC4xMDAwAQAAAGX6mAICAAAACDM2ODYuMjY5AQgAAAAFAAAAATEBAAAACy0xOTA2MTI1MzkyAwAAAAMxNjACAAAAAjEwBAAAAAEwBwAAAAg5LzQvMjAyNggAAAAKMTIvMzEvMjAyNQkAAAABMLpAUfzxCt8I0Q9y/PEK3wgTQ0lRLlBMVFIuSVFfR1AuMjAwMAEAAABl+pgCAgAAAAQ1MjIwAQgAAAAFAAAAATEBAAAACy0xODc5MjI4Njk5AwAAAAMxNjACAAAAAjEwBAAAAAEwBwAAAAg5LzQvMjAyNggAAAAJNi8zMC8yMDI2CQAAAAEwukBR/PEK3wjRD3L88QrfCBhDSVEuUExUUi5JUV9PUEVSX0lOQy45OTYBAAAAZfqYAgIAAAAILTQxMS4wNDYBCAAAAAUAAAABMQEAAAALLTIwMDk1ODYzMTMDAAAAAzE2MAIAAAACMjEEAAAAATAHAAAACDkvNC8yMDI2CAAAAAoxMi8zMS8yMDIxCQAAAAEwukBR/PEK3wjRD3L88QrfCBhDSVEuUExUUi5JUV9PUEVSX0lOQy45OTcBAAAAZfqYAgIAAAAILTE2MS4yMDEBCAAAAAUAAAABMQEAAAALLTE5NTkyNjIwNzIDAAAAAzE2MAIAAAACMjEEAAAAATAHAAAA | AZ1: CDkvNC8yMDI2CAAAAAoxMi8zMS8yMDIyCQAAAAEwukBR/PEK3wjRD3L88QrfCBhDSVEuUExUUi5JUV9PUEVSX0lOQy45OTgBAAAAZfqYAgIAAAAHMTE5Ljk2NgEIAAAABQAAAAExAQAAAAstMTkwNjEyNTQwMwMAAAADMTYwAgAAAAIyMQQAAAABMAcAAAAIOS80LzIwMjYIAAAACjEyLzMxLzIwMjMJAAAAATC6QFH88QrfCNEPcvzxCt8IGkNJUS5QTFRSLklRX1RPVEFMX1JFVi4yMDAwAQAAAGX6mAICAAAACDYxNTUuOTQxAQgAAAAFAAAAATEBAAAACy0xODc5MjI4Njk5AwAAAAMxNjACAAAAAjI4BAAAAAEwBwAAAAg5LzQvMjAyNggAAAAJNi8zMC8yMDI2CQAAAAEwukBR/PEK3wjRD3L88QrfCBJDSVEuUExUUi5JUV9HUC45OTYBAAAAZfqYAgIAAAAIMTIwMi40ODUBCAAAAAUAAAABMQEAAAALLTIwMDk1ODYzMTMDAAAAAzE2MAIAAAACMTAEAAAAATAHAAAACDkvNC8yMDI2CAAAAAoxMi8zMS8yMDIxCQAAAAEwukBR/PEK3wjRD3L88QrfCBJDSVEuUExUUi5JUV9HUC45OTcBAAAAZfqYAgIAAAAIMTQ5Ny4zMjIBCAAAAAUAAAABMQEAAAALLTE5NTkyNjIwNzIDAAAAAzE2MAIAAAACMTAEAAAAATAHAAAACDkvNC8yMDI2CAAAAAoxMi8zMS8yMDIyCQAAAAEwukBR/PEK3wjRD3L88QrfCBJDSVEuUExUUi5JUV9HUC45OTgBAAAAZfqYAgIAAAAIMTc5My45MDcBCAAAAAUAAAABMQEAAAALLTE5MDYxMjU0MDMDAAAA | BA1: AzE2MAIAAAACMTAEAAAAATAHAAAACDkvNC8yMDI2CAAAAAoxMi8zMS8yMDIzCQAAAAEwukBR/PEK3wjRD3L88QrfCBJDSVEuUExUUi5JUV9HUC45OTkBAAAAZfqYAgIAAAAIMjI5OS41MTcBCAAAAAUAAAABMQEAAAALLTE5MDYxMjUzODgDAAAAAzE2MAIAAAACMTAEAAAAATAHAAAACDkvNC8yMDI2CAAAAAoxMi8zMS8yMDI0CQAAAAEwukBR/PEK3wjRD3L88QrfCBlDSVEuUExUUi5JUV9UT1RBTF9SRVYuOTk2AQAAAGX6mAICAAAACDE1NDEuODg5AQgAAAAFAAAAATEBAAAACy0yMDA5NTg2MzEzAwAAAAMxNjACAAAAAjI4BAAAAAEwBwAAAAg5LzQvMjAyNggAAAAKMTIvMzEvMjAyMQkAAAABMLpAUfzxCt8ISuhx/PEK3wgZQ0lRLlBMVFIuSVFfVE9UQUxfUkVWLjk5NwEAAABl+pgCAgAAAAgxOTA1Ljg3MQEIAAAABQAAAAExAQAAAAstMTk1OTI2MjA3MgMAAAADMTYwAgAAAAIyOAQAAAABMAcAAAAIOS80LzIwMjYIAAAACjEyLzMxLzIwMjIJAAAAATC6QFH88QrfCNEPcvzxCt8IGUNJUS5QTFRSLklRX1RPVEFMX1JFVi45OTgBAAAAZfqYAgIAAAAIMjIyNS4wMTIBCAAAAAUAAAABMQEAAAALLTE5MDYxMjU0MDMDAAAAAzE2MAIAAAACMjgEAAAAATAHAAAACDkvNC8yMDI2CAAAAAoxMi8zMS8yMDIzCQAAAAEwukBR/PEK3wjRD3L88QrfCBlDSVEuUExUUi5JUV9UT1RBTF9SRVYuOTk5AQAAAGX6mAICAAAACDI4 | BB1: NjUuNTA3AQgAAAAFAAAAATEBAAAACy0xOTA2MTI1Mzg4AwAAAAMxNjACAAAAAjI4BAAAAAEwBwAAAAg5LzQvMjAyNggAAAAKMTIvMzEvMjAyNAkAAAABMLpAUfzxCt8I0Q9y/PEK3wgaQ0lRLlBMVFIuSVFfVE9UQUxfUkVWLjEwMDABAAAAZfqYAgIAAAAINDQ3NS40NDYBCAAAAAUAAAABMQEAAAALLTE5MDYxMjUzOTIDAAAAAzE2MAIAAAACMjgEAAAAATAHAAAACDkvNC8yMDI2CAAAAAoxMi8zMS8yMDI1CQAAAAEwukBR/PEK3wjRD3L88QrfCCVDSVEuUExUUi5JUV9TSE9SVF9JTlRFUkVTVF9PVkVSX0ZMT0FUAQAAAGX6mAICAAAABTMuMjM2ALpAUfzxCt8ISuhx/PEK3wgfQ0lRLlBMVFIuSVFfQ1VSUkVOVF9SQVRJTy4xMDAwMAEAAABl+pgCAgAAAAg3LjEwOTgyMwEIAAAABQAAAAExAQAAAAstMTkwNjEyNDI1OAMAAAADMTYwAgAAAAQ0MDMwBAAAAAEwBwAAAAg5LzQvMjAyNggAAAAKMTIvMzEvMjAyNQkAAAABMLpAUfzxCt8ISuhx/PEK3wgdQ0lRLlBMVFIuSVFfUVVJQ0tfUkFUSU8uMTAwMDABAAAAZfqYAgIAAAAINi45OTE1MjgBCAAAAAUAAAABMQEAAAALLTE5MDYxMjQyNTgDAAAAAzE2MAIAAAAENDEyMQQAAAABMAcAAAAIOS80LzIwMjYIAAAACjEyLzMxLzIwMjUJAAAAATC6QFH88QrfCErocfzxCt8IGUNJUS5QTFRSLklRX0VCSVRfSU5ULjIwMDABAAAAZfqYAgMAAAAAALpAUfzxCt8ISuhx/PEK | BC1: 3wgZQ0lRLlBMVFIuSVFfR1dfSU5UQU4uNTAwMAEAAABl+pgCAwAAAAAAukBR/PEK3whK6HH88QrfCBpDSVEuUExUUi5JUV9UQlZfU0hBUkUuNTAwMAEAAABl+pgCAgAAAAg0LjA2NzY3MQEIAAAABQAAAAExAQAAAAstMTg3OTIzNDg3NAMAAAADMTYwAgAAAAQ0MTU2BAAAAAEwBwAAAAg5LzQvMjAyNggAAAAJNi8zMC8yMDI2CQAAAAEwukBR/PEK3whK6HH88QrfCCJDSVEuUExUUi5JUV9UT1RBTF9ERUJUX0VRVUlUWS41MDAwAQAAAGX6mAICAAAABjIuMTM4NgEIAAAABQAAAAExAQAAAAstMTg3OTIzNDg3NAMAAAADMTYwAgAAAAQ0MDM0BAAAAAEwBwAAAAg5LzQvMjAyNggAAAAJNi8zMC8yMDI2CQAAAAEwukBR/PEK3whK6HH88QrfCCBDSVEuUExUUi5JUV9DQVNIX09QRVIuLjA1LVNFUC0yNgEAAABl+pgCAgAAAAgzNDAwLjI5MQEIAAAABQAAAAExAQAAAAstMTg3OTIyODY5OQMAAAADMTYwAgAAAAQyMDA2BAAAAAEwBwAAAAg5LzUvMjAyNggAAAAJNi8zMC8yMDI2CQAAAAEwukBR/PEK3whRPnIE8grfCBxDSVEuUExUUi5JUV9DQVBFWC4uMDUtU0VQLTI2AQAAAGX6mAICAAAABy00Mi4wMTkBCAAAAAUAAAABMQEAAAALLTE4NzkyMjg2OTkDAAAAAzE2MAIAAAAEMjAyMQQAAAABMAcAAAAIOS81LzIwMjYIAAAACTYvMzAvMjAyNgkAAAABMLpAUfzxCt8IUT5yBPIK3wghQ0lRLlBMVFIuSVFfVE9UQUxfREVC | BD1: VC4uMDUtU0VQLTI2AQAAAGX6mAICAAAABTIxMS40AQgAAAAFAAAAATEBAAAACy0xODc5MjI4Njk5AwAAAAMxNjACAAAABDQxNzMEAAAAATAHAAAACDkvNS8yMDI2CAAAAAk2LzMwLzIwMjYJAAAAATC6QFH88QrfCFE+cgTyCt8IJUNJUS5QTFRSLklRX0NBU0hfU1RfSU5WRVNULi4wNS1TRVAtMjYBAAAAZfqYAgIAAAAIOTQwOS4wOTkBCAAAAAUAAAABMQEAAAALLTE4NzkyMjg2OTkDAAAAAzE2MAIAAAAEMTAwMgQAAAABMAcAAAAIOS81LzIwMjYIAAAACTYvMzAvMjAyNgkAAAABMLpAUfzxCt8IUT5yBPIK3wgdQ0lRLlBMVFIuSVFfQ0FTSF9PUEVSX0NTLjIwMDABAAAAZfqYAgIAAAAIMzQwMC4yOTEBCQAAAAUAAAACMTkBAAAACDI5OTkyMTg5AgAAAAUzMjgyNAkAAAACLTEDAAAAAzE2MAYAAAAIOC80LzIwMjYHAAAACDkvNC8yMDI2CAAAAAEwBAAAAAEwukBR/PEK3wjRD3L88QrfCBxDSVEuUExUUi5JUV9DQVNIX09QRVJfQ1MuOTk2AQAAAGX6mAICAAAABzMzMy44NTEBCQAAAAUAAAACMTkBAAAACDI1Mjk5NjQ4AgAAAAUzMjgyNAkAAAACLTEDAAAAAzE2MAYAAAAJMi8xNy8yMDIyBwAAAAg5LzQvMjAyNggAAAABMAQAAAABMLpAUfzxCt8I0Q9y/PEK3wgcQ0lRLlBMVFIuSVFfQ0FTSF9PUEVSX0NTLjk5NwEAAABl+pgCAgAAAAcyMjMuNzM3AQkAAAAFAAAAAjE5AQAAAAgyNjM2NDEzNAIAAAAFMzI4MjQJ | BE1: AAAAAi0xAwAAAAMxNjAGAAAACTIvMTQvMjAyMwcAAAAIOS80LzIwMjYIAAAAATAEAAAAATC6QFH88QrfCNEPcvzxCt8IHENJUS5QTFRSLklRX0NBU0hfT1BFUl9DUy45OTgBAAAAZfqYAgIAAAAHNzEyLjE4MwEJAAAABQAAAAIxOQEAAAAIMjc0MDEzMDcCAAAABTMyODI0CQAAAAItMQMAAAADMTYwBgAAAAgyLzYvMjAyNAcAAAAIOS80LzIwMjYIAAAAATAEAAAAATC6QFH88QrfCNEPcvzxCt8IHENJUS5QTFRSLklRX0NBU0hfT1BFUl9DUy45OTkBAAAAZfqYAgIAAAAIMTE1My44NjUBCQAAAAUAAAACMTkBAAAACDI4NDYxNzUyAgAAAAUzMjgyNAkAAAACLTEDAAAAAzE2MAYAAAAIMi80LzIwMjUHAAAACDkvNC8yMDI2CAAAAAEwBAAAAAEwukBR/PEK3wjRD3L88QrfCB1DSVEuUExUUi5JUV9DQVNIX09QRVJfQ1MuMTAwMAEAAABl+pgCAgAAAAgyMTM0LjQ3MwEJAAAABQAAAAIxOQEAAAAIMjk0NTgwNjMCAAAABTMyODI0CQAAAAItMQMAAAADMTYwBgAAAAgyLzMvMjAyNgcAAAAIOS80LzIwMjYIAAAAATAEAAAAATC6QFH88QrfCNEPcvzxCt8IHkNJUS5QTFRSLklRX0ZJTElOR19DVVJSRU5DWV9DUwEAAABl+pgCAwAAAANVU0QAukBR/PEK3whK6HH88QrfCDNDSVEuUExUUi5JUV9UT1RBTF9PVVRTVEFORElOR19CU19EQVRFX0NTLi4wNS1TRVAtMjYBAAAAZfqYAgIAAAAIMjQwMi44OTcBCQAAAAUAAAACMTkB | BF1: AAAACDI5OTkyMTg5AgAAAAUzMjY2MgkAAAACLTEDAAAAATAGAAAACDgvNC8yMDI2BwAAAAg5LzUvMjAyNggAAAABMAQAAAABMLpAUfzxCt8IUT5yBPIK3wgaQ0lRLlBMVFIuSVFfSU5TSURFUl9TSEFSRVMBAAAAZfqYAgEAAAAIOTgzMzUwMDABBQAAAAUAAAACMjEBAAAABjE2MTk1OQIAAAAINDM1ODAwMDUGAAAAATEHAAAAATG6QFH88QrfCAOFcvzxCt8IG0NJUS5QTFRSLklRX1RFVl9UT1RBTF9SRVYuLgEAAABl+pgCAgAAAA82Ni41NzYwNDAyNTQxODcBBwAAAAUAAAABMQEAAAALLTE4NzkyMjg2OTkDAAAAATACAAAABjEwMDA2MQQAAAABMAcAAAAIOS80LzIwMjYIAAAACDkvNC8yMDI2AVeY/PEK3wgsBqz88QrfCBhDSVEuUExUUi5JUV9URVZfRUJJVERBLi4BAAAAZfqYAgIAAAAQMTUwLjk2MjYwMTEyNDg5NAEHAAAABQAAAAExAQAAAAstMTg3OTIyODY5OQMAAAABMAIAAAAGMTAwMDYzBAAAAAEwBwAAAAg5LzQvMjAyNggAAAAIOS80LzIwMjYBV5j88QrfCCwGrPzxCt8IEUNJUS5QTFRSLklRX1BCVi4uAQAAAGX6mAICAAAAEDQyLjg1NzQ0ODQwMjI5MjEBBwAAAAUAAAABMQEAAAALLTE4NzkyMjg2OTkDAAAAATACAAAABjEwMDA2NwQAAAABMAcAAAAIOS80LzIwMjYIAAAACDkvNC8yMDI2AVeY/PEK3wgsBqz88QrfCBVDSVEuUExUUi5JUV9CRVRBXzVZUi4BAAAAZfqYAgIAAAAQMS42MjEzNTQ2ODAz | BG1: MDg5OQABV5j88QrfCCwGrPzxCt8IF0NJUS5QTFRSLklRX01BUktFVENBUC4uAQAAAGX6mAICAAAADTQxODkyNS4xODQ4MTgBBgAAAAUAAAABMQEAAAALLTE4NzkyMzQ4NzQDAAAAAzE2MAIAAAAGMTAwMDU0BAAAAAEwBwAAAAg5LzQvMjAyNgFXmPzxCt8ILAas/PEK3wgRQ0lRLlBMVFIuSVFfVEVWLi4BAAAAZfqYAgIAAAANNDA5ODM4LjE3NTgxOAEGAAAABQAAAAExAQAAAAstMTg3OTIzNDg3NAMAAAADMTYwAgAAAAYxMDAwNjAEAAAAATAHAAAACDkvNC8yMDI2AVeY/PEK3wgsBqz88QrfCBtDSVEuUExUUi5JUV9ESVZJREVORF9ZSUVMRC4BAAAAZfqYAgMAAAAAAAFXmPzxCt8ILAas/PEK3wgjQ0lRLlBMVFIuSVFfU0hBUkVTT1VUU1RBTkRJTkdfT1VULi4BAAAAZfqYAgIAAAALMjU0Ny40NDgyMzYAAVeY/PEK3wgsBqz88QrfCBBDSVEuUExUUi5JUV9URVYuAQAAAGX6mAICAAAADTQwOTgzOC4xNzU4MTgBBgAAAAUAAAABMQEAAAALLTE4NzkyMzQ4NzQDAAAAAzE2MAIAAAAGMTAwMDYwBAAAAAEwBwAAAAg5LzQvMjAyNgFXmPzxCt8ILAas/PEK3wgWQ0lRLlBMVFIuSVFfTUFSS0VUQ0FQLgEAAABl+pgCAgAAAA00MTg5MjUuMTg0ODE4AQYAAAAFAAAAATEBAAAACy0xODc5MjM0ODc0AwAAAAMxNjACAAAABjEwMDA1NAQAAAABMAcAAAAIOS80LzIwMjYBV5j88QrfCCwGrPzxCt8IF0NJUS5QTFRSLklRX0NM | BH1: T1NFUFJJQ0UuAQAAAGX6mAICAAAABjE3NC4zMwABV5j88QrfCCwGrPzxCt8IFENJUS5QTFRSLklRX1lFQVJMT1cuAQAAAGX6mAICAAAABjEwNi4zNwABV5j88QrfCCwGrPzxCt8IFUNJUS5QTFRSLklRX1lFQVJISUdILgEAAABl+pgCAgAAAAYyMDcuNTIAAVeY/PEK3wgsBqz88QrfCBhDSVEuUExUUi5JUV9UT1RBTF9ERUJULi4BAAAAZfqYAgIAAAAFMjExLjQBCAAAAAUAAAABMQEAAAALLTE4NzkyMjg2OTkDAAAAAzE2MAIAAAAENDE3MwQAAAABMAcAAAAIOS80LzIwMjYIAAAACTYvMzAvMjAyNgkAAAABMAFXmPzxCt8ILAas/PEK3wgcQ0lRLlBMVFIuSVFfQ0FTSF9TVF9JTlZFU1QuLgEAAABl+pgCAgAAAAg5NDA5LjA5OQEIAAAABQAAAAExAQAAAAstMTg3OTIyODY5OQMAAAADMTYwAgAAAAQxMDAyBAAAAAEwBwAAAAg5LzQvMjAyNggAAAAJNi8zMC8yMDI2CQAAAAEwAVeY/PEK3wgsBqz88QrfCCpDSVEuUExUUi5JUV9UT1RBTF9PVVRTVEFORElOR19CU19EQVRFX0NTLi4BAAAAZfqYAgIAAAAIMjQwMi44OTcBCQAAAAUAAAACMTkBAAAACDI5OTkyMTg5AgAAAAUzMjY2MgkAAAACLTEDAAAAATAGAAAACDgvNC8yMDI2BwAAAAg5LzQvMjAyNggAAAABMAQAAAABMAFXmPzxCt8ILAas/PEK3wgZQ0lRLkdNRS5JUV9JTlNUX09XTkVSU0hJUAUAAAAAAAAACAAAABYoSW52YWxpZCBGb3JtdWxhIE5hbWUpKujp | BI1: CPIK3whfxwwJ8grfCBZDSVEuR01FLklRX0lOU1RfU0hBUkVTBQAAAAAAAAAIAAAAFihJbnZhbGlkIEZvcm11bGEgTmFtZSkq6OkI8grfCADvDAnyCt8IHENJUS5HTUUuSVFfSU5TSURFUl9PV05FUlNISVAFAAAAAAAAAAgAAAAWKEludmFsaWQgRm9ybXVsYSBOYW1lKSro6QjyCt8IAO8MCfIK3wgaQ0lRLkdNRS5JUV9JTkRVU1RSWV9TRUNUT1IBAAAAYHwUAAMAAAAWQ29uc3VtZXIgRGlzY3JldGlvbmFyeQAq6OkI8grfCE15DAnyCt8IG0NJUS5HTUUuSVFfUFJJTUFSWV9JTkRVU1RSWQEAAABgfBQAAwAAAB9Db21wdXRlciBhbmQgRWxlY3Ryb25pY3MgUmV0YWlsACro6QjyCt8ITXkMCfIK3wgTQ0lRLkdNRS5JUV9FWENIQU5HRQEAAABgfBQAAwAAAAROWVNFACro6QjyCt8ITXkMCfIK3wgaQ0lRLkdNRS5JUV9DT01QQU5ZX0FERFJFU1MBAAAAYHwUAAMAAAA8NjI1IFdlc3Rwb3J0IFBhcmt3YXksIEdyYXBldmluZSwgVGV4YXMsIDc2MDUxLCBVbml0ZWQgU3RhdGVzACro6QjyCt8ITXkMCfIK3wgXQ0lRLkdNRS5JUV9DT01QQU5ZX05BTUUBAAAAYHwUAAMAAAAOR2FtZVN0b3AgQ29ycC4AKujpCPIK3whNeQwJ8grfCCdDSVFSQU5HRS5HTUUuSVFfTkVXUy4xLjI1Li4uLi5ORVdTIERBVEUDAAAAYHwUAAEAAAAAAAAAAwAAAAAAAAAFIkdNRSIDR01FAQAAAAkiSVFfTkVXUyIHSVFfTkVXUwIAAAABMQExP//p | BJ1: CPIK3wg//+kI8grfCBFDSVEuR01FLklRX05FV1MuMQEAAABgfBQAAwAAAE9HYW1lU3RvcCBjb25zaWRlcnMgd2l0aGRyYXdpbmcgZUJheSBiaWQ7IEludGVsIHBsYW5zICQxNUIgY29tbW9uLXN0b2NrIG9mZmVyaW5nAQMAAAAFAAAAAjE3AQAAAAkzMjI3Mzc5OTkCAAAABDc3NzE//+kI8grfCD6gDAnyCt8IK0NJUVJBTkdFLkdNRS5JUV9ORVdTLjEuMjUuLi4uLk5FV1MgSEVBRExJTkUDAAAAYHwUAAEAAAAAAAAAAwAAAAAAAAAFIkdNRSIDR01FAQAAAAkiSVFfTkVXUyIHSVFfTkVXUwIAAAABMQExP//pCPIK3wg//+kI8grfCClDSVFSQU5HRS5HTUUuSVFfTkVXUy4xLjI1Li4uLi5ORVdTIFNPVVJDRQMAAABgfBQAAQAAAAAAAAADAAAAAAAAAAUiR01FIgNHTUUBAAAACSJJUV9ORVdTIgdJUV9ORVdTAgAAAAExATE//+kI8grfCD//6QjyCt8IJkNJUVJBTkdFLkdNRS5JUV9ORVdTLjEuMjUuLi4uLk5FV1MgVVJMAwAAAGB8FAABAAAAAAAAAAMAAAAAAAAABSJHTUUiA0dNRQEAAAAJIklRX05FV1MiB0lRX05FV1MCAAAAATEBMT//6QjyCt8IP//pCPIK3wgbQ0lRLkdNRS5JUV9QUklDRV9TQUxFUy4yMDAwAQAAAGB8FAACAAAAEDIuMjk5MTQzODA4OTI1MzEBBwAAAAUAAAABMQEAAAALLTE4ODQ0Mjg2MTYDAAAAATACAAAABTM4OTU4BAAAAAEwBwAAAAg5LzQvMjAyNggAAAAIOS80LzIwMjY//+kI8grfCE15 | BK1: DAnyCt8IF0NJUS5HTUUuSVFfUEVfRVhDTC4yMDAwAQAAAGB8FAACAAAAEDE0LjI3MDY5MDI2NjQzNTkBBwAAAAUAAAABMQEAAAALLTE4ODQ0Mjg2MTYDAAAAATACAAAABjEwMDA2NgQAAAABMAcAAAAIOS80LzIwMjYIAAAACDkvNC8yMDI2P//pCPIK3whNeQwJ8grfCCNDSVEuR01FLklRX1RFVl9UT1RBTF9SRVYuLjA1LVNFUC0yNgEAAABgfBQAAgAAAA8xLjIyMzcyNjAxOTEwNjMBBwAAAAUAAAABMQEAAAALLTE4ODQ0Mjg2MTYDAAAAATACAAAABjEwMDA2MQQAAAABMAcAAAAIOS80LzIwMjYIAAAACDkvNC8yMDI2P//pCPIK3wjRVyIT8grfCBlDSVEuR01FLklRX1BCVi4uMDUtU0VQLTI2AQAAAGB8FAACAAAAEDEuNDcxNTc1NzM4ODc3MzMBBwAAAAUAAAABMQEAAAALLTE4ODQ0Mjg2MTYDAAAAATACAAAABjEwMDA2NwQAAAABMAcAAAAIOS80LzIwMjYIAAAACDkvNC8yMDI2P//pCPIK3wjRVyIT8grfCCBDSVEuR01FLklRX1RFVl9FQklUREEuLjA1LVNFUC0yNgEAAABgfBQAAgAAABA3LjIzNjMxNjAxNDQ0NzUyAQcAAAAFAAAAATEBAAAACy0xODg0NDI4NjE2AwAAAAEwAgAAAAYxMDAwNjMEAAAAATAHAAAACDkvNC8yMDI2CAAAAAg5LzQvMjAyNj//6QjyCt8I0VciE/IK3wgdQ0lRLkdNRS5JUV9CRVRBXzVZUi4wNS1TRVAtMjYBAAAAYHwUAAIAAAAQMS43MTM5ODA5NTg5NTg0OQA//+kI8grfCNFXIhPy | BL1: Ct8IGUNJUS5HTUUuSVFfVEVWLi4wNS1TRVAtMjYBAAAAYHwUAAIAAAALNDU2Ny45MjQ0ODQBBgAAAAUAAAABMQEAAAALLTE4ODQ0Mjk3MjgDAAAAAzE2MAIAAAAGMTAwMDYwBAAAAAEwBwAAAAg5LzQvMjAyNj//6QjyCt8I0VciE/IK3wgfQ0lRLkdNRS5JUV9NQVJLRVRDQVAuLjA1LVNFUC0yNgEAAABgfBQAAgAAAAs4NTk2LjkyNDQ4NAEGAAAABQAAAAExAQAAAAstMTg4NDQyOTcyOAMAAAADMTYwAgAAAAYxMDAwNTQEAAAAATAHAAAACDkvNC8yMDI2P//pCPIK3wjRVyIT8grfCCtDSVEuR01FLklRX1NIQVJFU09VVFNUQU5ESU5HX09VVC4uMDUtU0VQLTI2AQAAAGB8FAACAAAACjQ0OC42OTEyNTcAP//pCPIK3wjRVyIT8grfCCNDSVEuR01FLklRX0RJVklERU5EX1lJRUxELjA1LVNFUC0yNgEAAABgfBQAAwAAAAAAP//pCPIK3wjRVyIT8grfCB1DSVEuR01FLklRX1lFQVJISUdILjA1LVNFUC0yNgEAAABgfBQAAgAAAAQyOC4xAD//6QjyCt8I0VciE/IK3wgcQ0lRLkdNRS5JUV9ZRUFSTE9XLjA1LVNFUC0yNgEAAABgfBQAAgAAAAUxNy43OQA//+kI8grfCNFXIhPyCt8IH0NJUS5HTUUuSVFfQ0xPU0VQUklDRS4wNS1TRVAtMjYBAAAAYHwUAAIAAAAFMTkuMTYAP//pCPIK3wjRVyIT8grfCB5DSVEuR01FLklRX01BUktFVENBUC4wNS1TRVAtMjYBAAAAYHwUAAIAAAALODU5Ni45MjQ0ODQBBgAAAAUAAAAB | BM1: MQEAAAALLTE4ODQ0Mjk3MjgDAAAAAzE2MAIAAAAGMTAwMDU0BAAAAAEwBwAAAAg5LzQvMjAyNj//6QjyCt8I0VciE/IK3wgYQ0lRLkdNRS5JUV9URVYuMDUtU0VQLTI2AQAAAGB8FAACAAAACzQ1NjcuOTI0NDg0AQYAAAAFAAAAATEBAAAACy0xODg0NDI5NzI4AwAAAAMxNjACAAAABjEwMDA2MAQAAAABMAcAAAAIOS80LzIwMjY//+kI8grfCNFXIhPyCt8IGENJUUFWRy5HTUUuSVFfVk9MVU1FLi0zTQEAAABgfBQAAgAAABA1LjYxNTAzOTk4NDYxNTM4AD//6QjyCt8ITXkMCfIK3wggQ0lRLkdNRS5JUV9QRV9FWENMX0ZXRF9DSVEuMTAwMDABAAAAYHwUAAMAAAAAAD//6QjyCt8ITXkMCfIK3wgXQ0lRLkdNRS5JUV9QRUdfRldELjYwMDABAAAAYHwUAAMAAAAAAD//6QjyCt8ITXkMCfIK3wgfQ0lRLkdNRS5JUV9QRV9FWENMX0ZXRF9DSVEuNjAwMAEAAABgfBQAAgAAABAxNC41NDI2OTQ0OTcxNTM3AQ0AAAAFAAAAATkBAAAACDI0MjY4MzM1AgAAAAk3MDUyOTc3MDIDAAAABjEwMDMwOQQAAAABMgYAAAABMAcAAAADMTYwCAAAAAEwCQAAAAExCgAAAAEwCwAAAAsxNDk0MDAwNTYzMgwAAAACMTINAAAACDkvNS8yMDI2P//pCPIK3whNeQwJ8grfCB1DSVEuR01FLklRX0ZJTElOR19DVVJSRU5DWV9DUwEAAABgfBQAAwAAAANVU0QAP//pCPIK3whNeQwJ8grfCBtDSVEuR01FLklRX0NBU0hfT1BFUl9DUy45OTYB | BN1: AAAAYHwUAAIAAAAGLTQzNC4zAQkAAAAFAAAAAjE5AQAAAAgyNTQwMTUzNAIAAAAFMzI4MjQJAAAAAi0xAwAAAAMxNjAGAAAACTMvMTgvMjAyMgcAAAAIOS80LzIwMjYIAAAAATAEAAAAATA//+kI8grfCEdSDAnyCt8IG0NJUS5HTUUuSVFfQ0FTSF9PUEVSX0NTLjk5NwEAAABgfBQAAgAAAAUxMDguMgEJAAAABQAAAAIxOQEAAAAIMjY1Mjg4MDcCAAAABTMyODI0CQAAAAItMQMAAAADMTYwBgAAAAg0LzgvMjAyMwcAAAAIOS80LzIwMjYIAAAAATAEAAAAATA//+kI8grfCEdSDAnyCt8IG0NJUS5HTUUuSVFfQ0FTSF9PUEVSX0NTLjk5OAEAAABgfBQAAgAAAAYtMjAzLjcBCQAAAAUAAAACMTkBAAAACDI3NTcxNzkzAgAAAAUzMjgyNAkAAAACLTEDAAAAAzE2MAYAAAAJMy8yNy8yMDI0BwAAAAg5LzQvMjAyNggAAAABMAQAAAABMD//6QjyCt8IR1IMCfIK3wgbQ0lRLkdNRS5JUV9DQVNIX09QRVJfQ1MuOTk5AQAAAGB8FAACAAAABTE0NS43AQkAAAAFAAAAAjE5AQAAAAgyODYyNTg3MgIAAAAFMzI4MjQJAAAAAi0xAwAAAAMxNjAGAAAACTMvMjYvMjAyNQcAAAAIOS80LzIwMjYIAAAAATAEAAAAATA//+kI8grfCEdSDAnyCt8IHENJUS5HTUUuSVFfQ0FTSF9PUEVSX0NTLjEwMDABAAAAYHwUAAIAAAAFNTkyLjMBCQAAAAUAAAACMTkBAAAACDI5NjEyMjkyAgAAAAUzMjgyNAkAAAACLTEDAAAAAzE2MAYAAAAINC8x | BO1: LzIwMjYHAAAACDkvNC8yMDI2CAAAAAEwBAAAAAEwP//pCPIK3whHUgwJ8grfCBxDSVEuR01FLklRX0NBU0hfT1BFUl9DUy4yMDAwAQAAAGB8FAACAAAABTc4Ni42AQkAAAAFAAAAAjE5AQAAAAgyOTg1MTU4OQIAAAAFMzI4MjQJAAAAAi0xAwAAAAMxNjAGAAAACTYvMTcvMjAyNgcAAAAIOS80LzIwMjYIAAAAATAEAAAAATA//+kI8grfCEdSDAnyCt8IMkNJUS5HTUUuSVFfVE9UQUxfT1VUU1RBTkRJTkdfQlNfREFURV9DUy4uMDUtU0VQLTI2AQAAAGB8FAACAAAABTQ0OC43AQkAAAAFAAAAAjE5AQAAAAgyOTg1MTU4OQIAAAAFMzI2NjIJAAAAAi0xAwAAAAEwBgAAAAk2LzE3LzIwMjYHAAAACDkvNS8yMDI2CAAAAAEwBAAAAAEwP//pCPIK3wjRVyIT8grfCBlDSVEuR01FLklRX1RCVl9TSEFSRS41MDAwAQAAAGB8FAACAAAACTEzLjAyMDA1NwEIAAAABQAAAAExAQAAAAstMTg4NDQyOTcyOAMAAAADMTYwAgAAAAQ0MTU2BAAAAAEwBwAAAAg5LzQvMjAyNggAAAAINS8yLzIwMjYJAAAAATA//+kI8grfCE15DAnyCt8IIUNJUS5HTUUuSVFfVE9UQUxfREVCVF9FUVVJVFkuNTAwMAEAAABgfBQAAgAAAAc3NC4yNzI5AQgAAAAFAAAAATEBAAAACy0xODg0NDI5NzI4AwAAAAMxNjACAAAABDQwMzQEAAAAATAHAAAACDkvNC8yMDI2CAAAAAg1LzIvMjAyNgkAAAABMD//6QjyCt8ITXkMCfIK3wgkQ0lRLkdNRS5JUV9T | BP1: SE9SVF9JTlRFUkVTVF9PVkVSX0ZMT0FUAQAAAGB8FAACAAAABzEzLjIxNzkAP//pCPIK3whNeQwJ8grfCB5DSVEuR01FLklRX0NVUlJFTlRfUkFUSU8uMTAwMDABAAAAYHwUAAIAAAAJMTUuMjk2NTYyAQgAAAAFAAAAATEBAAAACy0xOTAwMzk2NjI2AwAAAAMxNjACAAAABDQwMzAEAAAAATAHAAAACDkvNC8yMDI2CAAAAAkxLzMxLzIwMjYJAAAAATA//+kI8grfCE15DAnyCt8IHENJUS5HTUUuSVFfUVVJQ0tfUkFUSU8uMTAwMDABAAAAYHwUAAIAAAAJMTMuODQwNzk0AQgAAAAFAAAAATEBAAAACy0xOTAwMzk2NjI2AwAAAAMxNjACAAAABDQxMjEEAAAAATAHAAAACDkvNC8yMDI2CAAAAAkxLzMxLzIwMjYJAAAAATA//+kI8grfCE15DAnyCt8IGENJUS5HTUUuSVFfRUJJVF9JTlQuMjAwMAEAAABgfBQAAwAAAAAAP//pCPIK3whNeQwJ8grfCBhDSVEuR01FLklRX0dXX0lOVEFOLjUwMDABAAAAYHwUAAMAAAAAAD//6QjyCt8ITXkMCfIK3wgYQ0lRLkdNRS5JUV9UT1RBTF9SRVYuOTk2AQAAAGB8FAACAAAABjYwMTAuNwEIAAAABQAAAAExAQAAAAstMjAwNDY2MDYxMwMAAAADMTYwAgAAAAIyOAQAAAABMAcAAAAIOS80LzIwMjYIAAAACTEvMjkvMjAyMgkAAAABMD//6QjyCt8ITXkMCfIK3wgYQ0lRLkdNRS5JUV9UT1RBTF9SRVYuOTk3AQAAAGB8FAACAAAABjU5MjcuMgEIAAAABQAAAAExAQAAAAstMTk1NDQ2 | BQ1: NjAyOAMAAAADMTYwAgAAAAIyOAQAAAABMAcAAAAIOS80LzIwMjYIAAAACTEvMjgvMjAyMwkAAAABMD//6QjyCt8ITXkMCfIK3wgYQ0lRLkdNRS5JUV9UT1RBTF9SRVYuOTk4AQAAAGB8FAACAAAABjUyNzIuOAEIAAAABQAAAAExAQAAAAstMTkwMDM5NzAzNAMAAAADMTYwAgAAAAIyOAQAAAABMAcAAAAIOS80LzIwMjYIAAAACDIvMy8yMDI0CQAAAAEwP//pCPIK3whNeQwJ8grfCBhDSVEuR01FLklRX1RPVEFMX1JFVi45OTkBAAAAYHwUAAIAAAAEMzgyMwEIAAAABQAAAAExAQAAAAstMTkwMDM5NzAyNwMAAAADMTYwAgAAAAIyOAQAAAABMAcAAAAIOS80LzIwMjYIAAAACDIvMS8yMDI1CQAAAAEwP//pCPIK3whNeQwJ8grfCBlDSVEuR01FLklRX1RPVEFMX1JFVi4xMDAwAQAAAGB8FAACAAAABjM2MjkuOQEIAAAABQAAAAExAQAAAAstMTkwMDM5NzAxNgMAAAADMTYwAgAAAAIyOAQAAAABMAcAAAAIOS80LzIwMjYIAAAACTEvMzEvMjAyNgkAAAABMD//6QjyCt8ITXkMCfIK3wgZQ0lRLkdNRS5JUV9UT1RBTF9SRVYuMjAwMAEAAABgfBQAAgAAAAYzNzMyLjgBCAAAAAUAAAABMQEAAAALLTE4ODQ0Mjg2MTYDAAAAAzE2MAIAAAACMjgEAAAAATAHAAAACDkvNC8yMDI2CAAAAAg1LzIvMjAyNgkAAAABMD//6QjyCt8ITXkMCfIK3wgRQ0lRLkdNRS5JUV9HUC45OTYBAAAAYHwUAAIAAAAGMTM0Ny44AQgAAAAFAAAA | BR1: ATEBAAAACy0yMDA0NjYwNjEzAwAAAAMxNjACAAAAAjEwBAAAAAEwBwAAAAg5LzQvMjAyNggAAAAJMS8yOS8yMDIyCQAAAAEwP//pCPIK3whNeQwJ8grfCBFDSVEuR01FLklRX0dQLjk5NwEAAABgfBQAAgAAAAYxMzcyLjEBCAAAAAUAAAABMQEAAAALLTE5NTQ0NjYwMjgDAAAAAzE2MAIAAAACMTAEAAAAATAHAAAACDkvNC8yMDI2CAAAAAkxLzI4LzIwMjMJAAAAATA//+kI8grfCE15DAnyCt8IEUNJUS5HTUUuSVFfR1AuOTk4AQAAAGB8FAACAAAABjEyOTQuMgEIAAAABQAAAAExAQAAAAstMTkwMDM5NzAzNAMAAAADMTYwAgAAAAIxMAQAAAABMAcAAAAIOS80LzIwMjYIAAAACDIvMy8yMDI0CQAAAAEwP//pCPIK3whNeQwJ8grfCBFDSVEuR01FLklRX0dQLjk5OQEAAABgfBQAAgAAAAYxMTEzLjkBCAAAAAUAAAABMQEAAAALLTE5MDAzOTcwMjcDAAAAAzE2MAIAAAACMTAEAAAAATAHAAAACDkvNC8yMDI2CAAAAAgyLzEvMjAyNQkAAAABMD//6QjyCt8ITXkMCfIK3wgSQ0lRLkdNRS5JUV9HUC4xMDAwAQAAAGB8FAACAAAABjExOTYuMQEIAAAABQAAAAExAQAAAAstMTkwMDM5NzAxNgMAAAADMTYwAgAAAAIxMAQAAAABMAcAAAAIOS80LzIwMjYIAAAACTEvMzEvMjAyNgkAAAABMD//6QjyCt8IR1IMCfIK3wgSQ0lRLkdNRS5JUV9HUC4yMDAwAQAAAGB8FAACAAAABjEyODMuNgEIAAAABQAAAAExAQAAAAstMTg4 | BS1: NDQyODYxNgMAAAADMTYwAgAAAAIxMAQAAAABMAcAAAAIOS80LzIwMjYIAAAACDUvMi8yMDI2CQAAAAEwP//pCPIK3whHUgwJ8grfCBdDSVEuR01FLklRX09QRVJfSU5DLjk5NgEAAABgfBQAAgAAAAYtMzgwLjQBCAAAAAUAAAABMQEAAAALLTIwMDQ2NjA2MTMDAAAAAzE2MAIAAAACMjEEAAAAATAHAAAACDkvNC8yMDI2CAAAAAkxLzI5LzIwMjIJAAAAATA//+kI8grfCEdSDAnyCt8IF0NJUS5HTUUuSVFfT1BFUl9JTkMuOTk3AQAAAGB8FAACAAAABi0zNjMuNQEIAAAABQAAAAExAQAAAAstMTk1NDQ2NjAyOAMAAAADMTYwAgAAAAIyMQQAAAABMAcAAAAIOS80LzIwMjYIAAAACTEvMjgvMjAyMwkAAAABMD//6QjyCt8IR1IMCfIK3wgXQ0lRLkdNRS5JUV9PUEVSX0lOQy45OTgBAAAAYHwUAAIAAAAFLTMxLjcBCAAAAAUAAAABMQEAAAALLTE5MDAzOTcwMzQDAAAAAzE2MAIAAAACMjEEAAAAATAHAAAACDkvNC8yMDI2CAAAAAgyLzMvMjAyNAkAAAABMD//6QjyCt8IR1IMCfIK3wgXQ0lRLkdNRS5JUV9PUEVSX0lOQy45OTkBAAAAYHwUAAIAAAAFLTE3LjQBCAAAAAUAAAABMQEAAAALLTE5MDAzOTcwMjcDAAAAAzE2MAIAAAACMjEEAAAAATAHAAAACDkvNC8yMDI2CAAAAAgyLzEvMjAyNQkAAAABMD//6QjyCt8IR1IMCfIK3wgYQ0lRLkdNRS5JUV9PUEVSX0lOQy4xMDAwAQAAAGB8FAACAAAABTI4NC44AQgAAAAF | BT1: AAAAATEBAAAACy0xOTAwMzk3MDE2AwAAAAMxNjACAAAAAjIxBAAAAAEwBwAAAAg5LzQvMjAyNggAAAAJMS8zMS8yMDI2CQAAAAEwP//pCPIK3whHUgwJ8grfCBhDSVEuR01FLklRX09QRVJfSU5DLjIwMDABAAAAYHwUAAIAAAAFMzk4LjgBCAAAAAUAAAABMQEAAAALLTE4ODQ0Mjg2MTYDAAAAAzE2MAIAAAACMjEEAAAAATAHAAAACDkvNC8yMDI2CAAAAAg1LzIvMjAyNgkAAAABMD//6QjyCt8IR1IMCfIK3wgVQ0lRLkdNRS5JUV9FQklUREEuOTk2AQAAAGB8FAACAAAABi0zMDMuMgEIAAAABQAAAAExAQAAAAstMjAwNDY2MDYxMwMAAAADMTYwAgAAAAQ0MDUxBAAAAAEwBwAAAAg5LzQvMjAyNggAAAAJMS8yOS8yMDIyCQAAAAEwP//pCPIK3whHUgwJ8grfCBVDSVEuR01FLklRX0VCSVREQS45OTcBAAAAYHwUAAIAAAAGLTMwMS44AQgAAAAFAAAAATEBAAAACy0xOTU0NDY2MDI4AwAAAAMxNjACAAAABDQwNTEEAAAAATAHAAAACDkvNC8yMDI2CAAAAAkxLzI4LzIwMjMJAAAAATA//+kI8grfCEdSDAnyCt8IFUNJUS5HTUUuSVFfRUJJVERBLjk5OAEAAABgfBQAAgAAAAQyNC41AQgAAAAFAAAAATEBAAAACy0xOTAwMzk3MDM0AwAAAAMxNjACAAAABDQwNTEEAAAAATAHAAAACDkvNC8yMDI2CAAAAAgyLzMvMjAyNAkAAAABMD//6QjyCt8IR1IMCfIK3wgVQ0lRLkdNRS5JUV9FQklUREEuOTk5AQAAAGB8FAACAAAA | BU1: BDIxLjUBCAAAAAUAAAABMQEAAAALLTE5MDAzOTcwMjcDAAAAAzE2MAIAAAAENDA1MQQAAAABMAcAAAAIOS80LzIwMjYIAAAACDIvMS8yMDI1CQAAAAEwP//pCPIK3whHUgwJ8grfCBZDSVEuR01FLklRX0VCSVREQS4xMDAwAQAAAGB8FAACAAAABTI5OS40AQgAAAAFAAAAATEBAAAACy0xOTAwMzk3MDE2AwAAAAMxNjACAAAABDQwNTEEAAAAATAHAAAACDkvNC8yMDI2CAAAAAkxLzMxLzIwMjYJAAAAATA//+kI8grfCEdSDAnyCt8IFkNJUS5HTUUuSVFfRUJJVERBLjIwMDABAAAAYHwUAAIAAAAFNDEyLjMBCAAAAAUAAAABMQEAAAALLTE4ODQ0Mjg2MTYDAAAAAzE2MAIAAAAENDA1MQQAAAABMAcAAAAIOS80LzIwMjYIAAAACDUvMi8yMDI2CQAAAAEwP//pCPIK3wjUbCIT8grfCBFDSVEuR01FLklRX05JLjk5NgEAAABgfBQAAgAAAAYtMzgxLjMBCAAAAAUAAAABMQEAAAALLTIwMDQ2NjA2MTMDAAAAAzE2MAIAAAACMTUEAAAAATAHAAAACDkvNC8yMDI2CAAAAAkxLzI5LzIwMjIJAAAAATA//+kI8grfCEdSDAnyCt8IEUNJUS5HTUUuSVFfTkkuOTk3AQAAAGB8FAACAAAABi0zMTMuMQEIAAAABQAAAAExAQAAAAstMTk1NDQ2NjAyOAMAAAADMTYwAgAAAAIxNQQAAAABMAcAAAAIOS80LzIwMjYIAAAACTEvMjgvMjAyMwkAAAABMD//6QjyCt8IR1IMCfIK3wgRQ0lRLkdNRS5JUV9OSS45OTgBAAAAYHwUAAIAAAAD | BV1: Ni43AQgAAAAFAAAAATEBAAAACy0xOTAwMzk3MDM0AwAAAAMxNjACAAAAAjE1BAAAAAEwBwAAAAg5LzQvMjAyNggAAAAIMi8zLzIwMjQJAAAAATA//+kI8grfCEdSDAnyCt8IEUNJUS5HTUUuSVFfTkkuOTk5AQAAAGB8FAACAAAABTEzMS4zAQgAAAAFAAAAATEBAAAACy0xOTAwMzk3MDI3AwAAAAMxNjACAAAAAjE1BAAAAAEwBwAAAAg5LzQvMjAyNggAAAAIMi8xLzIwMjUJAAAAATA//+kI8grfCEdSDAnyCt8IEkNJUS5HTUUuSVFfTkkuMTAwMAEAAABgfBQAAgAAAAU0MTguNAEIAAAABQAAAAExAQAAAAstMTkwMDM5NzAxNgMAAAADMTYwAgAAAAIxNQQAAAABMAcAAAAIOS80LzIwMjYIAAAACTEvMzEvMjAyNgkAAAABMD//6QjyCt8IR1IMCfIK3wgSQ0lRLkdNRS5JUV9OSS4yMDAwAQAAAGB8FAACAAAABTc2My4yAQgAAAAFAAAAATEBAAAACy0xODg0NDI4NjE2AwAAAAMxNjACAAAAAjE1BAAAAAEwBwAAAAg5LzQvMjAyNggAAAAINS8yLzIwMjYJAAAAATA//+kI8grfCEdSDAnyCt8IFENJUS5HTUUuSVFfQ0FQRVguOTk2AQAAAGB8FAACAAAAAy02MgEIAAAABQAAAAExAQAAAAstMjAwNDY2MDYxMwMAAAADMTYwAgAAAAQyMDIxBAAAAAEwBwAAAAg5LzQvMjAyNggAAAAJMS8yOS8yMDIyCQAAAAEwP//pCPIK3whHUgwJ8grfCBRDSVEuR01FLklRX0NBUEVYLjk5NwEAAABgfBQAAgAAAAUtNTUuOQEIAAAABQAA | BW1: AAExAQAAAAstMTk1NDQ2NjAyOAMAAAADMTYwAgAAAAQyMDIxBAAAAAEwBwAAAAg5LzQvMjAyNggAAAAJMS8yOC8yMDIzCQAAAAEwP//pCPIK3whHUgwJ8grfCBRDSVEuR01FLklRX0NBUEVYLjk5OAEAAABgfBQAAgAAAAUtMzQuOQEIAAAABQAAAAExAQAAAAstMTkwMDM5NzAzNAMAAAADMTYwAgAAAAQyMDIxBAAAAAEwBwAAAAg5LzQvMjAyNggAAAAIMi8zLzIwMjQJAAAAATA//+kI8grfCEdSDAnyCt8IFENJUS5HTUUuSVFfQ0FQRVguOTk5AQAAAGB8FAACAAAABS0xNi4xAQgAAAAFAAAAATEBAAAACy0xOTAwMzk3MDI3AwAAAAMxNjACAAAABDIwMjEEAAAAATAHAAAACDkvNC8yMDI2CAAAAAgyLzEvMjAyNQkAAAABMD//6QjyCt8IR1IMCfIK3wgVQ0lRLkdNRS5JUV9DQVBFWC4xMDAwAQAAAGB8FAACAAAABS0xNy41AQgAAAAFAAAAATEBAAAACy0xOTAwMzk3MDE2AwAAAAMxNjACAAAABDIwMjEEAAAAATAHAAAACDkvNC8yMDI2CAAAAAkxLzMxLzIwMjYJAAAAATA//+kI8grfCEdSDAnyCt8IFUNJUS5HTUUuSVFfQ0FQRVguMjAwMAEAAABgfBQAAgAAAAUtMTkuMQEIAAAABQAAAAExAQAAAAstMTg4NDQyODYxNgMAAAADMTYwAgAAAAQyMDIxBAAAAAEwBwAAAAg5LzQvMjAyNggAAAAINS8yLzIwMjYJAAAAATA//+kI8grfCEdSDAnyCt8IHUNJUS5HTUUuSVFfU1RPQ0tfQkFTRURfQ0YuOTk2AQAAAGB8FAAC | BX1: AAAABDMwLjUBCAAAAAUAAAABMQEAAAALLTIwMDQ2NjA2MTMDAAAAAzE2MAIAAAAEMjEyNwQAAAABMAcAAAAIOS80LzIwMjYIAAAACTEvMjkvMjAyMgkAAAABMD//6QjyCt8IR1IMCfIK3wgdQ0lRLkdNRS5JUV9TVE9DS19CQVNFRF9DRi45OTcBAAAAYHwUAAIAAAAENDAuMQEIAAAABQAAAAExAQAAAAstMTk1NDQ2NjAyOAMAAAADMTYwAgAAAAQyMTI3BAAAAAEwBwAAAAg5LzQvMjAyNggAAAAJMS8yOC8yMDIzCQAAAAEwP//pCPIK3whHUgwJ8grfCB1DSVEuR01FLklRX1NUT0NLX0JBU0VEX0NGLjk5OAEAAABgfBQAAgAAAAQyMi4yAQgAAAAFAAAAATEBAAAACy0xOTAwMzk3MDM0AwAAAAMxNjACAAAABDIxMjcEAAAAATAHAAAACDkvNC8yMDI2CAAAAAgyLzMvMjAyNAkAAAABMD//6QjyCt8IR1IMCfIK3wgdQ0lRLkdNRS5JUV9TVE9DS19CQVNFRF9DRi45OTkBAAAAYHwUAAIAAAAEMTYuNAEIAAAABQAAAAExAQAAAAstMTkwMDM5NzAyNwMAAAADMTYwAgAAAAQyMTI3BAAAAAEwBwAAAAg5LzQvMjAyNggAAAAIMi8xLzIwMjUJAAAAATA//+kI8grfCEdSDAnyCt8IHkNJUS5HTUUuSVFfU1RPQ0tfQkFTRURfQ0YuMTAwMAEAAABgfBQAAgAAAAQyNi43AQgAAAAFAAAAATEBAAAACy0xOTAwMzk3MDE2AwAAAAMxNjACAAAABDIxMjcEAAAAATAHAAAACDkvNC8yMDI2CAAAAAkxLzMxLzIwMjYJAAAAATA//+kI8grf | BY1: CEdSDAnyCt8IHkNJUS5HTUUuSVFfU1RPQ0tfQkFTRURfQ0YuMjAwMAEAAABgfBQAAgAAAAQyOS43AQgAAAAFAAAAATEBAAAACy0xODg0NDI4NjE2AwAAAAMxNjACAAAABDIxMjcEAAAAATAHAAAACDkvNC8yMDI2CAAAAAg1LzIvMjAyNgkAAAABMD//6QjyCt8IR1IMCfIK3wggQ0lRLkdNRS5JUV9UT1RBTF9ESVZfUEFJRF9DRi45OTYBAAAAYHwUAAMAAAAAAD//6QjyCt8IR1IMCfIK3wggQ0lRLkdNRS5JUV9UT1RBTF9ESVZfUEFJRF9DRi45OTcBAAAAYHwUAAMAAAAAAD//6QjyCt8IR1IMCfIK3wggQ0lRLkdNRS5JUV9UT1RBTF9ESVZfUEFJRF9DRi45OTgBAAAAYHwUAAMAAAAAAD//6QjyCt8IR1IMCfIK3wggQ0lRLkdNRS5JUV9UT1RBTF9ESVZfUEFJRF9DRi45OTkBAAAAYHwUAAMAAAAAAD//6QjyCt8IR1IMCfIK3wghQ0lRLkdNRS5JUV9UT1RBTF9ESVZfUEFJRF9DRi4xMDAwAQAAAGB8FAADAAAAAAA//+kI8grfCEdSDAnyCt8IIUNJUS5HTUUuSVFfVE9UQUxfRElWX1BBSURfQ0YuMjAwMAEAAABgfBQAAwAAAAAAP//pCPIK3whHUgwJ8grfCBlDSVEuR01FLklRX0NPTU1PTl9SRVAuOTk2AQAAAGB8FAADAAAAAAA//+kI8grfCEdSDAnyCt8IGUNJUS5HTUUuSVFfQ09NTU9OX1JFUC45OTcBAAAAYHwUAAMAAAAAAD//6QjyCt8IR1IMCfIK3wgZQ0lRLkdNRS5JUV9DT01NT05fUkVQLjk5OAEAAABgfBQA | BZ1: AgAAAAQtOS41AQgAAAAFAAAAATEBAAAACy0xOTAwMzk3MDM0AwAAAAMxNjACAAAABDIxNjQEAAAAATAHAAAACDkvNC8yMDI2CAAAAAgyLzMvMjAyNAkAAAABMD//6QjyCt8IR1IMCfIK3wgZQ0lRLkdNRS5JUV9DT01NT05fUkVQLjk5OQEAAABgfBQAAgAAAAQtOC43AQgAAAAFAAAAATEBAAAACy0xOTAwMzk3MDI3AwAAAAMxNjACAAAABDIxNjQEAAAAATAHAAAACDkvNC8yMDI2CAAAAAgyLzEvMjAyNQkAAAABMD//6QjyCt8IR1IMCfIK3wgaQ0lRLkdNRS5JUV9DT01NT05fUkVQLjEwMDABAAAAYHwUAAIAAAAELTkuOQEIAAAABQAAAAExAQAAAAstMTkwMDM5NzAxNgMAAAADMTYwAgAAAAQyMTY0BAAAAAEwBwAAAAg5LzQvMjAyNggAAAAJMS8zMS8yMDI2CQAAAAEwP//pCPIK3whHUgwJ8grfCBpDSVEuR01FLklRX0NPTU1PTl9SRVAuMjAwMAEAAABgfBQAAgAAAAUtMTAuNQEIAAAABQAAAAExAQAAAAstMTg4NDQyODYxNgMAAAADMTYwAgAAAAQyMTY0BAAAAAEwBwAAAAg5LzQvMjAyNggAAAAINS8yLzIwMjYJAAAAATA//+kI8grfCNFXIhPyCt8IHUNJUS5HTUUuSVFfQ0FTSF9TVF9JTlZFU1QuOTk2AQAAAGB8FAACAAAABjEyNzEuNAEIAAAABQAAAAExAQAAAAstMjAwNDY2MDYxMwMAAAADMTYwAgAAAAQxMDAyBAAAAAEwBwAAAAg5LzQvMjAyNggAAAAJMS8yOS8yMDIyCQAAAAEwP//pCPIK3wg4KwwJ8grf | CA1: CB1DSVEuR01FLklRX0NBU0hfU1RfSU5WRVNULjk5NwEAAABgfBQAAgAAAAYxMzkwLjYBCAAAAAUAAAABMQEAAAALLTE5NTQ0NjYwMjgDAAAAAzE2MAIAAAAEMTAwMgQAAAABMAcAAAAIOS80LzIwMjYIAAAACTEvMjgvMjAyMwkAAAABMD//6QjyCt8IOCsMCfIK3wgdQ0lRLkdNRS5JUV9DQVNIX1NUX0lOVkVTVC45OTgBAAAAYHwUAAIAAAAGMTE5OS4zAQgAAAAFAAAAATEBAAAACy0xOTAwMzk3MDM0AwAAAAMxNjACAAAABDEwMDIEAAAAATAHAAAACDkvNC8yMDI2CAAAAAgyLzMvMjAyNAkAAAABMD//6QjyCt8IOCsMCfIK3wgdQ0lRLkdNRS5JUV9DQVNIX1NUX0lOVkVTVC45OTkBAAAAYHwUAAIAAAAGNDc3NC45AQgAAAAFAAAAATEBAAAACy0xOTAwMzk3MDI3AwAAAAMxNjACAAAABDEwMDIEAAAAATAHAAAACDkvNC8yMDI2CAAAAAgyLzEvMjAyNQkAAAABMD//6QjyCt8IR1IMCfIK3wgeQ0lRLkdNRS5JUV9DQVNIX1NUX0lOVkVTVC4xMDAwAQAAAGB8FAACAAAABjkwMTMuOAEIAAAABQAAAAExAQAAAAstMTkwMDM5NzAxNgMAAAADMTYwAgAAAAQxMDAyBAAAAAEwBwAAAAg5LzQvMjAyNggAAAAJMS8zMS8yMDI2CQAAAAEwP//pCPIK3whHUgwJ8grfCB5DSVEuR01FLklRX0NBU0hfU1RfSU5WRVNULjIwMDABAAAAYHwUAAIAAAAGODM2OC4xAQgAAAAFAAAAATEBAAAACy0xODg0NDI4NjE2AwAAAAMxNjACAAAA | CB1: BDEwMDIEAAAAATAHAAAACDkvNC8yMDI2CAAAAAg1LzIvMjAyNgkAAAABMD//6QjyCt8IOCsMCfIK3wgZQ0lRLkdNRS5JUV9UT1RBTF9ERUJULjk5NgEAAABgfBQAAgAAAAM2NDkBCAAAAAUAAAABMQEAAAALLTIwMDQ2NjA2MTMDAAAAAzE2MAIAAAAENDE3MwQAAAABMAcAAAAIOS80LzIwMjYIAAAACTEvMjkvMjAyMgkAAAABMD//6QjyCt8IOCsMCfIK3wgZQ0lRLkdNRS5JUV9UT1RBTF9ERUJULjk5NwEAAABgfBQAAgAAAAU2MTYuNgEIAAAABQAAAAExAQAAAAstMTk1NDQ2NjAyOAMAAAADMTYwAgAAAAQ0MTczBAAAAAEwBwAAAAg5LzQvMjAyNggAAAAJMS8yOC8yMDIzCQAAAAEwP//pCPIK3wg4KwwJ8grfCBlDSVEuR01FLklRX1RPVEFMX0RFQlQuOTk4AQAAAGB8FAACAAAABTYwMi44AQgAAAAFAAAAATEBAAAACy0xOTAwMzk3MDM0AwAAAAMxNjACAAAABDQxNzMEAAAAATAHAAAACDkvNC8yMDI2CAAAAAgyLzMvMjAyNAkAAAABMD//6QjyCt8IOCsMCfIK3wgZQ0lRLkdNRS5JUV9UT1RBTF9ERUJULjk5OQEAAABgfBQAAgAAAAU0MTAuNwEIAAAABQAAAAExAQAAAAstMTkwMDM5NzAyNwMAAAADMTYwAgAAAAQ0MTczBAAAAAEwBwAAAAg5LzQvMjAyNggAAAAIMi8xLzIwMjUJAAAAATA//+kI8grfCDgrDAnyCt8IGkNJUS5HTUUuSVFfVE9UQUxfREVCVC4xMDAwAQAAAGB8FAACAAAABjQzNjEuOQEIAAAABQAA | CC1: AAExAQAAAAstMTkwMDM5NzAxNgMAAAADMTYwAgAAAAQ0MTczBAAAAAEwBwAAAAg5LzQvMjAyNggAAAAJMS8zMS8yMDI2CQAAAAEwP//pCPIK3wg4KwwJ8grfCBpDSVEuR01FLklRX1RPVEFMX0RFQlQuMjAwMAEAAABgfBQAAgAAAAY0MzM5LjEBCAAAAAUAAAABMQEAAAALLTE4ODQ0Mjg2MTYDAAAAAzE2MAIAAAAENDE3MwQAAAABMAcAAAAIOS80LzIwMjYIAAAACDUvMi8yMDI2CQAAAAEwP//pCPIK3wg4KwwJ8grfCBtDSVEuR01FLklRX1RPVEFMX0VRVUlUWS45OTYBAAAAYHwUAAIAAAAGMTYwMi41AQgAAAAFAAAAATEBAAAACy0yMDA0NjYwNjEzAwAAAAMxNjACAAAABDEyNzUEAAAAATAHAAAACDkvNC8yMDI2CAAAAAkxLzI5LzIwMjIJAAAAATA//+kI8grfCDgrDAnyCt8IG0NJUS5HTUUuSVFfVE9UQUxfRVFVSVRZLjk5NwEAAABgfBQAAgAAAAYxMzIyLjMBCAAAAAUAAAABMQEAAAALLTE5NTQ0NjYwMjgDAAAAAzE2MAIAAAAEMTI3NQQAAAABMAcAAAAIOS80LzIwMjYIAAAACTEvMjgvMjAyMwkAAAABMD//6QjyCt8IOCsMCfIK3wgbQ0lRLkdNRS5JUV9UT1RBTF9FUVVJVFkuOTk4AQAAAGB8FAACAAAABjEzMzguNgEIAAAABQAAAAExAQAAAAstMTkwMDM5NzAzNAMAAAADMTYwAgAAAAQxMjc1BAAAAAEwBwAAAAg5LzQvMjAyNggAAAAIMi8zLzIwMjQJAAAAATA//+kI8grfCDgrDAnyCt8IG0NJUS5HTUUu | CD1: SVFfVE9UQUxfRVFVSVRZLjk5OQEAAABgfBQAAgAAAAY0OTI5LjgBCAAAAAUAAAABMQEAAAALLTE5MDAzOTcwMjcDAAAAAzE2MAIAAAAEMTI3NQQAAAABMAcAAAAIOS80LzIwMjYIAAAACDIvMS8yMDI1CQAAAAEwP//pCPIK3wg4KwwJ8grfCBxDSVEuR01FLklRX1RPVEFMX0VRVUlUWS4xMDAwAQAAAGB8FAACAAAABjU0NDQuNAEIAAAABQAAAAExAQAAAAstMTkwMDM5NzAxNgMAAAADMTYwAgAAAAQxMjc1BAAAAAEwBwAAAAg5LzQvMjAyNggAAAAJMS8zMS8yMDI2CQAAAAEwP//pCPIK3wg4KwwJ8grfCBxDSVEuR01FLklRX1RPVEFMX0VRVUlUWS4yMDAwAQAAAGB8FAACAAAABjU4NDIuMQEIAAAABQAAAAExAQAAAAstMTg4NDQyODYxNgMAAAADMTYwAgAAAAQxMjc1BAAAAAEwBwAAAAg5LzQvMjAyNggAAAAINS8yLzIwMjYJAAAAATA//+kI8grfCDgrDAnyCt8IG0NJUS5HTUUuSVFfVE9UQUxfQVNTRVRTLjk5NgEAAABgfBQAAgAAAAYzNDk5LjMBCAAAAAUAAAABMQEAAAALLTIwMDQ2NjA2MTMDAAAAAzE2MAIAAAAEMTAwNwQAAAABMAcAAAAIOS80LzIwMjYIAAAACTEvMjkvMjAyMgkAAAABMD//6QjyCt8IOCsMCfIK3wgbQ0lRLkdNRS5JUV9UT1RBTF9BU1NFVFMuOTk3AQAAAGB8FAACAAAABjMxMTMuNAEIAAAABQAAAAExAQAAAAstMTk1NDQ2NjAyOAMAAAADMTYwAgAAAAQxMDA3BAAAAAEwBwAAAAg5LzQv | CE1: MjAyNggAAAAJMS8yOC8yMDIzCQAAAAEwP//pCPIK3wg4KwwJ8grfCBtDSVEuR01FLklRX1RPVEFMX0FTU0VUUy45OTgBAAAAYHwUAAIAAAAEMjcwOQEIAAAABQAAAAExAQAAAAstMTkwMDM5NzAzNAMAAAADMTYwAgAAAAQxMDA3BAAAAAEwBwAAAAg5LzQvMjAyNggAAAAIMi8zLzIwMjQJAAAAATA//+kI8grfCDgrDAnyCt8IG0NJUS5HTUUuSVFfVE9UQUxfQVNTRVRTLjk5OQEAAABgfBQAAgAAAAY1ODc1LjQBCAAAAAUAAAABMQEAAAALLTE5MDAzOTcwMjcDAAAAAzE2MAIAAAAEMTAwNwQAAAABMAcAAAAIOS80LzIwMjYIAAAACDIvMS8yMDI1CQAAAAEwP//pCPIK3wg4KwwJ8grfCBxDSVEuR01FLklRX1RPVEFMX0FTU0VUUy4xMDAwAQAAAGB8FAACAAAABzEwMzg4LjQBCAAAAAUAAAABMQEAAAALLTE5MDAzOTcwMTYDAAAAAzE2MAIAAAAEMTAwNwQAAAABMAcAAAAIOS80LzIwMjYIAAAACTEvMzEvMjAyNgkAAAABMD//6QjyCt8IOCsMCfIK3wgcQ0lRLkdNRS5JUV9UT1RBTF9BU1NFVFMuMjAwMAEAAABgfBQAAgAAAAcxMDk3NC4zAQgAAAAFAAAAATEBAAAACy0xODg0NDI4NjE2AwAAAAMxNjACAAAABDEwMDcEAAAAATAHAAAACDkvNC8yMDI2CAAAAAg1LzIvMjAyNgkAAAABMD//6QjyCt8IOCsMCfIK3wgbQ0lRLkdNRS5JUV9ESUxVVF9XRUlHSFQuOTk2AQAAAGB8FAACAAAABTI5MC40AD//6QjyCt8IOCsM | CF1: CfIK3wgbQ0lRLkdNRS5JUV9ESUxVVF9XRUlHSFQuOTk3AQAAAGB8FAACAAAABTMwNC4yAD//6QjyCt8IOCsMCfIK3wgbQ0lRLkdNRS5JUV9ESUxVVF9XRUlHSFQuOTk4AQAAAGB8FAACAAAABTMwNS4yAD//6QjyCt8IOCsMCfIK3wgbQ0lRLkdNRS5JUV9ESUxVVF9XRUlHSFQuOTk5AQAAAGB8FAACAAAABTM5NC43AD//6QjyCt8IOCsMCfIK3wgcQ0lRLkdNRS5JUV9ESUxVVF9XRUlHSFQuMTAwMAEAAABgfBQAAgAAAAU1NDkuMQA//+kI8grfCDgrDAnyCt8IHENJUS5HTUUuSVFfRElMVVRfV0VJR0hULjIwMDABAAAAYHwUAAIAAAAFNTcyLjcAP//pCPIK3wg4KwwJ8grfCB9DSVEuR01FLklRX0NBU0hfT1BFUi4uMDUtU0VQLTI2AQAAAGB8FAACAAAABTc1OS43AQgAAAAFAAAAATEBAAAACy0xODg0NDI4NjE2AwAAAAMxNjACAAAABDIwMDYEAAAAATAHAAAACDkvNS8yMDI2CAAAAAg1LzIvMjAyNgkAAAABMD//6QjyCt8I0VciE/IK3wgbQ0lRLkdNRS5JUV9DQVBFWC4uMDUtU0VQLTI2AQAAAGB8FAACAAAABS0xOS4xAQgAAAAFAAAAATEBAAAACy0xODg0NDI4NjE2AwAAAAMxNjACAAAABDIwMjEEAAAAATAHAAAACDkvNS8yMDI2CAAAAAg1LzIvMjAyNgkAAAABMD//6QjyCt8I0VciE/IK3wgkQ0lRLkdNRS5JUV9DQVNIX1NUX0lOVkVTVC4uMDUtU0VQLTI2AQAAAGB8FAACAAAABjgzNjguMQEIAAAABQAAAAEx | CG1: AQAAAAstMTg4NDQyODYxNgMAAAADMTYwAgAAAAQxMDAyBAAAAAEwBwAAAAg5LzUvMjAyNggAAAAINS8yLzIwMjYJAAAAATA//+kI8grfCNFXIhPyCt8IIENJUS5HTUUuSVFfVE9UQUxfREVCVC4uMDUtU0VQLTI2AQAAAGB8FAACAAAABjQzMzkuMQEIAAAABQAAAAExAQAAAAstMTg4NDQyODYxNgMAAAADMTYwAgAAAAQ0MTczBAAAAAEwBwAAAAg5LzUvMjAyNggAAAAINS8yLzIwMjYJAAAAATA//+kI8grfCNFXIhPyCt8IGUNJUS5HTUUuSVFfSU5TSURFUl9TSEFSRVMBAAAAYHwUAAEAAAAIMzgzNDc4NDIBBQAAAAUAAAACMjEBAAAACTI3NDcxMzY4NAIAAAAHMTM0MjU2MAYAAAABMQcAAAABMT//6QjyCt8IAO8MCfIK3wgUQ0lRLkdNRS5JUV9CRVRBXzVZUi4BAAAAYHwUAAIAAAAQMS43MTM5ODA5NTg5NTg0OQDLczEJ8grfCPNKRAnyCt8IKUNJUS5HTUUuSVFfVE9UQUxfT1VUU1RBTkRJTkdfQlNfREFURV9DUy4uAQAAAGB8FAACAAAABTQ0OC43AQkAAAAFAAAAAjE5AQAAAAgyOTg1MTU4OQIAAAAFMzI2NjIJAAAAAi0xAwAAAAEwBgAAAAk2LzE3LzIwMjYHAAAACDkvNC8yMDI2CAAAAAEwBAAAAAEwy3MxCfIK3wjzSkQJ8grfCBdDSVEuR01FLklRX1RFVl9FQklUREEuLgEAAABgfBQAAgAAABA3LjIzNjMxNjAxNDQ0NzUyAQcAAAAFAAAAATEBAAAACy0xODg0NDI4NjE2AwAAAAEwAgAAAAYxMDAwNjMEAAAA | CH1: ATAHAAAACDkvNC8yMDI2CAAAAAg5LzQvMjAyNstzMQnyCt8I80pECfIK3wgQQ0lRLkdNRS5JUV9QQlYuLgEAAABgfBQAAgAAABAxLjQ3MTU3NTczODg3NzMzAQcAAAAFAAAAATEBAAAACy0xODg0NDI4NjE2AwAAAAEwAgAAAAYxMDAwNjcEAAAAATAHAAAACDkvNC8yMDI2CAAAAAg5LzQvMjAyNstzMQnyCt8I80pECfIK3wgaQ0lRLkdNRS5JUV9URVZfVE9UQUxfUkVWLi4BAAAAYHwUAAIAAAAPMS4yMjM3MjYwMTkxMDYzAQcAAAAFAAAAATEBAAAACy0xODg0NDI4NjE2AwAAAAEwAgAAAAYxMDAwNjEEAAAAATAHAAAACDkvNC8yMDI2CAAAAAg5LzQvMjAyNstzMQnyCt8I80pECfIK3wgTQ0lRLkdNRS5JUV9ZRUFSTE9XLgEAAABgfBQAAgAAAAUxNy43OQDLczEJ8grfCPNKRAnyCt8IFkNJUS5HTUUuSVFfQ0xPU0VQUklDRS4BAAAAYHwUAAIAAAAFMTkuMTYAy3MxCfIK3wjzSkQJ8grfCBVDSVEuR01FLklRX01BUktFVENBUC4BAAAAYHwUAAIAAAALODU5Ni45MjQ0ODQBBgAAAAUAAAABMQEAAAALLTE4ODQ0Mjk3MjgDAAAAAzE2MAIAAAAGMTAwMDU0BAAAAAEwBwAAAAg5LzQvMjAyNstzMQnyCt8I80pECfIK3wgPQ0lRLkdNRS5JUV9URVYuAQAAAGB8FAACAAAACzQ1NjcuOTI0NDg0AQYAAAAFAAAAATEBAAAACy0xODg0NDI5NzI4AwAAAAMxNjACAAAABjEwMDA2MAQAAAABMAcAAAAIOS80LzIwMjbLczEJ8grf | CI1: CPNKRAnyCt8IIkNJUS5HTUUuSVFfU0hBUkVTT1VUU1RBTkRJTkdfT1VULi4BAAAAYHwUAAIAAAAKNDQ4LjY5MTI1NwDLczEJ8grfCPNKRAnyCt8IGkNJUS5HTUUuSVFfRElWSURFTkRfWUlFTEQuAQAAAGB8FAADAAAAAADLczEJ8grfCPNKRAnyCt8IFENJUS5HTUUuSVFfWUVBUkhJR0guAQAAAGB8FAACAAAABDI4LjEAy3MxCfIK3wjzSkQJ8grfCBZDSVEuR01FLklRX01BUktFVENBUC4uAQAAAGB8FAACAAAACzg1OTYuOTI0NDg0AQYAAAAFAAAAATEBAAAACy0xODg0NDI5NzI4AwAAAAMxNjACAAAABjEwMDA1NAQAAAABMAcAAAAIOS80LzIwMjbLczEJ8grfCLEkRAnyCt8IEENJUS5HTUUuSVFfVEVWLi4BAAAAYHwUAAIAAAALNDU2Ny45MjQ0ODQBBgAAAAUAAAABMQEAAAALLTE4ODQ0Mjk3MjgDAAAAAzE2MAIAAAAGMTAwMDYwBAAAAAEwBwAAAAg5LzQvMjAyNstzMQnyCt8I80pECfIK3wgXQ0lRLkdNRS5JUV9UT1RBTF9ERUJULi4BAAAAYHwUAAIAAAAGNDMzOS4xAQgAAAAFAAAAATEBAAAACy0xODg0NDI4NjE2AwAAAAMxNjACAAAABDQxNzMEAAAAATAHAAAACDkvNC8yMDI2CAAAAAg1LzIvMjAyNgkAAAABMMtzMQnyCt8IsSRECfIK3wgbQ0lRLkdNRS5JUV9DQVNIX1NUX0lOVkVTVC4uAQAAAGB8FAACAAAABjgzNjguMQEIAAAABQAAAAExAQAAAAstMTg4NDQyODYxNgMAAAADMTYwAgAAAAQxMDAyBAAA | CJ1: AAEwBwAAAAg5LzQvMjAyNggAAAAINS8yLzIwMjYJAAAAATDLczEJ8grfCLEkRAnyCt8I

Sheet Snapshot
A1: DENNIS — data · latest snapshot (formulas pre-filled)
B2: Refinitiv | C2: Capital IQ | D2: RIC override (optional, wins if set) →
A3: Ticker / RIC -> | B3: =IF($E$2<>"",$E$2,C3&_RICMap!$E$1) | C3: GME
A4: Green=auto add-in formula (verify mnemonic in last col). Grey=computed. Yellow=you set. % in points; currency absolute.
A6: Section | B6: field_key | C6: Label | D6: Value (Capital IQ) MM | E6: Field mnemonic (verify) | F6: Priority
A7: Identity | B7: company_name | C7: Company Name | D7: =_xll.ciqfunctions.udf.CIQ(C3, "IQ_COMPANY_NAME") | E7: TR.CommonName | F7: Required
B8: ticker | C8: Ticker | D8: =$C$3 | E8: plain ticker (RIC lives in B3, used by Peers) | F8: Required
B9: exchange | C9: Exchange | D9: =_xll.ciqfunctions.udf.CIQ(C3, "IQ_EXCHANGE") | E9: TR.ExchangeName | F9: Recommended
B10: sector | C10: GICS Sector | D10: =_xll.ciqfunctions.udf.CIQ(C3, "IQ_INDUSTRY_SECTOR") | E10: TR.GICSSector | F10: Recommended
B11: industry | C11: Industry | D11: =_xll.ciqfunctions.udf.CIQ(C3, "IQ_PRIMARY_INDUSTRY") | E11: TR.GICSIndustry | F11: Optional
B12: country | C12: Country | D12: =TRIM(RIGHT(SUBSTITUTE(_xll.ciqfunctions.udf.CIQ(C3,"IQ_COMPANY_ADDRESS"),",",REPT(" ",200)),200)) | E12: computed: the last part of IQ_COMPANY_ADDRESS (the whole address before) | F12: Optional
B13: currency | C13: Reporting Currency | D13: =_xll.ciqfunctions.udf.CIQ(C3, "IQ_FILING_CURRENCY_CS") | E13: TR.FinancialCurrency | F13: Recommended
B14: as_of_date | C14: As-of Date | D14: =TODAY() | F14: Required
A15: Price & Size | B15: price | C15: Price | D15: =_xll.ciqfunctions.udf.CIQ(C3, "IQ_CLOSEPRICE", D14) | E15: TR.PriceClose | F15: Required
B16: market_cap | C16: Market Cap | D16: =_xll.ciqfunctions.udf.CIQ(C3, "IQ_MARKETCAP", D14) | E16: TR.CompanyMarketCap | F16: Required
B17: enterprise_value | C17: Enterprise Value | D17: =_xll.ciqfunctions.udf.CIQ(C3, "IQ_TEV", D14) | E17: TR.EV | F17: Recommended
B18: shares_out | C18: Shares Outstanding | D18: =_xll.ciqfunctions.udf.CIQ(C3, "IQ_TOTAL_OUTSTANDING_BS_DATE_CS", , D14) | E18: TR.SharesOutstanding | F18: Required
B19: shares_dill_out | C19: Diluted Shares (latest quarter) | D19: =Quarters!J22 | E19: computed: Quarters!J22, IQ_DILUT_WEIGHT for the latest quarter (IQ_SHARESOUTSTANDING_OUT was the basic count again) | F19: Optional
B20: avg_volume_3m | C20: Avg Daily Volume (3m) | D20: =_xll.ciqfunctions.udf.CIQAVG(C3, "IQ_VOLUME", "-3M") | E20: TR.AvgDailyVolume3M | F20: Optional
B21: beta | C21: Beta (5y) | D21: =_xll.ciqfunctions.udf.CIQ(C3, "IQ_BETA_5YR", D14) | E21: TR.Beta | F21: Optional
B22: week52_high | C22: 52-Week High | D22: =_xll.ciqfunctions.udf.CIQ(C3, "IQ_YEARHIGH", D14) | E22: TR.Price52WeekHigh | F22: Recommended
B23: week52_low | C23: 52-Week Low | D23: =_xll.ciqfunctions.udf.CIQ(C3, "IQ_YEARLOW", D14) | E23: TR.Price52WeekLow | F23: Recommended
B24: pct_from_52w_high | C24: % From 52w High | D24: =D15/D22-1 | E24: computed | F24: Recommended
A25: Valuation (now) | B25: pe_ttm | C25: P/E (TTM) | D25: =_xll.ciqfunctions.udf.CIQ(C3, "IQ_PE_EXCL", IQ_LTM) | E25: TR.PE | F25: Required
B26: forward_pe | C26: Forward P/E | D26: =_xll.ciqfunctions.udf.CIQ(C3, "IQ_PE_EXCL_FWD_CIQ", IQ_NTM) | E26: IQ_PE_EXCL_FWD_CIQ | F26: Recommended
B27: ps_ttm | C27: P/S (TTM) | D27: =_xll.ciqfunctions.udf.CIQ(C3, "IQ_PRICE_SALES", IQ_LTM) | E27: TR.PriceToSalesPerShare | F27: Required
B28: ev_ebitda | C28: EV / EBITDA | D28: =_xll.ciqfunctions.udf.CIQ(C3, "IQ_TEV_EBITDA", , D14) | E28: TR.EVToEBITDA | F28: Required
B29: ev_sales | C29: EV / Sales | D29: =_xll.ciqfunctions.udf.CIQ(C3, "IQ_TEV_TOTAL_REV", , D14) | E29: TR.EVToSales | F29: Recommended
B30: ev_fcf | C30: EV / FCF | D30: =IF(N(History!H15)>0,D17/History!H15,"") | E30: computed: EV / LTM free cash flow; blank when FCF is not positive | F30: Recommended
B31: pb | C31: P / B | D31: =_xll.ciqfunctions.udf.CIQ(C3, "IQ_PBV", , D14) | E31: TR.PriceToBVPerShare | F31: Recommended
B32: p_fcf | C32: P / FCF | D32: =IF(N(History!H15)>0,D16/History!H15,"") | E32: computed: market cap / LTM free cash flow; blank when FCF is not positive | F32: Recommended
B33: peg | C33: PEG | D33: =_xll.ciqfunctions.udf.CIQ(C3, "IQ_PEG_FWD", IQ_NTM) | E33: TR.PEG | F33: Optional
B34: earnings_yield | C34: Earnings Yield (%) | D34: =IF(N(D16)>0,IFERROR(History!H11/D16,""),"") | E34: computed: LTM net income / market cap (negative for a loss) | F34: Recommended
B35: fcf_yield | C35: FCF Yield (%) | D35: =IF(N(D16)>0,IFERROR(History!H15/D16,""),"") | E35: computed: LTM free cash flow / market cap (the LSEG RDP.Data call here showed #NAME?) | F35: Required
B36: dividend_yield | C36: Dividend Yield (%) | D36: =IFERROR(_xll.ciqfunctions.udf.CIQ(C3, "IQ_DIVIDEND_YIELD", D14)/100,"") | F36: Optional
B37: buyback_yield | C37: Buyback Yield (%) | D37: =IFERROR(-_xll.ciqfunctions.udf.CIQ(C3,"IQ_COMMON_REP",IQ_LTM)/D16,"") | E37: TR.BuybackYield | F37: Optional
B38: shareholder_yield | C38: Shareholder Yield (%) | D38: =IF(AND(NOT(ISNUMBER(D36)),NOT(ISNUMBER(D37))),"",N(D36)+N(D37)) | E38: computed | F38: Recommended
A39: Balance (now) | B39: cash_st | C39: Cash & ST Investments | D39: =_xll.ciqfunctions.udf.CIQ(C3, "IQ_CASH_ST_INVEST", , D14) | E39: TR.CashAndSTInvestments | F39: Required
B40: total_debt_now | C40: Total Debt | D40: =_xll.ciqfunctions.udf.CIQ(C3, "IQ_TOTAL_DEBT", , D14) | E40: TR.TotalDebtOutstanding | F40: Required
B41: net_debt_now | C41: Net Debt | D41: =D40-D39 | E41: computed | F41: Recommended
B42: net_debt_ebitda_now | C42: Net Debt / EBITDA | D42: =IF(N(History!H10)>0,D41/History!H10,"") | E42: computed: net debt / LTM EBITDA; blank when EBITDA is not positive | F42: Recommended
B43: debt_to_equity | C43: Debt / Equity (%) | D43: =_xll.ciqfunctions.udf.CIQ(C3, "IQ_TOTAL_DEBT_EQUITY", IQ_CQ)/100 | E43: TR.TotalDebtToTotalEquityPct | F43: Recommended
B44: current_ratio | C44: Current Ratio as of last quarter | D44: =_xll.ciqfunctions.udf.CIQ(C3, "IQ_CURRENT_RATIO", IQ_CQ) | E44: TR.CurrentRatio | F44: Optional
B45: quick_ratio | C45: Quick Ratio as of last quarter | D45: =_xll.ciqfunctions.udf.CIQ(C3, "IQ_QUICK_RATIO", IQ_CQ) | E45: TR.QuickRatio | F45: Optional
B46: interest_coverage | C46: Interest Coverage | D46: =_xll.ciqfunctions.udf.CIQ(C3, "IQ_EBIT_INT", IQ_LTM) | E46: TR.InterestCoverageRatio | F46: Recommended
B47: goodwill_intang | C47: Goodwill & Intangibles | D47: =_xll.ciqfunctions.udf.CIQ(C3, "IQ_GW_INTAN", IQ_CQ) | E47: TR.GoodwillGross | F47: Optional | G47: OWNERSHIP RESOLVER
B48: tangible_bv | C48: Tangible BV / Share | D48: =_xll.ciqfunctions.udf.CIQ(C3, "IQ_TBV_SHARE", IQ_CQ) | E48: TR.TangibleBVPerShare | F48: Optional | G48: The add-ins return a FAILURE AS TEXT, not as an Excel error, so IFERROR cannot chain them — ISNUMBER can. Each row tries four candidate field names in order and takes the first that returns a number. Edit H:K only. M says which one won, or that none did.
A49: Ownership & Risk | B49: short_interest | C49: Short Interest (% float) | D49: =_xll.ciqfunctions.udf.CIQ(C3, "IQ_SHORT_INTEREST_OVER_FLOAT")/100 | E49: TR.ShortInterestPercentOfFloat | F49: Optional | H49: TR field A | I49: TR field B | J49: CIQ mnem A | K49: CIQ mnem B | L49: raw holding | M49: source that resolved
B50: insider_own | C50: Insider Ownership (% of shares out) | D50: =IF(N($L$50)=0,"",IF(N($D$18)=0,"",IF(OR(IF($L$50<=100,$L$50/100,IF($L$50<=$D$18,$L$50/$D$18,$L$50/($D$18*1000000)))<0,IF($L$50<=100,$L$50/100,IF($L$50<=$D$18,$L$50/$D$18,$L$50/($D$18*1000000)))>1),"",IF($L$50<=100,$L$50/100,IF($L$50<=$D$18,$L$50/$D$18,$L$50/($D$18*1000000)))))) | E50: computed: L50 normalised — see the resolver at G47 and the note at A54 | F50: Optional | G50: insider | H50: TR.InsiderPercentHeld | I50: TR.PctOfSharesOutHeld | J50: IQ_INSIDER_OWNERSHIP | K50: IQ_INSIDER_SHARES | L50: =IF(ISNUMBER(_xll.TR($B$3,H50)),_xll.TR($B$3,H50),IF(ISNUMBER(_xll.TR($B$3,I50)),_xll.TR($B$3,I50),IF(ISNUMBER(_xll.ciqfunctions.udf.CIQ($C$3,J50)),_xll.ciqfunctions.udf.CIQ($C$3,J50),IF(ISNUMBER(_xll.ciqfunctions.udf.CIQ($C$3,K50)),_xll.ciqfunctions.udf.CIQ($C$3,K50),"")))) | M50: =IF(ISNUMBER(_xll.TR($B$3,H50)),$H$50,IF(ISNUMBER(_xll.TR($B$3,I50)),$I$50,IF(ISNUMBER(_xll.ciqfunctions.udf.CIQ($C$3,J50)),$J$50,IF(ISNUMBER(_xll.ciqfunctions.udf.CIQ($C$3,K50)),$K$50,"none resolved - paste the right field name into H50"))))
B51: institutional_own | C51: Institutional Own (% of shares out) | D51: =IF(N($L$51)=0,"",IF(N($D$18)=0,"",IF(OR(IF($L$51<=100,$L$51/100,IF($L$51<=$D$18,$L$51/$D$18,$L$51/($D$18*1000000)))<0,IF($L$51<=100,$L$51/100,IF($L$51<=$D$18,$L$51/$D$18,$L$51/($D$18*1000000)))>1),"",IF($L$51<=100,$L$51/100,IF($L$51<=$D$18,$L$51/$D$18,$L$51/($D$18*1000000)))))) | E51: computed: L51 normalised — see the resolver at G47 and the note at A54 | F51: Optional | G51: institutional | H51: TR.SIInstitutionalOwn | I51: TR.InstSharesHeld | J51: IQ_INST_OWNERSHIP | K51: IQ_INST_SHARES | L51: =IF(ISNUMBER(_xll.TR($B$3,H51)),_xll.TR($B$3,H51),IF(ISNUMBER(_xll.TR($B$3,I51)),_xll.TR($B$3,I51),IF(ISNUMBER(_xll.ciqfunctions.udf.CIQ($C$3,J51)),_xll.ciqfunctions.udf.CIQ($C$3,J51),IF(ISNUMBER(_xll.ciqfunctions.udf.CIQ($C$3,K51)),_xll.ciqfunctions.udf.CIQ($C$3,K51),"")))) | M51: =IF(ISNUMBER(_xll.TR($B$3,H51)),$H$51,IF(ISNUMBER(_xll.TR($B$3,I51)),$I$51,IF(ISNUMBER(_xll.ciqfunctions.udf.CIQ($C$3,J51)),$J$51,IF(ISNUMBER(_xll.ciqfunctions.udf.CIQ($C$3,K51)),$K$51,"none resolved - paste the right field name into H51"))))
A54: insider_own (D50) and institutional_own (D51) are COMPUTED, not read from a vendor percentage field. The add-ins report a field they do not know as TEXT ('(Invalid Formula Name)', or 'The formula must contain at least one field or function'), not as an Excel error, so an IFERROR chain stops at the first bad name. The resolver at G47:M51 uses ISNUMBER instead: four candidate field names per row, first numeric one wins, M50/M51 name it. D50/D51 then normalise: a figure up to 100 is a percent; up to the share count in D18 (millions) it is millions of shares; above that it is a plain share count (IQ_INSIDER_SHARES returns one, 38,347,842 for GME). Anything outside 0-1 is blanked. IF M SAYS 'none resolved': open Formula Builder, find the field your licence exposes, paste its name into H50 or H51.

Sheet History
A1: DENNIS — financial history (6 periods) + trend (formulas pre-filled)
A2: Green rows auto-pull per period; grey rows/CAGR auto-calc. Set the ticker on Snapshot!C3; refresh. A CAGR, a ratio over negative equity or EBITDA, and a multiple of negative cash are left blank: they mean nothing.
A4: field_key | B4: Label | C4: FY-4 | D4: FY-3 | E4: FY-2 | F4: FY-1 | G4: FY-0 | H4: LTM | I4: CAGR FY-4->FY-0 % | J4: Field mnemonic (verify)
A5: revenue | B5: Revenue | C5: =_xll.ciqfunctions.udf.CIQ(Snapshot!C3, "IQ_TOTAL_REV", IQ_FY - 4) | D5: =_xll.ciqfunctions.udf.CIQ(Snapshot!C3, "IQ_TOTAL_REV", IQ_FY - 3) | E5: =_xll.ciqfunctions.udf.CIQ(Snapshot!C3, "IQ_TOTAL_REV", IQ_FY - 2) | F5: =_xll.ciqfunctions.udf.CIQ(Snapshot!C3, "IQ_TOTAL_REV", IQ_FY - 1) | G5: =_xll.ciqfunctions.udf.CIQ(Snapshot!C3, "IQ_TOTAL_REV", IQ_FY) | H5: =_xll.ciqfunctions.udf.CIQ(Snapshot!C3, "IQ_TOTAL_REV", IQ_LTM) | I5: =IF(AND(N(C5)>0,N(G5)>0),((G5/C5)^(1/4)-1)*100,"") | J5: TR.Revenue
A6: gross_profit | B6: Gross Profit | C6: =_xll.ciqfunctions.udf.CIQ(Snapshot!C3, "IQ_GP", IQ_FY - 4) | D6: =_xll.ciqfunctions.udf.CIQ(Snapshot!C3, "IQ_GP", IQ_FY - 3) | E6: =_xll.ciqfunctions.udf.CIQ(Snapshot!C3, "IQ_GP", IQ_FY - 2) | F6: =_xll.ciqfunctions.udf.CIQ(Snapshot!C3, "IQ_GP", IQ_FY - 1) | G6: =_xll.ciqfunctions.udf.CIQ(Snapshot!C3, "IQ_GP", IQ_FY) | H6: =_xll.ciqfunctions.udf.CIQ(Snapshot!C3, "IQ_GP", IQ_LTM) | I6: =IF(AND(N(C6)>0,N(G6)>0),((G6/C6)^(1/4)-1)*100,"") | J6: TR.GrossProfit
A7: gross_margin | B7: Gross Margin % | C7: =IFERROR(C6/C5*100,"") | D7: =IFERROR(D6/D5*100,"") | E7: =IFERROR(E6/E5*100,"") | F7: =IFERROR(F6/F5*100,"") | G7: =IFERROR(G6/G5*100,"") | H7: =IFERROR(H6/H5*100,"") | J7: computed
A8: operating_income | B8: Operating Income | C8: =_xll.ciqfunctions.udf.CIQ(Snapshot!C3, "IQ_OPER_INC", IQ_FY - 4) | D8: =_xll.ciqfunctions.udf.CIQ(Snapshot!C3, "IQ_OPER_INC", IQ_FY - 3) | E8: =_xll.ciqfunctions.udf.CIQ(Snapshot!C3, "IQ_OPER_INC", IQ_FY - 2) | F8: =_xll.ciqfunctions.udf.CIQ(Snapshot!C3, "IQ_OPER_INC", IQ_FY - 1) | G8: =_xll.ciqfunctions.udf.CIQ(Snapshot!C3, "IQ_OPER_INC", IQ_FY) | H8: =_xll.ciqfunctions.udf.CIQ(Snapshot!C3, "IQ_OPER_INC", IQ_LTM) | I8: =IF(AND(N(C8)>0,N(G8)>0),((G8/C8)^(1/4)-1)*100,"") | J8: TR.OperatingIncome
A9: operating_margin | B9: Operating Margin % | C9: =IFERROR(C8/C5*100,"") | D9: =IFERROR(D8/D5*100,"") | E9: =IFERROR(E8/E5*100,"") | F9: =IFERROR(F8/F5*100,"") | G9: =IFERROR(G8/G5*100,"") | H9: =IFERROR(H8/H5*100,"") | J9: computed
A10: ebitda | B10: EBITDA | C10: =_xll.ciqfunctions.udf.CIQ(Snapshot!C3, "IQ_EBITDA", IQ_FY - 4) | D10: =_xll.ciqfunctions.udf.CIQ(Snapshot!C3, "IQ_EBITDA", IQ_FY - 3) | E10: =_xll.ciqfunctions.udf.CIQ(Snapshot!C3, "IQ_EBITDA", IQ_FY - 2) | F10: =_xll.ciqfunctions.udf.CIQ(Snapshot!C3, "IQ_EBITDA", IQ_FY - 1) | G10: =_xll.ciqfunctions.udf.CIQ(Snapshot!C3, "IQ_EBITDA", IQ_FY) | H10: =_xll.ciqfunctions.udf.CIQ(Snapshot!C3, "IQ_EBITDA", IQ_LTM) | I10: =IF(AND(N(C10)>0,N(G10)>0),((G10/C10)^(1/4)-1)*100,"") | J10: TR.EBITDA
A11: net_income | B11: Net Income | C11: =_xll.ciqfunctions.udf.CIQ(Snapshot!C3, "IQ_NI", IQ_FY - 4) | D11: =_xll.ciqfunctions.udf.CIQ(Snapshot!C3, "IQ_NI", IQ_FY - 3) | E11: =_xll.ciqfunctions.udf.CIQ(Snapshot!C3, "IQ_NI", IQ_FY - 2) | F11: =_xll.ciqfunctions.udf.CIQ(Snapshot!C3, "IQ_NI", IQ_FY - 1) | G11: =_xll.ciqfunctions.udf.CIQ(Snapshot!C3, "IQ_NI", IQ_FY) | H11: =_xll.ciqfunctions.udf.CIQ(Snapshot!C3, "IQ_NI", IQ_LTM) | I11: =IF(AND(N(C11)>0,N(G11)>0),((G11/C11)^(1/4)-1)*100,"") | J11: TR.NetIncomeAfterTax
A12: net_margin | B12: Net Margin % | C12: =IFERROR(C11/C5*100,"") | D12: =IFERROR(D11/D5*100,"") | E12: =IFERROR(E11/E5*100,"") | F12: =IFERROR(F11/F5*100,"") | G12: =IFERROR(G11/G5*100,"") | H12: =IFERROR(H11/H5*100,"") | J12: computed
A13: operating_cf | B13: Operating Cash Flow | C13: =_xll.ciqfunctions.udf.CIQ(Snapshot!C3, "IQ_CASH_OPER_CS", IQ_FY - 4) | D13: =_xll.ciqfunctions.udf.CIQ(Snapshot!C3, "IQ_CASH_OPER_CS", IQ_FY - 3) | E13: =_xll.ciqfunctions.udf.CIQ(Snapshot!C3, "IQ_CASH_OPER_CS", IQ_FY - 2) | F13: =_xll.ciqfunctions.udf.CIQ(Snapshot!C3, "IQ_CASH_OPER_CS", IQ_FY - 1) | G13: =_xll.ciqfunctions.udf.CIQ(Snapshot!C3, "IQ_CASH_OPER_CS", IQ_FY) | H13: =_xll.ciqfunctions.udf.CIQ(Snapshot!C3, "IQ_CASH_OPER_CS", IQ_LTM) | I13: =IF(AND(N(C13)>0,N(G13)>0),((G13/C13)^(1/4)-1)*100,"") | J13: TR.CashFromOperatingAct
A14: capex | B14: CapEx | C14: =_xll.ciqfunctions.udf.CIQ(Snapshot!C3, "IQ_CAPEX", IQ_FY - 4) | D14: =_xll.ciqfunctions.udf.CIQ(Snapshot!C3, "IQ_CAPEX", IQ_FY - 3) | E14: =_xll.ciqfunctions.udf.CIQ(Snapshot!C3, "IQ_CAPEX", IQ_FY - 2) | F14: =_xll.ciqfunctions.udf.CIQ(Snapshot!C3, "IQ_CAPEX", IQ_FY - 1) | G14: =_xll.ciqfunctions.udf.CIQ(Snapshot!C3, "IQ_CAPEX", IQ_FY) | H14: =_xll.ciqfunctions.udf.CIQ(Snapshot!C3, "IQ_CAPEX", IQ_LTM) | J14: TR.CapitalExpenditures
A15: fcf | B15: Free Cash Flow | C15: =IF(C13="","",C13+C14) | D15: =IF(D13="","",D13+D14) | E15: =IF(E13="","",E13+E14) | F15: =IF(F13="","",F13+F14) | G15: =IF(G13="","",G13+G14) | H15: =IF(H13="","",H13+H14) | I15: =IF(AND(N(C15)>0,N(G15)>0),((G15/C15)^(1/4)-1)*100,"") | J15: computed
A16: fcf_margin | B16: FCF Margin % | C16: =IFERROR(C15/C5*100,"") | D16: =IFERROR(D15/D5*100,"") | E16: =IFERROR(E15/E5*100,"") | F16: =IFERROR(F15/F5*100,"") | G16: =IFERROR(G15/G5*100,"") | H16: =IFERROR(H15/H5*100,"") | J16: computed
A17: sbc | B17: Stock-Based Comp | C17: =_xll.ciqfunctions.udf.CIQ(Snapshot!C3, "IQ_STOCK_BASED_CF", IQ_FY - 4) | D17: =_xll.ciqfunctions.udf.CIQ(Snapshot!C3, "IQ_STOCK_BASED_CF", IQ_FY - 3) | E17: =_xll.ciqfunctions.udf.CIQ(Snapshot!C3, "IQ_STOCK_BASED_CF", IQ_FY - 2) | F17: =_xll.ciqfunctions.udf.CIQ(Snapshot!C3, "IQ_STOCK_BASED_CF", IQ_FY - 1) | G17: =_xll.ciqfunctions.udf.CIQ(Snapshot!C3, "IQ_STOCK_BASED_CF", IQ_FY) | H17: =_xll.ciqfunctions.udf.CIQ(Snapshot!C3, "IQ_STOCK_BASED_CF", IQ_LTM) | J17: TR.StockBasedCompensation
A18: sbc_pct_rev | B18: SBC % of Revenue | C18: =IFERROR(C17/C5*100,"") | D18: =IFERROR(D17/D5*100,"") | E18: =IFERROR(E17/E5*100,"") | F18: =IFERROR(F17/F5*100,"") | G18: =IFERROR(G17/G5*100,"") | H18: =IFERROR(H17/H5*100,"") | J18: computed
A19: dividends_paid | B19: Dividends Paid | C19: =_xll.ciqfunctions.udf.CIQ(Snapshot!C3, "IQ_TOTAL_DIV_PAID_CF", IQ_FY - 4) | D19: =_xll.ciqfunctions.udf.CIQ(Snapshot!C3, "IQ_TOTAL_DIV_PAID_CF", IQ_FY - 3) | E19: =_xll.ciqfunctions.udf.CIQ(Snapshot!C3, "IQ_TOTAL_DIV_PAID_CF", IQ_FY - 2) | F19: =_xll.ciqfunctions.udf.CIQ(Snapshot!C3, "IQ_TOTAL_DIV_PAID_CF", IQ_FY - 1) | G19: =_xll.ciqfunctions.udf.CIQ(Snapshot!C3, "IQ_TOTAL_DIV_PAID_CF", IQ_FY) | H19: =_xll.ciqfunctions.udf.CIQ(Snapshot!C3, "IQ_TOTAL_DIV_PAID_CF", IQ_LTM) | J19: TR.CommonDividendsPaid
A20: buybacks | B20: Buybacks | C20: =_xll.ciqfunctions.udf.CIQ(Snapshot!C3, "IQ_COMMON_REP", IQ_FY - 4) | D20: =_xll.ciqfunctions.udf.CIQ(Snapshot!C3, "IQ_COMMON_REP", IQ_FY - 3) | E20: =_xll.ciqfunctions.udf.CIQ(Snapshot!C3, "IQ_COMMON_REP", IQ_FY - 2) | F20: =_xll.ciqfunctions.udf.CIQ(Snapshot!C3, "IQ_COMMON_REP", IQ_FY - 1) | G20: =_xll.ciqfunctions.udf.CIQ(Snapshot!C3, "IQ_COMMON_REP", IQ_FY) | H20: =_xll.ciqfunctions.udf.CIQ(Snapshot!C3, "IQ_COMMON_REP", IQ_LTM) | J20: TR.RepurchaseOfCommonStock
A21: cash | B21: Cash & ST Investments | C21: =_xll.ciqfunctions.udf.CIQ(Snapshot!C3, "IQ_CASH_ST_INVEST", IQ_FY - 4) | D21: =_xll.ciqfunctions.udf.CIQ(Snapshot!C3, "IQ_CASH_ST_INVEST", IQ_FY - 3) | E21: =_xll.ciqfunctions.udf.CIQ(Snapshot!C3, "IQ_CASH_ST_INVEST", IQ_FY - 2) | F21: =_xll.ciqfunctions.udf.CIQ(Snapshot!C3, "IQ_CASH_ST_INVEST", IQ_FY - 1) | G21: =_xll.ciqfunctions.udf.CIQ(Snapshot!C3, "IQ_CASH_ST_INVEST", IQ_FY) | H21: =_xll.ciqfunctions.udf.CIQ(Snapshot!C3, "IQ_CASH_ST_INVEST", IQ_LTM) | J21: TR.CashAndSTInvestments
A22: total_debt | B22: Total Debt | C22: =_xll.ciqfunctions.udf.CIQ(Snapshot!C3, "IQ_TOTAL_DEBT", IQ_FY - 4) | D22: =_xll.ciqfunctions.udf.CIQ(Snapshot!C3, "IQ_TOTAL_DEBT", IQ_FY - 3) | E22: =_xll.ciqfunctions.udf.CIQ(Snapshot!C3, "IQ_TOTAL_DEBT", IQ_FY - 2) | F22: =_xll.ciqfunctions.udf.CIQ(Snapshot!C3, "IQ_TOTAL_DEBT", IQ_FY - 1) | G22: =_xll.ciqfunctions.udf.CIQ(Snapshot!C3, "IQ_TOTAL_DEBT", IQ_FY) | H22: =_xll.ciqfunctions.udf.CIQ(Snapshot!C3, "IQ_TOTAL_DEBT", IQ_LTM) | J22: TR.TotalDebtOutstanding
A23: net_debt | B23: Net Debt | C23: =IF(C22="","",C22-C21) | D23: =IF(D22="","",D22-D21) | E23: =IF(E22="","",E22-E21) | F23: =IF(F22="","",F22-F21) | G23: =IF(G22="","",G22-G21) | H23: =IF(H22="","",H22-H21) | J23: computed
A24: total_equity | B24: Total Equity | C24: =_xll.ciqfunctions.udf.CIQ(Snapshot!C3, "IQ_TOTAL_EQUITY", IQ_FY - 4) | D24: =_xll.ciqfunctions.udf.CIQ(Snapshot!C3, "IQ_TOTAL_EQUITY", IQ_FY - 3) | E24: =_xll.ciqfunctions.udf.CIQ(Snapshot!C3, "IQ_TOTAL_EQUITY", IQ_FY - 2) | F24: =_xll.ciqfunctions.udf.CIQ(Snapshot!C3, "IQ_TOTAL_EQUITY", IQ_FY - 1) | G24: =_xll.ciqfunctions.udf.CIQ(Snapshot!C3, "IQ_TOTAL_EQUITY", IQ_FY) | H24: =_xll.ciqfunctions.udf.CIQ(Snapshot!C3, "IQ_TOTAL_EQUITY", IQ_LTM) | J24: TR.TotalEquity
A25: total_assets | B25: Total Assets | C25: =_xll.ciqfunctions.udf.CIQ(Snapshot!C3, "IQ_TOTAL_ASSETS", IQ_FY - 4) | D25: =_xll.ciqfunctions.udf.CIQ(Snapshot!C3, "IQ_TOTAL_ASSETS", IQ_FY - 3) | E25: =_xll.ciqfunctions.udf.CIQ(Snapshot!C3, "IQ_TOTAL_ASSETS", IQ_FY - 2) | F25: =_xll.ciqfunctions.udf.CIQ(Snapshot!C3, "IQ_TOTAL_ASSETS", IQ_FY - 1) | G25: =_xll.ciqfunctions.udf.CIQ(Snapshot!C3, "IQ_TOTAL_ASSETS", IQ_FY) | H25: =_xll.ciqfunctions.udf.CIQ(Snapshot!C3, "IQ_TOTAL_ASSETS", IQ_LTM) | J25: TR.TotalAssets
A26: invested_capital | B26: Invested Capital | C26: =C22+C24-C21 | D26: =D22+D24-D21 | E26: =E22+E24-E21 | F26: =F22+F24-F21 | G26: =G22+G24-G21 | H26: =H22+H24-H21 | J26: TR.InvestedCapital
A27: net_debt_ebitda | B27: Net Debt / EBITDA | C27: =IF(N(C10)>0,C23/C10,"") | D27: =IF(N(D10)>0,D23/D10,"") | E27: =IF(N(E10)>0,E23/E10,"") | F27: =IF(N(F10)>0,F23/F10,"") | G27: =IF(N(G10)>0,G23/G10,"") | H27: =IF(N(H10)>0,H23/H10,"") | J27: computed
A28: eps | B28: EPS (diluted) | C28: =IFERROR(C11/C33*1,"") | D28: =IFERROR(D11/D33*1,"") | E28: =IFERROR(E11/E33*1,"") | F28: =IFERROR(F11/F33*1,"") | G28: =IFERROR(G11/G33*1,"") | H28: =IFERROR(H11/H33*1,"") | J28: computed
A29: fcf_ps | B29: FCF per Share | C29: =IFERROR(C15/C33*1,"") | D29: =IFERROR(D15/D33*1,"") | E29: =IFERROR(E15/E33*1,"") | F29: =IFERROR(F15/F33*1,"") | G29: =IFERROR(G15/G33*1,"") | H29: =IFERROR(H15/H33*1,"") | J29: computed
A30: bvps | B30: Book Value / Share | C30: =IFERROR(C24/C33*1,"") | D30: =IFERROR(D24/D33*1,"") | E30: =IFERROR(E24/E33*1,"") | F30: =IFERROR(F24/F33*1,"") | G30: =IFERROR(G24/G33*1,"") | H30: =IFERROR(H24/H33*1,"") | J30: computed
A31: roic | B31: ROIC % | C31: =IF(N(C26)>0,C8*(1-Valuation!$B$22)/C26*100,"") | D31: =IF(N(D26)>0,D8*(1-Valuation!$B$22)/D26*100,"") | E31: =IF(N(E26)>0,E8*(1-Valuation!$B$22)/E26*100,"") | F31: =IF(N(F26)>0,F8*(1-Valuation!$B$22)/F26*100,"") | G31: =IF(N(G26)>0,G8*(1-Valuation!$B$22)/G26*100,"") | H31: =IF(N(H26)>0,H8*(1-Valuation!$B$22)/H26*100,"") | J31: computed
A32: roe | B32: ROE % | C32: =IF(N(C24)>0,C11/C24*100,"") | D32: =IF(N(D24)>0,D11/D24*100,"") | E32: =IF(N(E24)>0,E11/E24*100,"") | F32: =IF(N(F24)>0,F11/F24*100,"") | G32: =IF(N(G24)>0,G11/G24*100,"") | H32: =IF(N(H24)>0,H11/H24*100,"") | J32: computed
A33: diluted_shares | B33: Diluted Shares | C33: =_xll.ciqfunctions.udf.CIQ(Snapshot!C3, "IQ_DILUT_WEIGHT", IQ_FY - 4) | D33: =_xll.ciqfunctions.udf.CIQ(Snapshot!C3, "IQ_DILUT_WEIGHT", IQ_FY - 3) | E33: =_xll.ciqfunctions.udf.CIQ(Snapshot!C3, "IQ_DILUT_WEIGHT", IQ_FY - 2) | F33: =_xll.ciqfunctions.udf.CIQ(Snapshot!C3, "IQ_DILUT_WEIGHT", IQ_FY - 1) | G33: =_xll.ciqfunctions.udf.CIQ(Snapshot!C3, "IQ_DILUT_WEIGHT", IQ_FY) | H33: =_xll.ciqfunctions.udf.CIQ(Snapshot!C3, "IQ_DILUT_WEIGHT", IQ_LTM) | I33: =IF(AND(N(C33)>0,N(G33)>0),((G33/C33)^(1/4)-1)*100,"") | J33: TR.DilutedWeightedAvgShares
A34: shares_yoy | B34: Share Count YoY % | D34: =IFERROR((D33/C33-1)*100,"") | E34: =IFERROR((E33/D33-1)*100,"") | F34: =IFERROR((F33/E33-1)*100,"") | G34: =IFERROR((G33/F33-1)*100,"") | H34: =IFERROR((H33/G33-1)*100,"") | J34: computed
A35: fiscal_year | B35: Fiscal year (labels the column) | C35: =_xll.ciqfunctions.udf.CIQ(Snapshot!C3, "IQ_FISCAL_Y", IQ_FY - 4) | D35: =_xll.ciqfunctions.udf.CIQ(Snapshot!C3, "IQ_FISCAL_Y", IQ_FY - 3) | E35: =_xll.ciqfunctions.udf.CIQ(Snapshot!C3, "IQ_FISCAL_Y", IQ_FY - 2) | F35: =_xll.ciqfunctions.udf.CIQ(Snapshot!C3, "IQ_FISCAL_Y", IQ_FY - 1) | G35: =_xll.ciqfunctions.udf.CIQ(Snapshot!C3, "IQ_FISCAL_Y", IQ_FY) | J35: TR.FiscalYear
A36: period_end | B36: Fiscal year end date (names a year the row above does not) | C36: =_xll.ciqfunctions.udf.CIQ(Snapshot!C3, "IQ_PERIODDATE", IQ_FY - 4) | D36: =_xll.ciqfunctions.udf.CIQ(Snapshot!C3, "IQ_PERIODDATE", IQ_FY - 3) | E36: =_xll.ciqfunctions.udf.CIQ(Snapshot!C3, "IQ_PERIODDATE", IQ_FY - 2) | F36: =_xll.ciqfunctions.udf.CIQ(Snapshot!C3, "IQ_PERIODDATE", IQ_FY - 1) | G36: =_xll.ciqfunctions.udf.CIQ(Snapshot!C3, "IQ_PERIODDATE", IQ_FY) | J36: IQ_PERIODDATE

Sheet Quarters
A1: DENNIS — quarterly results (8 quarters) + both comparisons
A2: Green rows auto-pull per quarter; grey rows auto-calc. Q-0 is the latest reported quarter. Read QoQ (Q-1) and YoY (Q-4) together: a retailer beats its own Q3 every December. Rows 27-29 NAME the columns (Q3 FY26): the bot needs the fiscal year at least, or the period end date.
A4: field_key | B4: Label | C4: Q-7 | D4: Q-6 | E4: Q-5 | F4: Q-4 | G4: Q-3 | H4: Q-2 | I4: Q-1 | J4: Q-0 | K4: Field mnemonic (verify)
A5: revenue | B5: Revenue | C5: =_xll.ciqfunctions.udf.CIQ(Snapshot!C3, "IQ_TOTAL_REV", IQ_FQ - 7) | D5: =_xll.ciqfunctions.udf.CIQ(Snapshot!C3, "IQ_TOTAL_REV", IQ_FQ - 6) | E5: =_xll.ciqfunctions.udf.CIQ(Snapshot!C3, "IQ_TOTAL_REV", IQ_FQ - 5) | F5: =_xll.ciqfunctions.udf.CIQ(Snapshot!C3, "IQ_TOTAL_REV", IQ_FQ - 4) | G5: =_xll.ciqfunctions.udf.CIQ(Snapshot!C3, "IQ_TOTAL_REV", IQ_FQ - 3) | H5: =_xll.ciqfunctions.udf.CIQ(Snapshot!C3, "IQ_TOTAL_REV", IQ_FQ - 2) | I5: =_xll.ciqfunctions.udf.CIQ(Snapshot!C3, "IQ_TOTAL_REV", IQ_FQ - 1) | J5: =_xll.ciqfunctions.udf.CIQ(Snapshot!C3, "IQ_TOTAL_REV", IQ_FQ) | K5: TR.Revenue
A6: gross_profit | B6: Gross Profit | C6: =_xll.ciqfunctions.udf.CIQ(Snapshot!C3, "IQ_GP", IQ_FQ - 7) | D6: =_xll.ciqfunctions.udf.CIQ(Snapshot!C3, "IQ_GP", IQ_FQ - 6) | E6: =_xll.ciqfunctions.udf.CIQ(Snapshot!C3, "IQ_GP", IQ_FQ - 5) | F6: =_xll.ciqfunctions.udf.CIQ(Snapshot!C3, "IQ_GP", IQ_FQ - 4) | G6: =_xll.ciqfunctions.udf.CIQ(Snapshot!C3, "IQ_GP", IQ_FQ - 3) | H6: =_xll.ciqfunctions.udf.CIQ(Snapshot!C3, "IQ_GP", IQ_FQ - 2) | I6: =_xll.ciqfunctions.udf.CIQ(Snapshot!C3, "IQ_GP", IQ_FQ - 1) | J6: =_xll.ciqfunctions.udf.CIQ(Snapshot!C3, "IQ_GP", IQ_FQ) | K6: TR.GrossProfit
A7: gross_margin | B7: Gross Margin % | C7: =IFERROR(C6/C5*100,"") | D7: =IFERROR(D6/D5*100,"") | E7: =IFERROR(E6/E5*100,"") | F7: =IFERROR(F6/F5*100,"") | G7: =IFERROR(G6/G5*100,"") | H7: =IFERROR(H6/H5*100,"") | I7: =IFERROR(I6/I5*100,"") | J7: =IFERROR(J6/J5*100,"") | K7: computed
A8: operating_income | B8: Operating Income | C8: =_xll.ciqfunctions.udf.CIQ(Snapshot!C3, "IQ_OPER_INC", IQ_FQ - 7) | D8: =_xll.ciqfunctions.udf.CIQ(Snapshot!C3, "IQ_OPER_INC", IQ_FQ - 6) | E8: =_xll.ciqfunctions.udf.CIQ(Snapshot!C3, "IQ_OPER_INC", IQ_FQ - 5) | F8: =_xll.ciqfunctions.udf.CIQ(Snapshot!C3, "IQ_OPER_INC", IQ_FQ - 4) | G8: =_xll.ciqfunctions.udf.CIQ(Snapshot!C3, "IQ_OPER_INC", IQ_FQ - 3) | H8: =_xll.ciqfunctions.udf.CIQ(Snapshot!C3, "IQ_OPER_INC", IQ_FQ - 2) | I8: =_xll.ciqfunctions.udf.CIQ(Snapshot!C3, "IQ_OPER_INC", IQ_FQ - 1) | J8: =_xll.ciqfunctions.udf.CIQ(Snapshot!C3, "IQ_OPER_INC", IQ_FQ) | K8: TR.OperatingIncome
A9: operating_margin | B9: Operating Margin % | C9: =IFERROR(C8/C5*100,"") | D9: =IFERROR(D8/D5*100,"") | E9: =IFERROR(E8/E5*100,"") | F9: =IFERROR(F8/F5*100,"") | G9: =IFERROR(G8/G5*100,"") | H9: =IFERROR(H8/H5*100,"") | I9: =IFERROR(I8/I5*100,"") | J9: =IFERROR(J8/J5*100,"") | K9: computed
A10: ebitda | B10: EBITDA | C10: =_xll.ciqfunctions.udf.CIQ(Snapshot!C3, "IQ_EBITDA", IQ_FQ - 7) | D10: =_xll.ciqfunctions.udf.CIQ(Snapshot!C3, "IQ_EBITDA", IQ_FQ - 6) | E10: =_xll.ciqfunctions.udf.CIQ(Snapshot!C3, "IQ_EBITDA", IQ_FQ - 5) | F10: =_xll.ciqfunctions.udf.CIQ(Snapshot!C3, "IQ_EBITDA", IQ_FQ - 4) | G10: =_xll.ciqfunctions.udf.CIQ(Snapshot!C3, "IQ_EBITDA", IQ_FQ - 3) | H10: =_xll.ciqfunctions.udf.CIQ(Snapshot!C3, "IQ_EBITDA", IQ_FQ - 2) | I10: =_xll.ciqfunctions.udf.CIQ(Snapshot!C3, "IQ_EBITDA", IQ_FQ - 1) | J10: =_xll.ciqfunctions.udf.CIQ(Snapshot!C3, "IQ_EBITDA", IQ_FQ) | K10: TR.EBITDA
A11: net_income | B11: Net Income | C11: =_xll.ciqfunctions.udf.CIQ(Snapshot!C3, "IQ_NI", IQ_FQ - 7) | D11: =_xll.ciqfunctions.udf.CIQ(Snapshot!C3, "IQ_NI", IQ_FQ - 6) | E11: =_xll.ciqfunctions.udf.CIQ(Snapshot!C3, "IQ_NI", IQ_FQ - 5) | F11: =_xll.ciqfunctions.udf.CIQ(Snapshot!C3, "IQ_NI", IQ_FQ - 4) | G11: =_xll.ciqfunctions.udf.CIQ(Snapshot!C3, "IQ_NI", IQ_FQ - 3) | H11: =_xll.ciqfunctions.udf.CIQ(Snapshot!C3, "IQ_NI", IQ_FQ - 2) | I11: =_xll.ciqfunctions.udf.CIQ(Snapshot!C3, "IQ_NI", IQ_FQ - 1) | J11: =_xll.ciqfunctions.udf.CIQ(Snapshot!C3, "IQ_NI", IQ_FQ) | K11: TR.NetIncomeAfterTax
A12: net_margin | B12: Net Margin % | C12: =IFERROR(C11/C5*100,"") | D12: =IFERROR(D11/D5*100,"") | E12: =IFERROR(E11/E5*100,"") | F12: =IFERROR(F11/F5*100,"") | G12: =IFERROR(G11/G5*100,"") | H12: =IFERROR(H11/H5*100,"") | I12: =IFERROR(I11/I5*100,"") | J12: =IFERROR(J11/J5*100,"") | K12: computed
A13: operating_cf | B13: Operating Cash Flow | C13: =_xll.ciqfunctions.udf.CIQ(Snapshot!C3, "IQ_CASH_OPER_CS", IQ_FQ - 7) | D13: =_xll.ciqfunctions.udf.CIQ(Snapshot!C3, "IQ_CASH_OPER_CS", IQ_FQ - 6) | E13: =_xll.ciqfunctions.udf.CIQ(Snapshot!C3, "IQ_CASH_OPER_CS", IQ_FQ - 5) | F13: =_xll.ciqfunctions.udf.CIQ(Snapshot!C3, "IQ_CASH_OPER_CS", IQ_FQ - 4) | G13: =_xll.ciqfunctions.udf.CIQ(Snapshot!C3, "IQ_CASH_OPER_CS", IQ_FQ - 3) | H13: =_xll.ciqfunctions.udf.CIQ(Snapshot!C3, "IQ_CASH_OPER_CS", IQ_FQ - 2) | I13: =_xll.ciqfunctions.udf.CIQ(Snapshot!C3, "IQ_CASH_OPER_CS", IQ_FQ - 1) | J13: =_xll.ciqfunctions.udf.CIQ(Snapshot!C3, "IQ_CASH_OPER_CS", IQ_FQ) | K13: TR.CashFromOperatingAct
A14: capex | B14: CapEx | C14: =_xll.ciqfunctions.udf.CIQ(Snapshot!C3, "IQ_CAPEX", IQ_FQ - 7) | D14: =_xll.ciqfunctions.udf.CIQ(Snapshot!C3, "IQ_CAPEX", IQ_FQ - 6) | E14: =_xll.ciqfunctions.udf.CIQ(Snapshot!C3, "IQ_CAPEX", IQ_FQ - 5) | F14: =_xll.ciqfunctions.udf.CIQ(Snapshot!C3, "IQ_CAPEX", IQ_FQ - 4) | G14: =_xll.ciqfunctions.udf.CIQ(Snapshot!C3, "IQ_CAPEX", IQ_FQ - 3) | H14: =_xll.ciqfunctions.udf.CIQ(Snapshot!C3, "IQ_CAPEX", IQ_FQ - 2) | I14: =_xll.ciqfunctions.udf.CIQ(Snapshot!C3, "IQ_CAPEX", IQ_FQ - 1) | J14: =_xll.ciqfunctions.udf.CIQ(Snapshot!C3, "IQ_CAPEX", IQ_FQ) | K14: TR.CapitalExpenditures
A15: fcf | B15: Free Cash Flow | C15: =IF(C13="","",C13+C14) | D15: =IF(D13="","",D13+D14) | E15: =IF(E13="","",E13+E14) | F15: =IF(F13="","",F13+F14) | G15: =IF(G13="","",G13+G14) | H15: =IF(H13="","",H13+H14) | I15: =IF(I13="","",I13+I14) | J15: =IF(J13="","",J13+J14) | K15: computed
A16: fcf_margin | B16: FCF Margin % | C16: =IFERROR(C15/C5*100,"") | D16: =IFERROR(D15/D5*100,"") | E16: =IFERROR(E15/E5*100,"") | F16: =IFERROR(F15/F5*100,"") | G16: =IFERROR(G15/G5*100,"") | H16: =IFERROR(H15/H5*100,"") | I16: =IFERROR(I15/I5*100,"") | J16: =IFERROR(J15/J5*100,"") | K16: computed
A17: sbc | B17: Stock-Based Comp | C17: =_xll.ciqfunctions.udf.CIQ(Snapshot!C3, "IQ_STOCK_BASED_CF", IQ_FQ - 7) | D17: =_xll.ciqfunctions.udf.CIQ(Snapshot!C3, "IQ_STOCK_BASED_CF", IQ_FQ - 6) | E17: =_xll.ciqfunctions.udf.CIQ(Snapshot!C3, "IQ_STOCK_BASED_CF", IQ_FQ - 5) | F17: =_xll.ciqfunctions.udf.CIQ(Snapshot!C3, "IQ_STOCK_BASED_CF", IQ_FQ - 4) | G17: =_xll.ciqfunctions.udf.CIQ(Snapshot!C3, "IQ_STOCK_BASED_CF", IQ_FQ - 3) | H17: =_xll.ciqfunctions.udf.CIQ(Snapshot!C3, "IQ_STOCK_BASED_CF", IQ_FQ - 2) | I17: =_xll.ciqfunctions.udf.CIQ(Snapshot!C3, "IQ_STOCK_BASED_CF", IQ_FQ - 1) | J17: =_xll.ciqfunctions.udf.CIQ(Snapshot!C3, "IQ_STOCK_BASED_CF", IQ_FQ) | K17: TR.StockBasedCompensation
A18: cash | B18: Cash & Equivalents | C18: =_xll.ciqfunctions.udf.CIQ(Snapshot!C3, "IQ_CASH_ST_INVEST", IQ_FQ - 7) | D18: =_xll.ciqfunctions.udf.CIQ(Snapshot!C3, "IQ_CASH_ST_INVEST", IQ_FQ - 6) | E18: =_xll.ciqfunctions.udf.CIQ(Snapshot!C3, "IQ_CASH_ST_INVEST", IQ_FQ - 5) | F18: =_xll.ciqfunctions.udf.CIQ(Snapshot!C3, "IQ_CASH_ST_INVEST", IQ_FQ - 4) | G18: =_xll.ciqfunctions.udf.CIQ(Snapshot!C3, "IQ_CASH_ST_INVEST", IQ_FQ - 3) | H18: =_xll.ciqfunctions.udf.CIQ(Snapshot!C3, "IQ_CASH_ST_INVEST", IQ_FQ - 2) | I18: =_xll.ciqfunctions.udf.CIQ(Snapshot!C3, "IQ_CASH_ST_INVEST", IQ_FQ - 1) | J18: =_xll.ciqfunctions.udf.CIQ(Snapshot!C3, "IQ_CASH_ST_INVEST", IQ_FQ) | K18: TR.CashAndSTInvestments
A19: total_debt | B19: Total Debt | C19: =_xll.ciqfunctions.udf.CIQ(Snapshot!C3, "IQ_TOTAL_DEBT", IQ_FQ - 7) | D19: =_xll.ciqfunctions.udf.CIQ(Snapshot!C3, "IQ_TOTAL_DEBT", IQ_FQ - 6) | E19: =_xll.ciqfunctions.udf.CIQ(Snapshot!C3, "IQ_TOTAL_DEBT", IQ_FQ - 5) | F19: =_xll.ciqfunctions.udf.CIQ(Snapshot!C3, "IQ_TOTAL_DEBT", IQ_FQ - 4) | G19: =_xll.ciqfunctions.udf.CIQ(Snapshot!C3, "IQ_TOTAL_DEBT", IQ_FQ - 3) | H19: =_xll.ciqfunctions.udf.CIQ(Snapshot!C3, "IQ_TOTAL_DEBT", IQ_FQ - 2) | I19: =_xll.ciqfunctions.udf.CIQ(Snapshot!C3, "IQ_TOTAL_DEBT", IQ_FQ - 1) | J19: =_xll.ciqfunctions.udf.CIQ(Snapshot!C3, "IQ_TOTAL_DEBT", IQ_FQ) | K19: TR.TotalDebtOutstanding
A20: net_debt | B20: Net Debt | C20: =IF(C19="","",C19-C18) | D20: =IF(D19="","",D19-D18) | E20: =IF(E19="","",E19-E18) | F20: =IF(F19="","",F19-F18) | G20: =IF(G19="","",G19-G18) | H20: =IF(H19="","",H19-H18) | I20: =IF(I19="","",I19-I18) | J20: =IF(J19="","",J19-J18) | K20: computed
A21: total_equity | B21: Total Equity | C21: =_xll.ciqfunctions.udf.CIQ(Snapshot!C3, "IQ_TOTAL_EQUITY", IQ_FQ - 7) | D21: =_xll.ciqfunctions.udf.CIQ(Snapshot!C3, "IQ_TOTAL_EQUITY", IQ_FQ - 6) | E21: =_xll.ciqfunctions.udf.CIQ(Snapshot!C3, "IQ_TOTAL_EQUITY", IQ_FQ - 5) | F21: =_xll.ciqfunctions.udf.CIQ(Snapshot!C3, "IQ_TOTAL_EQUITY", IQ_FQ - 4) | G21: =_xll.ciqfunctions.udf.CIQ(Snapshot!C3, "IQ_TOTAL_EQUITY", IQ_FQ - 3) | H21: =_xll.ciqfunctions.udf.CIQ(Snapshot!C3, "IQ_TOTAL_EQUITY", IQ_FQ - 2) | I21: =_xll.ciqfunctions.udf.CIQ(Snapshot!C3, "IQ_TOTAL_EQUITY", IQ_FQ - 1) | J21: =_xll.ciqfunctions.udf.CIQ(Snapshot!C3, "IQ_TOTAL_EQUITY", IQ_FQ) | K21: TR.TotalEquity
A22: diluted_shares | B22: Diluted Shares | C22: =_xll.ciqfunctions.udf.CIQ(Snapshot!C3, "IQ_DILUT_WEIGHT", IQ_FQ - 7) | D22: =_xll.ciqfunctions.udf.CIQ(Snapshot!C3, "IQ_DILUT_WEIGHT", IQ_FQ - 6) | E22: =_xll.ciqfunctions.udf.CIQ(Snapshot!C3, "IQ_DILUT_WEIGHT", IQ_FQ - 5) | F22: =_xll.ciqfunctions.udf.CIQ(Snapshot!C3, "IQ_DILUT_WEIGHT", IQ_FQ - 4) | G22: =_xll.ciqfunctions.udf.CIQ(Snapshot!C3, "IQ_DILUT_WEIGHT", IQ_FQ - 3) | H22: =_xll.ciqfunctions.udf.CIQ(Snapshot!C3, "IQ_DILUT_WEIGHT", IQ_FQ - 2) | I22: =_xll.ciqfunctions.udf.CIQ(Snapshot!C3, "IQ_DILUT_WEIGHT", IQ_FQ - 1) | J22: =_xll.ciqfunctions.udf.CIQ(Snapshot!C3, "IQ_DILUT_WEIGHT", IQ_FQ) | K22: TR.DilutedWeightedAvgShares
A23: eps | B23: EPS (diluted) | C23: =IFERROR(C11/C22*1,"") | D23: =IFERROR(D11/D22*1,"") | E23: =IFERROR(E11/E22*1,"") | F23: =IFERROR(F11/F22*1,"") | G23: =IFERROR(G11/G22*1,"") | H23: =IFERROR(H11/H22*1,"") | I23: =IFERROR(I11/I22*1,"") | J23: =IFERROR(J11/J22*1,"") | K23: computed
A24: eps_street | B24: EPS actual (street basis) | C24: =_xll.ciqfunctions.udf.CIQ(Snapshot!C3, "IQ_EPS_ACT", IQ_FQ - 7) | D24: =_xll.ciqfunctions.udf.CIQ(Snapshot!C3, "IQ_EPS_ACT", IQ_FQ - 6) | E24: =_xll.ciqfunctions.udf.CIQ(Snapshot!C3, "IQ_EPS_ACT", IQ_FQ - 5) | F24: =_xll.ciqfunctions.udf.CIQ(Snapshot!C3, "IQ_EPS_ACT", IQ_FQ - 4) | G24: =_xll.ciqfunctions.udf.CIQ(Snapshot!C3, "IQ_EPS_ACT", IQ_FQ - 3) | H24: =_xll.ciqfunctions.udf.CIQ(Snapshot!C3, "IQ_EPS_ACT", IQ_FQ - 2) | I24: =_xll.ciqfunctions.udf.CIQ(Snapshot!C3, "IQ_EPS_ACT", IQ_FQ - 1) | J24: =_xll.ciqfunctions.udf.CIQ(Snapshot!C3, "IQ_EPS_ACT", IQ_FQ) | K24: TR.EPSActValue
A25: eps_consensus | B25: EPS estimate (consensus mean) | C25: =_xll.ciqfunctions.udf.CIQ(Snapshot!C3, "IQ_EPS_EST", IQ_FQ - 7) | D25: =_xll.ciqfunctions.udf.CIQ(Snapshot!C3, "IQ_EPS_EST", IQ_FQ - 6) | E25: =_xll.ciqfunctions.udf.CIQ(Snapshot!C3, "IQ_EPS_EST", IQ_FQ - 5) | F25: =_xll.ciqfunctions.udf.CIQ(Snapshot!C3, "IQ_EPS_EST", IQ_FQ - 4) | G25: =_xll.ciqfunctions.udf.CIQ(Snapshot!C3, "IQ_EPS_EST", IQ_FQ - 3) | H25: =_xll.ciqfunctions.udf.CIQ(Snapshot!C3, "IQ_EPS_EST", IQ_FQ - 2) | I25: =_xll.ciqfunctions.udf.CIQ(Snapshot!C3, "IQ_EPS_EST", IQ_FQ - 1) | J25: =_xll.ciqfunctions.udf.CIQ(Snapshot!C3, "IQ_EPS_EST", IQ_FQ) | K25: TR.EPSMean
A26: revenue_consensus | B26: Revenue estimate (consensus mean) | C26: =_xll.ciqfunctions.udf.CIQ(Snapshot!C3, "IQ_REVENUE_EST", IQ_FQ - 7) | D26: =_xll.ciqfunctions.udf.CIQ(Snapshot!C3, "IQ_REVENUE_EST", IQ_FQ - 6) | E26: =_xll.ciqfunctions.udf.CIQ(Snapshot!C3, "IQ_REVENUE_EST", IQ_FQ - 5) | F26: =_xll.ciqfunctions.udf.CIQ(Snapshot!C3, "IQ_REVENUE_EST", IQ_FQ - 4) | G26: =_xll.ciqfunctions.udf.CIQ(Snapshot!C3, "IQ_REVENUE_EST", IQ_FQ - 3) | H26: =_xll.ciqfunctions.udf.CIQ(Snapshot!C3, "IQ_REVENUE_EST", IQ_FQ - 2) | I26: =_xll.ciqfunctions.udf.CIQ(Snapshot!C3, "IQ_REVENUE_EST", IQ_FQ - 1) | J26: =_xll.ciqfunctions.udf.CIQ(Snapshot!C3, "IQ_REVENUE_EST", IQ_FQ) | K26: TR.RevenueMean
A27: fiscal_year | B27: Fiscal year (labels the column) | C27: =_xll.ciqfunctions.udf.CIQ(Snapshot!C3, "IQ_FISCAL_Y", IQ_FQ - 7) | D27: =_xll.ciqfunctions.udf.CIQ(Snapshot!C3, "IQ_FISCAL_Y", IQ_FQ - 6) | E27: =_xll.ciqfunctions.udf.CIQ(Snapshot!C3, "IQ_FISCAL_Y", IQ_FQ - 5) | F27: =_xll.ciqfunctions.udf.CIQ(Snapshot!C3, "IQ_FISCAL_Y", IQ_FQ - 4) | G27: =_xll.ciqfunctions.udf.CIQ(Snapshot!C3, "IQ_FISCAL_Y", IQ_FQ - 3) | H27: =_xll.ciqfunctions.udf.CIQ(Snapshot!C3, "IQ_FISCAL_Y", IQ_FQ - 2) | I27: =_xll.ciqfunctions.udf.CIQ(Snapshot!C3, "IQ_FISCAL_Y", IQ_FQ - 1) | J27: =_xll.ciqfunctions.udf.CIQ(Snapshot!C3, "IQ_FISCAL_Y", IQ_FQ) | K27: TR.FiscalYear
A28: fiscal_quarter | B28: Fiscal quarter (labels the column) | C28: =_xll.ciqfunctions.udf.CIQ(Snapshot!C3, "IQ_FISCAL_Q", IQ_FQ - 7) | D28: =_xll.ciqfunctions.udf.CIQ(Snapshot!C3, "IQ_FISCAL_Q", IQ_FQ - 6) | E28: =_xll.ciqfunctions.udf.CIQ(Snapshot!C3, "IQ_FISCAL_Q", IQ_FQ - 5) | F28: =_xll.ciqfunctions.udf.CIQ(Snapshot!C3, "IQ_FISCAL_Q", IQ_FQ - 4) | G28: =_xll.ciqfunctions.udf.CIQ(Snapshot!C3, "IQ_FISCAL_Q", IQ_FQ - 3) | H28: =_xll.ciqfunctions.udf.CIQ(Snapshot!C3, "IQ_FISCAL_Q", IQ_FQ - 2) | I28: =_xll.ciqfunctions.udf.CIQ(Snapshot!C3, "IQ_FISCAL_Q", IQ_FQ - 1) | J28: =_xll.ciqfunctions.udf.CIQ(Snapshot!C3, "IQ_FISCAL_Q", IQ_FQ) | K28: TR.FiscalQuarter
A29: period_end | B29: Period end date (names a quarter no fiscal row names) | C29: =_xll.ciqfunctions.udf.CIQ(Snapshot!C3, "IQ_PERIODDATE", IQ_FQ - 7) | D29: =_xll.ciqfunctions.udf.CIQ(Snapshot!C3, "IQ_PERIODDATE", IQ_FQ - 6) | E29: =_xll.ciqfunctions.udf.CIQ(Snapshot!C3, "IQ_PERIODDATE", IQ_FQ - 5) | F29: =_xll.ciqfunctions.udf.CIQ(Snapshot!C3, "IQ_PERIODDATE", IQ_FQ - 4) | G29: =_xll.ciqfunctions.udf.CIQ(Snapshot!C3, "IQ_PERIODDATE", IQ_FQ - 3) | H29: =_xll.ciqfunctions.udf.CIQ(Snapshot!C3, "IQ_PERIODDATE", IQ_FQ - 2) | I29: =_xll.ciqfunctions.udf.CIQ(Snapshot!C3, "IQ_PERIODDATE", IQ_FQ - 1) | J29: =_xll.ciqfunctions.udf.CIQ(Snapshot!C3, "IQ_PERIODDATE", IQ_FQ) | K29: IQ_PERIODDATE

Sheet Valuation
A1: DENNIS — valuation & bear/base/bull
A2: Bear/base/bull exit multiples AUTO-SUGGEST from peer P/E percentiles (yellow, override anytime). WACC + reverse DCF below are fully auto. A loss per share has no bear/base/bull price, and negative free cash flow has no implied growth: those cells stay blank.
A4: Inputs & links
A5: Current price | B5: =Snapshot!D15
A6: LTM EPS | B6: =History!H28
A7: LTM FCF / share | B7: =History!H29
A9: Scenario | B9: Metric | C9: (EPS) | D9: Exit multiple | E9: Implied price | F9: Upside %
A10: Bear | B10: =B6 | C10: EPS | D10: =IFERROR(PERCENTILE(Peers!N5:N54,0.25),"") | E10: =IF(AND(ISNUMBER(B10),N(B10)>0,ISNUMBER(D10)),B10*D10,"") | F10: =IF(ISNUMBER(E10),(E10/$B$5-1)*100,"")
A11: Base | B11: =B6 | C11: EPS | D11: =IFERROR(PERCENTILE(Peers!N5:N54,0.5),"") | E11: =IF(AND(ISNUMBER(B11),N(B11)>0,ISNUMBER(D11)),B11*D11,"") | F11: =IF(ISNUMBER(E11),(E11/$B$5-1)*100,"")
A12: Bull | B12: =B6 | C12: EPS | D12: =IFERROR(PERCENTILE(Peers!N5:N54,0.75),"") | E12: =IF(AND(ISNUMBER(B12),N(B12)>0,ISNUMBER(D12)),B12*D12,"") | F12: =IF(ISNUMBER(E12),(E12/$B$5-1)*100,"")
A14: Swap the metric to FCF/share (=B7) and use a P/FCF multiple for a cash-based valuation.
A16: WACC (auto — CAPM)
A17: Risk-free rate (10Y) | B17: 0.043
A18: Equity risk premium | B18: 0.05
A19: Beta (5y) | B19: =Snapshot!D21
A20: Cost of equity (Ke) | B20: =B17+B19*B18
A21: Pre-tax cost of debt | B21: =B17+0.015
A22: Tax rate | B22: 0.21
A23: After-tax cost of debt | B23: =B21*(1-B22)
A24: Equity value (mkt cap) | B24: =Snapshot!D16
A25: Total debt | B25: =Snapshot!D40
A26: Debt weight | B26: =IFERROR(B25/(B24+B25),0)
A27: Equity weight | B27: =IFERROR(B24/(B24+B25),1)
A28: WACC | B28: =B27*B20+B26*B23
A30: Reverse DCF — growth priced into today's price
A31: Enterprise value (EV) | B31: =Snapshot!D17
A32: FCF base (LTM) | B32: =History!H15
A33: FCF / EV yield | B33: =IF(N(B31)>0,IFERROR(B32/B31,""),"")
A34: Implied growth (WACC − FCF/EV) | B34: =IF(AND(N(B32)>0,ISNUMBER(B33)),B28-B33,"")
A35: Historical FCF CAGR (4y) | B35: =IFERROR(History!I15/100,"")
A36: Revenue CAGR (4y) | B36: =IFERROR(History!I5/100,"")
A37: Priced-for − delivered (FCF) | B37: =IF(AND(ISNUMBER(B34),ISNUMBER(B35)),B34-B35,"")
A38: Read | B38: =IF(OR(NOT(ISNUMBER(B34)),NOT(ISNUMBER(B35))),"",IF(B34>B35,"market prices in MORE growth than history delivered","market prices in LESS growth than history delivered"))
A40: Implied growth sensitivity (WACC ±1%)
A41: WACC −1% | B41: =IF(ISNUMBER(B34),(B28-0.01)-B33,"")
A42: WACC base | B42: =B34
A43: WACC +1% | B43: =IF(ISNUMBER(B34),(B28+0.01)-B33,"")

Sheet ZDdiODliMGYtNjhhNC00OT

Sheet Peers
A1: DENNIS — peers (auto via PEERS(); optional / long-form)
A2: Auto-pulls Refinitiv's peer list for the ticker — no manual RICs. Optional: mainly for long-form context.
A4: Peer (auto) | B4: Price | C4: Market Cap | D4: P/E | E4: EV/EBITDA | F4: P/S | G4: Gross Mgn % | H4: Net Mgn % | I4: FCF Yield % | J4: NetDebt/EBITDA | K4: Rev LTM (now) | L4: Rev LTM (-3Y) | M4: Rev Growth % (3Y CAGR) | N4: cln P/E | O4: cln EV/EBITDA | P4: cln P/S | Q4: cln GrossM | R4: cln NetM | S4: cln FCFY | T4: cln ND/EBITDA | U4: cln RevGrw3Y | W4: Peer (chk) | X4: Fwd P/E | Y4: Fwd PEG | Z4: cln FwdP/E | AA4: cln FwdPEG
A5: =_xll.TR("PEERS("&Snapshot!$B$3&")",_xlfn._LONGTEXT("TR.CommonName;TR.PriceClose;TR.CompanyMarketCap(Scale=6);TR.PE;TR.EVToEBITDA;TR.PriceToSalesPerShare;TR.GrossMargin;TR.NetProfitMargin;TR.FreeOperatingCashFlowExclDividends(Period=LTM,SDate=0D,Curn=USD)/TR.CompanyMarketCap(SDate=0D,Curn=USD)*100/*Free Cas","h Flow Yield*/;TR.NetDebt/TR.EBITDA(Period=LTM)/*Net Debt to EBITDA*/;TR.Revenue(Period=LTM,Scale=6)/*Rev LTM (now)*/;TR.Revenue(Period=LTM-3,Scale=6)/*Rev LTM (-3)*/")) | M5: =IFERROR(((K5/L5)^(1/3)-1)*100,"") | N5: =IF(ISNUMBER(D5),D5,"") | O5: =IF(ISNUMBER(E5),E5,"") | P5: =IF(ISNUMBER(F5),F5,"") | Q5: =IF(ISNUMBER(G5),G5,"") | R5: =IF(ISNUMBER(H5),H5,"") | S5: =IF(ISNUMBER(I5),I5,"") | T5: =IF(ISNUMBER(J5),J5,"") | U5: =IF(ISNUMBER(M5),M5,"") | W5: =_xll.TR("PEERS("&Snapshot!$B$3&")","TR.CommonName;TR.FwdPE;TR.FwdPEG") | Z5: =IF(AND($W5=$A5,ISNUMBER($X5)),$X5,"") | AA5: =IF(AND($W5=$A5,ISNUMBER($Y5)),$Y5,"")
M6: =IFERROR(((K6/L6)^(1/3)-1)*100,"") | N6: =IF(ISNUMBER(D6),D6,"") | O6: =IF(ISNUMBER(E6),E6,"") | P6: =IF(ISNUMBER(F6),F6,"") | Q6: =IF(ISNUMBER(G6),G6,"") | R6: =IF(ISNUMBER(H6),H6,"") | S6: =IF(ISNUMBER(I6),I6,"") | T6: =IF(ISNUMBER(J6),J6,"") | U6: =IF(ISNUMBER(M6),M6,"") | Z6: =IF(AND($W6=$A6,ISNUMBER($X6)),$X6,"") | AA6: =IF(AND($W6=$A6,ISNUMBER($Y6)),$Y6,"")
M7: =IFERROR(((K7/L7)^(1/3)-1)*100,"") | N7: =IF(ISNUMBER(D7),D7,"") | O7: =IF(ISNUMBER(E7),E7,"") | P7: =IF(ISNUMBER(F7),F7,"") | Q7: =IF(ISNUMBER(G7),G7,"") | R7: =IF(ISNUMBER(H7),H7,"") | S7: =IF(ISNUMBER(I7),I7,"") | T7: =IF(ISNUMBER(J7),J7,"") | U7: =IF(ISNUMBER(M7),M7,"") | Z7: =IF(AND($W7=$A7,ISNUMBER($X7)),$X7,"") | AA7: =IF(AND($W7=$A7,ISNUMBER($Y7)),$Y7,"")
M8: =IFERROR(((K8/L8)^(1/3)-1)*100,"") | N8: =IF(ISNUMBER(D8),D8,"") | O8: =IF(ISNUMBER(E8),E8,"") | P8: =IF(ISNUMBER(F8),F8,"") | Q8: =IF(ISNUMBER(G8),G8,"") | R8: =IF(ISNUMBER(H8),H8,"") | S8: =IF(ISNUMBER(I8),I8,"") | T8: =IF(ISNUMBER(J8),J8,"") | U8: =IF(ISNUMBER(M8),M8,"") | Z8: =IF(AND($W8=$A8,ISNUMBER($X8)),$X8,"") | AA8: =IF(AND($W8=$A8,ISNUMBER($Y8)),$Y8,"")
M9: =IFERROR(((K9/L9)^(1/3)-1)*100,"") | N9: =IF(ISNUMBER(D9),D9,"") | O9: =IF(ISNUMBER(E9),E9,"") | P9: =IF(ISNUMBER(F9),F9,"") | Q9: =IF(ISNUMBER(G9),G9,"") | R9: =IF(ISNUMBER(H9),H9,"") | S9: =IF(ISNUMBER(I9),I9,"") | T9: =IF(ISNUMBER(J9),J9,"") | U9: =IF(ISNUMBER(M9),M9,"") | Z9: =IF(AND($W9=$A9,ISNUMBER($X9)),$X9,"") | AA9: =IF(AND($W9=$A9,ISNUMBER($Y9)),$Y9,"")
M10: =IFERROR(((K10/L10)^(1/3)-1)*100,"") | N10: =IF(ISNUMBER(D10),D10,"") | O10: =IF(ISNUMBER(E10),E10,"") | P10: =IF(ISNUMBER(F10),F10,"") | Q10: =IF(ISNUMBER(G10),G10,"") | R10: =IF(ISNUMBER(H10),H10,"") | S10: =IF(ISNUMBER(I10),I10,"") | T10: =IF(ISNUMBER(J10),J10,"") | U10: =IF(ISNUMBER(M10),M10,"") | Z10: =IF(AND($W10=$A10,ISNUMBER($X10)),$X10,"") | AA10: =IF(AND($W10=$A10,ISNUMBER($Y10)),$Y10,"")
M11: =IFERROR(((K11/L11)^(1/3)-1)*100,"") | N11: =IF(ISNUMBER(D11),D11,"") | O11: =IF(ISNUMBER(E11),E11,"") | P11: =IF(ISNUMBER(F11),F11,"") | Q11: =IF(ISNUMBER(G11),G11,"") | R11: =IF(ISNUMBER(H11),H11,"") | S11: =IF(ISNUMBER(I11),I11,"") | T11: =IF(ISNUMBER(J11),J11,"") | U11: =IF(ISNUMBER(M11),M11,"") | Z11: =IF(AND($W11=$A11,ISNUMBER($X11)),$X11,"") | AA11: =IF(AND($W11=$A11,ISNUMBER($Y11)),$Y11,"")
M12: =IFERROR(((K12/L12)^(1/3)-1)*100,"") | N12: =IF(ISNUMBER(D12),D12,"") | O12: =IF(ISNUMBER(E12),E12,"") | P12: =IF(ISNUMBER(F12),F12,"") | Q12: =IF(ISNUMBER(G12),G12,"") | R12: =IF(ISNUMBER(H12),H12,"") | S12: =IF(ISNUMBER(I12),I12,"") | T12: =IF(ISNUMBER(J12),J12,"") | U12: =IF(ISNUMBER(M12),M12,"") | Z12: =IF(AND($W12=$A12,ISNUMBER($X12)),$X12,"") | AA12: =IF(AND($W12=$A12,ISNUMBER($Y12)),$Y12,"")
M13: =IFERROR(((K13/L13)^(1/3)-1)*100,"") | N13: =IF(ISNUMBER(D13),D13,"") | O13: =IF(ISNUMBER(E13),E13,"") | P13: =IF(ISNUMBER(F13),F13,"") | Q13: =IF(ISNUMBER(G13),G13,"") | R13: =IF(ISNUMBER(H13),H13,"") | S13: =IF(ISNUMBER(I13),I13,"") | T13: =IF(ISNUMBER(J13),J13,"") | U13: =IF(ISNUMBER(M13),M13,"") | Z13: =IF(AND($W13=$A13,ISNUMBER($X13)),$X13,"") | AA13: =IF(AND($W13=$A13,ISNUMBER($Y13)),$Y13,"")
M14: =IFERROR(((K14/L14)^(1/3)-1)*100,"") | N14: =IF(ISNUMBER(D14),D14,"") | O14: =IF(ISNUMBER(E14),E14,"") | P14: =IF(ISNUMBER(F14),F14,"") | Q14: =IF(ISNUMBER(G14),G14,"") | R14: =IF(ISNUMBER(H14),H14,"") | S14: =IF(ISNUMBER(I14),I14,"") | T14: =IF(ISNUMBER(J14),J14,"") | U14: =IF(ISNUMBER(M14),M14,"") | Z14: =IF(AND($W14=$A14,ISNUMBER($X14)),$X14,"") | AA14: =IF(AND($W14=$A14,ISNUMBER($Y14)),$Y14,"")
M15: =IFERROR(((K15/L15)^(1/3)-1)*100,"") | N15: =IF(ISNUMBER(D15),D15,"") | O15: =IF(ISNUMBER(E15),E15,"") | P15: =IF(ISNUMBER(F15),F15,"") | Q15: =IF(ISNUMBER(G15),G15,"") | R15: =IF(ISNUMBER(H15),H15,"") | S15: =IF(ISNUMBER(I15),I15,"") | T15: =IF(ISNUMBER(J15),J15,"") | U15: =IF(ISNUMBER(M15),M15,"") | Z15: =IF(AND($W15=$A15,ISNUMBER($X15)),$X15,"") | AA15: =IF(AND($W15=$A15,ISNUMBER($Y15)),$Y15,"")
M16: =IFERROR(((K16/L16)^(1/3)-1)*100,"") | N16: =IF(ISNUMBER(D16),D16,"") | O16: =IF(ISNUMBER(E16),E16,"") | P16: =IF(ISNUMBER(F16),F16,"") | Q16: =IF(ISNUMBER(G16),G16,"") | R16: =IF(ISNUMBER(H16),H16,"") | S16: =IF(ISNUMBER(I16),I16,"") | T16: =IF(ISNUMBER(J16),J16,"") | U16: =IF(ISNUMBER(M16),M16,"") | Z16: =IF(AND($W16=$A16,ISNUMBER($X16)),$X16,"") | AA16: =IF(AND($W16=$A16,ISNUMBER($Y16)),$Y16,"")
M17: =IFERROR(((K17/L17)^(1/3)-1)*100,"") | N17: =IF(ISNUMBER(D17),D17,"") | O17: =IF(ISNUMBER(E17),E17,"") | P17: =IF(ISNUMBER(F17),F17,"") | Q17: =IF(ISNUMBER(G17),G17,"") | R17: =IF(ISNUMBER(H17),H17,"") | S17: =IF(ISNUMBER(I17),I17,"") | T17: =IF(ISNUMBER(J17),J17,"") | U17: =IF(ISNUMBER(M17),M17,"") | Z17: =IF(AND($W17=$A17,ISNUMBER($X17)),$X17,"") | AA17: =IF(AND($W17=$A17,ISNUMBER($Y17)),$Y17,"")
... M54: =IFERROR(((K54/L54)^(1/3)-1)*100,"") | N54: =IF(ISNUMBER(D54),D54,"") | O54: =IF(ISNUMBER(E54),E54,"") | P54: =IF(ISNUMBER(F54),F54,"") | Q54: =IF(ISNUMBER(G54),G54,"") | R54: =IF(ISNUMBER(H54),H54,"") | S54: =IF(ISNUMBER(I54),I54,"") | T54: =IF(ISNUMBER(J54),J54,"") | U54: =IF(ISNUMBER(M54),M54,"") | Z54: =IF(AND($W54=$A54,ISNUMBER($X54)),$X54,"") | AA54: =IF(AND($W54=$A54,ISNUMBER($Y54)),$Y54,"")
M55: subj-> | N55: =Snapshot!D25 | O55: =Snapshot!D28 | P55: =Snapshot!D27 | Q55: =History!H7 | R55: =History!H12 | S55: =Snapshot!D35*100 | T55: =Snapshot!D42 | U55: =IFERROR(((History!G5/History!D5)^(1/3)-1)*100,"") | Z55: =Snapshot!D26 | AA55: =Snapshot!D33
A57: DENNIS — self-scoring vs peers (percentile of THIS ticker in each peer column)
A58: PERCENTRANK.INC of the subject value within the cleaned peer columns above. 'Read' bakes in direction so a glance tells you cheap/expensive and strong/weak.
A59: Metric | B59: Subject | C59: Peer median | D59: Percentile | E59: Higher is | F59: Read | G59: Peer low (p10) | H59: Peer high (p90) | I59: t (subject) | J59: t (median)
A60: P/E (TTM) | B60: =Snapshot!D25 | C60: =IFERROR(MEDIAN(N5:N54),"") | D60: =IFERROR(_xlfn.PERCENTRANK.INC(N5:N55,B60),"") | E60: worse (expensive/levered) | F60: =IF(D60="","",IF(D60>=0.8,"expensive vs peers",IF(D60<=0.2,"cheap vs peers","mid-pack"))) | G60: =IFERROR(_xlfn.PERCENTILE.INC(N5:N54,0.1),"") | H60: =IFERROR(_xlfn.PERCENTILE.INC(N5:N54,0.9),"") | I60: =IF(OR($G60="",$H60="",$H60=$G60,$B60=""),"",($B60-$G60)/($H60-$G60)) | J60: =IF(OR($G60="",$H60="",$H60=$G60,$C60=""),"",($C60-$G60)/($H60-$G60))
A61: EV/EBITDA | B61: =Snapshot!D28 | C61: =IFERROR(MEDIAN(O5:O54),"") | D61: =IFERROR(_xlfn.PERCENTRANK.INC(O5:O55,B61),"") | E61: worse (expensive/levered) | F61: =IF(D61="","",IF(D61>=0.8,"expensive vs peers",IF(D61<=0.2,"cheap vs peers","mid-pack"))) | G61: =IFERROR(_xlfn.PERCENTILE.INC(O5:O54,0.1),"") | H61: =IFERROR(_xlfn.PERCENTILE.INC(O5:O54,0.9),"") | I61: =IF(OR($G61="",$H61="",$H61=$G61,$B61=""),"",($B61-$G61)/($H61-$G61)) | J61: =IF(OR($G61="",$H61="",$H61=$G61,$C61=""),"",($C61-$G61)/($H61-$G61))
A62: P/S (TTM) | B62: =Snapshot!D27 | C62: =IFERROR(MEDIAN(P5:P54),"") | D62: =IFERROR(_xlfn.PERCENTRANK.INC(P5:P55,B62),"") | E62: worse (expensive/levered) | F62: =IF(D62="","",IF(D62>=0.8,"expensive vs peers",IF(D62<=0.2,"cheap vs peers","mid-pack"))) | G62: =IFERROR(_xlfn.PERCENTILE.INC(P5:P54,0.1),"") | H62: =IFERROR(_xlfn.PERCENTILE.INC(P5:P54,0.9),"") | I62: =IF(OR($G62="",$H62="",$H62=$G62,$B62=""),"",($B62-$G62)/($H62-$G62)) | J62: =IF(OR($G62="",$H62="",$H62=$G62,$C62=""),"",($C62-$G62)/($H62-$G62))
A63: Rev growth % (3Y CAGR) | B63: =IFERROR(((History!G5/History!D5)^(1/3)-1)*100,"") | C63: =IFERROR(MEDIAN(U5:U54),"") | D63: =IFERROR(_xlfn.PERCENTRANK.INC(U5:U55,B63),"") | E63: better | F63: =IF(D63="","",IF(D63>=0.8,"strong vs peers",IF(D63<=0.2,"weak vs peers","mid-pack"))) | G63: =IFERROR(_xlfn.PERCENTILE.INC(U5:U54,0.1),"") | H63: =IFERROR(_xlfn.PERCENTILE.INC(U5:U54,0.9),"") | I63: =IF(OR($G63="",$H63="",$H63=$G63,$B63=""),"",($B63-$G63)/($H63-$G63)) | J63: =IF(OR($G63="",$H63="",$H63=$G63,$C63=""),"",($C63-$G63)/($H63-$G63))
A64: Gross margin % | B64: =History!H7 | C64: =IFERROR(MEDIAN(Q5:Q54),"") | D64: =IFERROR(_xlfn.PERCENTRANK.INC(Q5:Q55,B64),"") | E64: better | F64: =IF(D64="","",IF(D64>=0.8,"strong vs peers",IF(D64<=0.2,"weak vs peers","mid-pack"))) | G64: =IFERROR(_xlfn.PERCENTILE.INC(Q5:Q54,0.1),"") | H64: =IFERROR(_xlfn.PERCENTILE.INC(Q5:Q54,0.9),"") | I64: =IF(OR($G64="",$H64="",$H64=$G64,$B64=""),"",($B64-$G64)/($H64-$G64)) | J64: =IF(OR($G64="",$H64="",$H64=$G64,$C64=""),"",($C64-$G64)/($H64-$G64))
A65: Net margin % | B65: =History!H12 | C65: =IFERROR(MEDIAN(R5:R54),"") | D65: =IFERROR(_xlfn.PERCENTRANK.INC(R5:R55,B65),"") | E65: better | F65: =IF(D65="","",IF(D65>=0.8,"strong vs peers",IF(D65<=0.2,"weak vs peers","mid-pack"))) | G65: =IFERROR(_xlfn.PERCENTILE.INC(R5:R54,0.1),"") | H65: =IFERROR(_xlfn.PERCENTILE.INC(R5:R54,0.9),"") | I65: =IF(OR($G65="",$H65="",$H65=$G65,$B65=""),"",($B65-$G65)/($H65-$G65)) | J65: =IF(OR($G65="",$H65="",$H65=$G65,$C65=""),"",($C65-$G65)/($H65-$G65))
A66: FCF yield % | B66: =Snapshot!D35*100 | C66: =IFERROR(MEDIAN(S5:S54),"") | D66: =IFERROR(_xlfn.PERCENTRANK.INC(S5:S55,B66),"") | E66: better | F66: =IF(D66="","",IF(D66>=0.8,"strong vs peers",IF(D66<=0.2,"weak vs peers","mid-pack"))) | G66: =IFERROR(_xlfn.PERCENTILE.INC(S5:S54,0.1),"") | H66: =IFERROR(_xlfn.PERCENTILE.INC(S5:S54,0.9),"") | I66: =IF(OR($G66="",$H66="",$H66=$G66,$B66=""),"",($B66-$G66)/($H66-$G66)) | J66: =IF(OR($G66="",$H66="",$H66=$G66,$C66=""),"",($C66-$G66)/($H66-$G66))
A67: Net debt / EBITDA | B67: =Snapshot!D42 | C67: =IFERROR(MEDIAN(T5:T54),"") | D67: =IFERROR(_xlfn.PERCENTRANK.INC(T5:T55,B67),"") | E67: worse (expensive/levered) | F67: =IF(D67="","",IF(D67>=0.8,"expensive vs peers",IF(D67<=0.2,"cheap vs peers","mid-pack"))) | G67: =IFERROR(_xlfn.PERCENTILE.INC(T5:T54,0.1),"") | H67: =IFERROR(_xlfn.PERCENTILE.INC(T5:T54,0.9),"") | I67: =IF(OR($G67="",$H67="",$H67=$G67,$B67=""),"",($B67-$G67)/($H67-$G67)) | J67: =IF(OR($G67="",$H67="",$H67=$G67,$C67=""),"",($C67-$G67)/($H67-$G67))
A68: Forward P/E | B68: =Snapshot!D26 | C68: =IFERROR(MEDIAN(Z5:Z54),"") | D68: =IFERROR(_xlfn.PERCENTRANK.INC(Z5:Z55,B68),"") | E68: worse (expensive/levered) | F68: =IF(D68="","",IF(D68>=0.8,"expensive vs peers",IF(D68<=0.2,"cheap vs peers","mid-pack"))) | G68: =IFERROR(_xlfn.PERCENTILE.INC(Z5:Z54,0.1),"") | H68: =IFERROR(_xlfn.PERCENTILE.INC(Z5:Z54,0.9),"") | I68: =IF(OR($G68="",$H68="",$H68=$G68,$B68=""),"",($B68-$G68)/($H68-$G68)) | J68: =IF(OR($G68="",$H68="",$H68=$G68,$C68=""),"",($C68-$G68)/($H68-$G68))
A69: Forward PEG | B69: =Snapshot!D33 | C69: =IFERROR(MEDIAN(AA5:AA54),"") | D69: =IFERROR(_xlfn.PERCENTRANK.INC(AA5:AA55,B69),"") | E69: worse (expensive/levered) | F69: =IF(D69="","",IF(D69>=0.8,"expensive vs peers",IF(D69<=0.2,"cheap vs peers","mid-pack"))) | G69: =IFERROR(_xlfn.PERCENTILE.INC(AA5:AA54,0.1),"") | H69: =IFERROR(_xlfn.PERCENTILE.INC(AA5:AA54,0.9),"") | I69: =IF(OR($G69="",$H69="",$H69=$G69,$B69=""),"",($B69-$G69)/($H69-$G69)) | J69: =IF(OR($G69="",$H69="",$H69=$G69,$C69=""),"",($C69-$G69)/($H69-$G69))
A72: PEG (fwd)
A73: Forward P/E and PEG for peers come from a SECOND PEERS() call in W5 (TR.FwdPE; TR.FwdPEG) so nothing above it had to move. The cln columns Z/AA only take a value when W matches the name in A, so if the two calls ever return different orders the percentile blanks instead of mislabelling. If the add-in rejects a mnemonic, swap TR.FwdPE for TR.PE(Period=FY1) in W5; if TR.FwdPEG comes back empty the PEG row just stays blank, which is the intended degradation.
A75: G:J feed tables/multiples-strip. The plate's rail is a VALUE axis, not a rank axis: series.rangeMark takes t (the subject's position along the rail, 0 at the low end and 1 at the high) and median on that same scale. Column D percentile cannot serve as t — it is rank-based, so the median would compute to 0.5 on every row and every median tick would sit dead centre, which is both wrong and the one thing on the plate worth looking at.
A76: The rail ends are the 10th and 90th percentile of the peer column, NOT min and max. One peer on a 900x P/E would otherwise own the whole axis and squash every subject to t=0.02. A subject outside p10-p90 gives t<0 or t>1, which is a real reading and the most quotable row on the plate — the renderer clamps the dot to the end tick and adds a chevron past it. Do not clamp t here.
A77: Column E ('Higher is better/worse') is for the CAPTION, not the rail. The rail is not inverted for expensive-is-bad metrics and nothing on the plate is drawn in up or down: cheap is not up.

Sheet News
A1: DENNIS — recent news & key developments (auto; Capital IQ)
A2: Capital IQ IQ_NEWS — latest headlines (Date / Headline / Source / URL). Each column spills down from row 6 when the add-in refreshes. Feeds the /headline shorts flow.
A3: Ticker → | B3: =Snapshot!C3
A5: Date | B5: Headline | C5: Source | D5: URL | F5: Pattern: CIQRANGE(ticker, "IQ_NEWS", 1, N, , , , , "<data item>") — items: News Headline/Date/Source/URL/Time
A6: =_xll.ciqfunctions.udf.CIQRANGE(Snapshot!C3,"IQ_NEWS",1,25,,,,,"News Date") | B6: =_xll.ciqfunctions.udf.CIQRANGE(Snapshot!C3,"IQ_NEWS",1,25,,,,,"News Headline") | C6: =_xll.ciqfunctions.udf.CIQRANGE(Snapshot!C3,"IQ_NEWS",1,25,,,,,"News Source") | D6: =_xll.ciqfunctions.udf.CIQRANGE(Snapshot!C3,"IQ_NEWS",1,25,,,,,"News URL")

Sheet Dashboard
A1: DENNIS — one-glance summary (feeds the numbers sheet)
A2: Auto from the other sheets. Flags are rough heuristics, and blank when the figure behind them is.
A4: Company | B4: =Snapshot!D7
A5: Price | B5: =Snapshot!D15
A6: Market cap | B6: =Snapshot!D16
A7: % from 52w high | B7: =Snapshot!D24
A8: Revenue (LTM) | B8: =History!H5
A9: Revenue 4y CAGR | B9: =History!I5
A10: Gross margin (LTM) | B10: =History!H7
A11: Operating margin (LTM) | B11: =History!H9
A12: Net margin (LTM) | B12: =History!H12
A13: FCF (LTM) | B13: =History!H15
A14: FCF margin (LTM) | B14: =History!H16
A15: FCF yield | B15: =Snapshot!D35
A16: Net debt / EBITDA | B16: =Snapshot!D42
A17: ROIC (LTM) | B17: =History!H31
A18: Share count 4y CAGR | B18: =History!I33
A19: P/E (TTM) | B19: =Snapshot!D25
A20: EV/EBITDA | B20: =Snapshot!D28
A22: Quick flags
A23: Profitable? (LTM NI>0) | B23: =IF(ISNUMBER(History!H11),IF(History!H11>0,"yes","no"),"")
A24: FCF positive? (LTM) | B24: =IF(ISNUMBER(History!H15),IF(History!H15>0,"yes","no"),"")
A25: Growing? (rev CAGR>0) | B25: =IF(ISNUMBER(History!I5),IF(History!I5>0,"yes","no"),"")
A26: Diluting? (share CAGR>1%) | B26: =IF(ISNUMBER(History!I33),IF(History!I33>1,"yes","no"),"")
A27: Over-levered? (ND/EBITDA>3x) | B27: =IF(ISNUMBER(Snapshot!D42),IF(Snapshot!D42>3,"yes","no"),IF(AND(ISNUMBER(History!H10),N(History!H10)<=0,N(Snapshot!D41)>0),"yes",""))

Sheet Instructions
A1: DENNIS — data template v3.2
A3: How to fill it
A4: 1. Type the ticker into Snapshot!C3 (plain ticker, e.g. BA). Everything else follows it.
A5: 2. Excel needs the Capital IQ plug-in signed in. The Peers sheet also uses the LSEG (Refinitiv) add-in;
A6: without it Peers stays empty and the video simply has no peer comparison.
A7: 3. Refresh (Capital IQ ▸ Refresh Workbook) and wait until no cell says 'Requesting data'.
A8: 4. Save, and upload the file on the bot's page for that video (it is saved as dennis_data.xlsx).
A10: What the bot reads
A11: Snapshot, History, Quarters, Valuation, Peers, News and Dashboard, each by name. Don't rename
A12: sheets or the field_key cells in column A/B. Figures are in millions where the column says MM.
A13: The quarter columns are named from Quarters rows 27-29 (fiscal year, fiscal quarter, period end).
A14: If all three fail, the bot calls the columns 'the latest quarter', 'the prior quarter' and so on.
... A24: On screen the videos never name the data vendor.

Sheet _RICMap
A1: keyword (found in Capital IQ exchange name) | B1: RIC suffix | D1: derived suffix | E1: =IFERROR(LOOKUP(2,1/ISNUMBER(SEARCH($A$2:$A$43,Snapshot!$D$9)),$B$2:$B$43),".O")
A2: New York | B2: .N
A3: NYSE | B3: .N
A4: Nasdaq | B4: .O
A5: London | B5: .L
A6: Toronto | B6: .TO
A7: Australian | B7: .AX
A8: ASX | B8: .AX
A9: Hong Kong | B9: .HK
A10: Tokyo | B10: .T
A11: Frankfurt | B11: .F
A12: Xetra | B12: .DE
A13: Deutsche | B13: .DE
... A43: Venture | B43: .V
